Workbook

Sheet Project
A1: Contributor | B1: Project ID | C1: List of contributors | D1: Description | E1: BRA version
E2: Template-v2-2.bra
A4: Sheet Name | B4: Review End Line
A5: References
A6: Circuits
A7: Connections
A8: FRG
B9: Note: fill in "1" if you do not register any data

Sheet References
A1: =IFERROR(__xludf.DUMMYFUNCTION("IMPORTRANGE(Settings!$A$2,""wbReferences!A1:W1"")"),"Reference ID") -> Reference ID | B1: =IFERROR(__xludf.DUMMYFUNCTION("""COMPUTED_VALUE"""),"Doc. Link") -> Doc. Link | C1: =IFERROR(__xludf.DUMMYFUNCTION("""COMPUTED_VALUE"""),"BibTex link") -> BibTex link | D1: =IFERROR(__xludf.DUMMYFUNCTION("""COMPUTED_VALUE"""),"DOI") -> DOI | E1: =IFERROR(__xludf.DUMMYFUNCTION("""COMPUTED_VALUE"""),"BibTex ") -> BibTex | F1: =IFERROR(__xludf.DUMMYFUNCTION("""COMPUTED_VALUE"""),"Litterature type") -> Litterature type | G1: =IFERROR(__xludf.DUMMYFUNCTION("""COMPUTED_VALUE"""),"Type") -> Type | H1: =IFERROR(__xludf.DUMMYFUNCTION("""COMPUTED_VALUE"""),"Authors") -> Authors | I1: =IFERROR(__xludf.DUMMYFUNCTION("""COMPUTED_VALUE"""),"Title") -> Title | J1: =IFERROR(__xludf.DUMMYFUNCTION("""COMPUTED_VALUE"""),"Journal names") -> Journal names | K1: =IFERROR(__xludf.DUMMYFUNCTION("""COMPUTED_VALUE"""),"Alternative URL") -> Alternative URL | L1: =IFERROR(__xludf.DUMMYFUNCTION("""COMPUTED_VALUE"""),"Contributor") -> Contributor | M1: =IFERROR(__xludf.DUMMYFUNCTION("""COMPUTED_VALUE"""),"Project ID") -> Project ID | N1: =IFERROR(__xludf.DUMMYFUNCTION("""COMPUTED_VALUE"""),"WBIF pull request") -> WBIF pull request | O1: =IFERROR(__xludf.DUMMYFUNCTION("""COMPUTED_VALUE"""),"WBIF copied") -> WBIF copied | P1: =IFERROR(__xludf.DUMMYFUNCTION("""COMPUTED_VALUE"""),"Review results") -> Review results | Q1: =IFERROR(__xludf.DUMMYFUNCTION("""COMPUTED_VALUE"""),"Auto Error Codes") -> Auto Error Codes | R1: =IFERROR(__xludf.DUMMYFUNCTION("""COMPUTED_VALUE"""),"Error Code-1") -> Error Code-1 | S1: =IFERROR(__xludf.DUMMYFUNCTION("""COMPUTED_VALUE"""),"Error Code-2") -> Error Code-2 | T1: =IFERROR(__xludf.DUMMYFUNCTION("""COMPUTED_VALUE"""),"Other Error Codes") -> Other Error Codes | U1: =IFERROR(__xludf.DUMMYFUNCTION("""COMPUTED_VALUE"""),"Review comments") -> Review comments | V1: =IFERROR(__xludf.DUMMYFUNCTION("""COMPUTED_VALUE"""),"Reviewer") -> Reviewer | W1: =IFERROR(__xludf.DUMMYFUNCTION("""COMPUTED_VALUE"""),"Reviewed date") -> Reviewed date
A2: =IFERROR(__xludf.DUMMYFUNCTION("IF(ISBLANK(E2), ""(no BibTex)"", CONCATENATE(REGEXEXTRACT(SUBSTITUTE($E2, ""_"", """"),""@.+{(.+)\d{4}""),"", "",REGEXEXTRACT($E2,""@.+{.+(\d{4}.*),"")))"),"(no BibTex)") -> (no BibTex) | B2: =IF(ISBLANK(D2),IF(ISBLANK(K2),"-",HYPERLINK(K2,"DOC(alt)")), HYPERLINK(CONCAT("https://www.doi.org/",D2),"DOC")) -> - | C2: =IF(ISBLANK(D2),"(no DOI)", HYPERLINK(CONCAT("https://www.doi2bib.org/bib/",D2),"BIB")) -> (no DOI) | G2: =IFERROR(__xludf.DUMMYFUNCTION("IF(ISBLANK(E2),""(no BibTex)"",PROPER(REGEXEXTRACT($E2,""@(.+){"")))"),"(no BibTex)") -> (no BibTex) | H2: =IFERROR(__xludf.DUMMYFUNCTION("IF(ISBLANK(E2),""(no BibTex)"",SUBSTITUTE(IFNA(REGEXEXTRACT($E2,""author += +{(.+)}""),REGEXEXTRACT($E2,""editor *= *{(.+)}"")),"" and"", "",""))"),"(no BibTex)") -> (no BibTex) | I2: =IFERROR(__xludf.DUMMYFUNCTION("IF(ISBLANK(E2),""(no BibTex)"",REGEXEXTRACT($E2,""title *= *{(.+)}""))"),"(no BibTex)") -> (no BibTex) | J2: =IFERROR(__xludf.DUMMYFUNCTION("IFNA(IFNA(REGEXEXTRACT($E2,""journal *= *{(.+)}""), REGEXEXTRACT($E2,""booktitle *= *{(.+)}"")), ""-"")"),"-") -> -
A3: =IFERROR(__xludf.DUMMYFUNCTION("IF(ISBLANK(E3), ""(no BibTex)"", CONCATENATE(REGEXEXTRACT(SUBSTITUTE($E3, ""_"", """"),""@.+{(.+)\d{4}""),"", "",REGEXEXTRACT($E3,""@.+{.+(\d{4}.*),"")))"),"(no BibTex)") -> (no BibTex) | B3: =IF(ISBLANK(D3),IF(ISBLANK(K3),"-",HYPERLINK(K3,"DOC(alt)")), HYPERLINK(CONCAT("https://www.doi.org/",D3),"DOC")) -> - | C3: =IF(ISBLANK(D3),"(no DOI)", HYPERLINK(CONCAT("https://www.doi2bib.org/bib/",D3),"BIB")) -> (no DOI) | G3: =IFERROR(__xludf.DUMMYFUNCTION("IF(ISBLANK(E3),""(no BibTex)"",PROPER(REGEXEXTRACT($E3,""@(.+){"")))"),"(no BibTex)") -> (no BibTex) | H3: =IFERROR(__xludf.DUMMYFUNCTION("IF(ISBLANK(E3),""(no BibTex)"",SUBSTITUTE(IFNA(REGEXEXTRACT($E3,""author += +{(.+)}""),REGEXEXTRACT($E3,""editor *= *{(.+)}"")),"" and"", "",""))"),"(no BibTex)") -> (no BibTex) | I3: =IFERROR(__xludf.DUMMYFUNCTION("IF(ISBLANK(E3),""(no BibTex)"",REGEXEXTRACT($E3,""title *= *{(.+)}""))"),"(no BibTex)") -> (no BibTex) | J3: =IFERROR(__xludf.DUMMYFUNCTION("IFNA(IFNA(REGEXEXTRACT($E3,""journal *= *{(.+)}""), REGEXEXTRACT($E3,""booktitle *= *{(.+)}"")), ""-"")"),"-") -> -
A4: =IFERROR(__xludf.DUMMYFUNCTION("IF(ISBLANK(E4), ""(no BibTex)"", CONCATENATE(REGEXEXTRACT(SUBSTITUTE($E4, ""_"", """"),""@.+{(.+)\d{4}""),"", "",REGEXEXTRACT($E4,""@.+{.+(\d{4}.*),"")))"),"(no BibTex)") -> (no BibTex) | B4: =IF(ISBLANK(D4),IF(ISBLANK(K4),"-",HYPERLINK(K4,"DOC(alt)")), HYPERLINK(CONCAT("https://www.doi.org/",D4),"DOC")) -> - | C4: =IF(ISBLANK(D4),"(no DOI)", HYPERLINK(CONCAT("https://www.doi2bib.org/bib/",D4),"BIB")) -> (no DOI) | G4: =IFERROR(__xludf.DUMMYFUNCTION("IF(ISBLANK(E4),""(no BibTex)"",PROPER(REGEXEXTRACT($E4,""@(.+){"")))"),"(no BibTex)") -> (no BibTex) | H4: =IFERROR(__xludf.DUMMYFUNCTION("IF(ISBLANK(E4),""(no BibTex)"",SUBSTITUTE(IFNA(REGEXEXTRACT($E4,""author += +{(.+)}""),REGEXEXTRACT($E4,""editor *= *{(.+)}"")),"" and"", "",""))"),"(no BibTex)") -> (no BibTex) | I4: =IFERROR(__xludf.DUMMYFUNCTION("IF(ISBLANK(E4),""(no BibTex)"",REGEXEXTRACT($E4,""title *= *{(.+)}""))"),"(no BibTex)") -> (no BibTex) | J4: =IFERROR(__xludf.DUMMYFUNCTION("IFNA(IFNA(REGEXEXTRACT($E4,""journal *= *{(.+)}""), REGEXEXTRACT($E4,""booktitle *= *{(.+)}"")), ""-"")"),"-") -> -
A5: =IFERROR(__xludf.DUMMYFUNCTION("IF(ISBLANK(E5), ""(no BibTex)"", CONCATENATE(REGEXEXTRACT(SUBSTITUTE($E5, ""_"", """"),""@.+{(.+)\d{4}""),"", "",REGEXEXTRACT($E5,""@.+{.+(\d{4}.*),"")))"),"(no BibTex)") -> (no BibTex) | B5: =IF(ISBLANK(D5),IF(ISBLANK(K5),"-",HYPERLINK(K5,"DOC(alt)")), HYPERLINK(CONCAT("https://www.doi.org/",D5),"DOC")) -> - | C5: =IF(ISBLANK(D5),"(no DOI)", HYPERLINK(CONCAT("https://www.doi2bib.org/bib/",D5),"BIB")) -> (no DOI) | G5: =IFERROR(__xludf.DUMMYFUNCTION("IF(ISBLANK(E5),""(no BibTex)"",PROPER(REGEXEXTRACT($E5,""@(.+){"")))"),"(no BibTex)") -> (no BibTex) | H5: =IFERROR(__xludf.DUMMYFUNCTION("IF(ISBLANK(E5),""(no BibTex)"",SUBSTITUTE(IFNA(REGEXEXTRACT($E5,""author += +{(.+)}""),REGEXEXTRACT($E5,""editor *= *{(.+)}"")),"" and"", "",""))"),"(no BibTex)") -> (no BibTex) | I5: =IFERROR(__xludf.DUMMYFUNCTION("IF(ISBLANK(E5),""(no BibTex)"",REGEXEXTRACT($E5,""title *= *{(.+)}""))"),"(no BibTex)") -> (no BibTex) | J5: =IFERROR(__xludf.DUMMYFUNCTION("IFNA(IFNA(REGEXEXTRACT($E5,""journal *= *{(.+)}""), REGEXEXTRACT($E5,""booktitle *= *{(.+)}"")), ""-"")"),"-") -> -
A6: =IFERROR(__xludf.DUMMYFUNCTION("IF(ISBLANK(E6), ""(no BibTex)"", CONCATENATE(REGEXEXTRACT(SUBSTITUTE($E6, ""_"", """"),""@.+{(.+)\d{4}""),"", "",REGEXEXTRACT($E6,""@.+{.+(\d{4}.*),"")))"),"(no BibTex)") -> (no BibTex) | B6: =IF(ISBLANK(D6),IF(ISBLANK(K6),"-",HYPERLINK(K6,"DOC(alt)")), HYPERLINK(CONCAT("https://www.doi.org/",D6),"DOC")) -> - | C6: =IF(ISBLANK(D6),"(no DOI)", HYPERLINK(CONCAT("https://www.doi2bib.org/bib/",D6),"BIB")) -> (no DOI) | G6: =IFERROR(__xludf.DUMMYFUNCTION("IF(ISBLANK(E6),""(no BibTex)"",PROPER(REGEXEXTRACT($E6,""@(.+){"")))"),"(no BibTex)") -> (no BibTex) | H6: =IFERROR(__xludf.DUMMYFUNCTION("IF(ISBLANK(E6),""(no BibTex)"",SUBSTITUTE(IFNA(REGEXEXTRACT($E6,""author += +{(.+)}""),REGEXEXTRACT($E6,""editor *= *{(.+)}"")),"" and"", "",""))"),"(no BibTex)") -> (no BibTex) | I6: =IFERROR(__xludf.DUMMYFUNCTION("IF(ISBLANK(E6),""(no BibTex)"",REGEXEXTRACT($E6,""title *= *{(.+)}""))"),"(no BibTex)") -> (no BibTex) | J6: =IFERROR(__xludf.DUMMYFUNCTION("IFNA(IFNA(REGEXEXTRACT($E6,""journal *= *{(.+)}""), REGEXEXTRACT($E6,""booktitle *= *{(.+)}"")), ""-"")"),"-") -> -
A7: =IFERROR(__xludf.DUMMYFUNCTION("IF(ISBLANK(E7), ""(no BibTex)"", CONCATENATE(REGEXEXTRACT(SUBSTITUTE($E7, ""_"", """"),""@.+{(.+)\d{4}""),"", "",REGEXEXTRACT($E7,""@.+{.+(\d{4}.*),"")))"),"(no BibTex)") -> (no BibTex) | B7: =IF(ISBLANK(D7),IF(ISBLANK(K7),"-",HYPERLINK(K7,"DOC(alt)")), HYPERLINK(CONCAT("https://www.doi.org/",D7),"DOC")) -> - | C7: =IF(ISBLANK(D7),"(no DOI)", HYPERLINK(CONCAT("https://www.doi2bib.org/bib/",D7),"BIB")) -> (no DOI) | G7: =IFERROR(__xludf.DUMMYFUNCTION("IF(ISBLANK(E7),""(no BibTex)"",PROPER(REGEXEXTRACT($E7,""@(.+){"")))"),"(no BibTex)") -> (no BibTex) | H7: =IFERROR(__xludf.DUMMYFUNCTION("IF(ISBLANK(E7),""(no BibTex)"",SUBSTITUTE(IFNA(REGEXEXTRACT($E7,""author += +{(.+)}""),REGEXEXTRACT($E7,""editor *= *{(.+)}"")),"" and"", "",""))"),"(no BibTex)") -> (no BibTex) | I7: =IFERROR(__xludf.DUMMYFUNCTION("IF(ISBLANK(E7),""(no BibTex)"",REGEXEXTRACT($E7,""title *= *{(.+)}""))"),"(no BibTex)") -> (no BibTex) | J7: =IFERROR(__xludf.DUMMYFUNCTION("IFNA(IFNA(REGEXEXTRACT($E7,""journal *= *{(.+)}""), REGEXEXTRACT($E7,""booktitle *= *{(.+)}"")), ""-"")"),"-") -> -
A8: =IFERROR(__xludf.DUMMYFUNCTION("IF(ISBLANK(E8), ""(no BibTex)"", CONCATENATE(REGEXEXTRACT(SUBSTITUTE($E8, ""_"", """"),""@.+{(.+)\d{4}""),"", "",REGEXEXTRACT($E8,""@.+{.+(\d{4}.*),"")))"),"(no BibTex)") -> (no BibTex) | B8: =IF(ISBLANK(D8),IF(ISBLANK(K8),"-",HYPERLINK(K8,"DOC(alt)")), HYPERLINK(CONCAT("https://www.doi.org/",D8),"DOC")) -> - | C8: =IF(ISBLANK(D8),"(no DOI)", HYPERLINK(CONCAT("https://www.doi2bib.org/bib/",D8),"BIB")) -> (no DOI) | G8: =IFERROR(__xludf.DUMMYFUNCTION("IF(ISBLANK(E8),""(no BibTex)"",PROPER(REGEXEXTRACT($E8,""@(.+){"")))"),"(no BibTex)") -> (no BibTex) | H8: =IFERROR(__xludf.DUMMYFUNCTION("IF(ISBLANK(E8),""(no BibTex)"",SUBSTITUTE(IFNA(REGEXEXTRACT($E8,""author += +{(.+)}""),REGEXEXTRACT($E8,""editor *= *{(.+)}"")),"" and"", "",""))"),"(no BibTex)") -> (no BibTex) | I8: =IFERROR(__xludf.DUMMYFUNCTION("IF(ISBLANK(E8),""(no BibTex)"",REGEXEXTRACT($E8,""title *= *{(.+)}""))"),"(no BibTex)") -> (no BibTex) | J8: =IFERROR(__xludf.DUMMYFUNCTION("IFNA(IFNA(REGEXEXTRACT($E8,""journal *= *{(.+)}""), REGEXEXTRACT($E8,""booktitle *= *{(.+)}"")), ""-"")"),"-") -> -
A9: =IFERROR(__xludf.DUMMYFUNCTION("IF(ISBLANK(E9), ""(no BibTex)"", CONCATENATE(REGEXEXTRACT(SUBSTITUTE($E9, ""_"", """"),""@.+{(.+)\d{4}""),"", "",REGEXEXTRACT($E9,""@.+{.+(\d{4}.*),"")))"),"(no BibTex)") -> (no BibTex) | B9: =IF(ISBLANK(D9),IF(ISBLANK(K9),"-",HYPERLINK(K9,"DOC(alt)")), HYPERLINK(CONCAT("https://www.doi.org/",D9),"DOC")) -> - | C9: =IF(ISBLANK(D9),"(no DOI)", HYPERLINK(CONCAT("https://www.doi2bib.org/bib/",D9),"BIB")) -> (no DOI) | G9: =IFERROR(__xludf.DUMMYFUNCTION("IF(ISBLANK(E9),""(no BibTex)"",PROPER(REGEXEXTRACT($E9,""@(.+){"")))"),"(no BibTex)") -> (no BibTex) | H9: =IFERROR(__xludf.DUMMYFUNCTION("IF(ISBLANK(E9),""(no BibTex)"",SUBSTITUTE(IFNA(REGEXEXTRACT($E9,""author += +{(.+)}""),REGEXEXTRACT($E9,""editor *= *{(.+)}"")),"" and"", "",""))"),"(no BibTex)") -> (no BibTex) | I9: =IFERROR(__xludf.DUMMYFUNCTION("IF(ISBLANK(E9),""(no BibTex)"",REGEXEXTRACT($E9,""title *= *{(.+)}""))"),"(no BibTex)") -> (no BibTex) | J9: =IFERROR(__xludf.DUMMYFUNCTION("IFNA(IFNA(REGEXEXTRACT($E9,""journal *= *{(.+)}""), REGEXEXTRACT($E9,""booktitle *= *{(.+)}"")), ""-"")"),"-") -> -
A10: =IFERROR(__xludf.DUMMYFUNCTION("IF(ISBLANK(E10), ""(no BibTex)"", CONCATENATE(REGEXEXTRACT(SUBSTITUTE($E10, ""_"", """"),""@.+{(.+)\d{4}""),"", "",REGEXEXTRACT($E10,""@.+{.+(\d{4}.*),"")))"),"(no BibTex)") -> (no BibTex) | B10: =IF(ISBLANK(D10),IF(ISBLANK(K10),"-",HYPERLINK(K10,"DOC(alt)")), HYPERLINK(CONCAT("https://www.doi.org/",D10),"DOC")) -> - | C10: =IF(ISBLANK(D10),"(no DOI)", HYPERLINK(CONCAT("https://www.doi2bib.org/bib/",D10),"BIB")) -> (no DOI) | G10: =IFERROR(__xludf.DUMMYFUNCTION("IF(ISBLANK(E10),""(no BibTex)"",PROPER(REGEXEXTRACT($E10,""@(.+){"")))"),"(no BibTex)") -> (no BibTex) | H10: =IFERROR(__xludf.DUMMYFUNCTION("IF(ISBLANK(E10),""(no BibTex)"",SUBSTITUTE(IFNA(REGEXEXTRACT($E10,""author += +{(.+)}""),REGEXEXTRACT($E10,""editor *= *{(.+)}"")),"" and"", "",""))"),"(no BibTex)") -> (no BibTex) | I10: =IFERROR(__xludf.DUMMYFUNCTION("IF(ISBLANK(E10),""(no BibTex)"",REGEXEXTRACT($E10,""title *= *{(.+)}""))"),"(no BibTex)") -> (no BibTex) | J10: =IFERROR(__xludf.DUMMYFUNCTION("IFNA(IFNA(REGEXEXTRACT($E10,""journal *= *{(.+)}""), REGEXEXTRACT($E10,""booktitle *= *{(.+)}"")), ""-"")"),"-") -> -
A11: =IFERROR(__xludf.DUMMYFUNCTION("IF(ISBLANK(E11), ""(no BibTex)"", CONCATENATE(REGEXEXTRACT(SUBSTITUTE($E11, ""_"", """"),""@.+{(.+)\d{4}""),"", "",REGEXEXTRACT($E11,""@.+{.+(\d{4}.*),"")))"),"(no BibTex)") -> (no BibTex) | B11: =IF(ISBLANK(D11),IF(ISBLANK(K11),"-",HYPERLINK(K11,"DOC(alt)")), HYPERLINK(CONCAT("https://www.doi.org/",D11),"DOC")) -> - | C11: =IF(ISBLANK(D11),"(no DOI)", HYPERLINK(CONCAT("https://www.doi2bib.org/bib/",D11),"BIB")) -> (no DOI) | G11: =IFERROR(__xludf.DUMMYFUNCTION("IF(ISBLANK(E11),""(no BibTex)"",PROPER(REGEXEXTRACT($E11,""@(.+){"")))"),"(no BibTex)") -> (no BibTex) | H11: =IFERROR(__xludf.DUMMYFUNCTION("IF(ISBLANK(E11),""(no BibTex)"",SUBSTITUTE(IFNA(REGEXEXTRACT($E11,""author += +{(.+)}""),REGEXEXTRACT($E11,""editor *= *{(.+)}"")),"" and"", "",""))"),"(no BibTex)") -> (no BibTex) | I11: =IFERROR(__xludf.DUMMYFUNCTION("IF(ISBLANK(E11),""(no BibTex)"",REGEXEXTRACT($E11,""title *= *{(.+)}""))"),"(no BibTex)") -> (no BibTex) | J11: =IFERROR(__xludf.DUMMYFUNCTION("IFNA(IFNA(REGEXEXTRACT($E11,""journal *= *{(.+)}""), REGEXEXTRACT($E11,""booktitle *= *{(.+)}"")), ""-"")"),"-") -> -
A12: =IFERROR(__xludf.DUMMYFUNCTION("IF(ISBLANK(E12), ""(no BibTex)"", CONCATENATE(REGEXEXTRACT(SUBSTITUTE($E12, ""_"", """"),""@.+{(.+)\d{4}""),"", "",REGEXEXTRACT($E12,""@.+{.+(\d{4}.*),"")))"),"(no BibTex)") -> (no BibTex) | B12: =IF(ISBLANK(D12),IF(ISBLANK(K12),"-",HYPERLINK(K12,"DOC(alt)")), HYPERLINK(CONCAT("https://www.doi.org/",D12),"DOC")) -> - | C12: =IF(ISBLANK(D12),"(no DOI)", HYPERLINK(CONCAT("https://www.doi2bib.org/bib/",D12),"BIB")) -> (no DOI) | G12: =IFERROR(__xludf.DUMMYFUNCTION("IF(ISBLANK(E12),""(no BibTex)"",PROPER(REGEXEXTRACT($E12,""@(.+){"")))"),"(no BibTex)") -> (no BibTex) | H12: =IFERROR(__xludf.DUMMYFUNCTION("IF(ISBLANK(E12),""(no BibTex)"",SUBSTITUTE(IFNA(REGEXEXTRACT($E12,""author += +{(.+)}""),REGEXEXTRACT($E12,""editor *= *{(.+)}"")),"" and"", "",""))"),"(no BibTex)") -> (no BibTex) | I12: =IFERROR(__xludf.DUMMYFUNCTION("IF(ISBLANK(E12),""(no BibTex)"",REGEXEXTRACT($E12,""title *= *{(.+)}""))"),"(no BibTex)") -> (no BibTex) | J12: =IFERROR(__xludf.DUMMYFUNCTION("IFNA(IFNA(REGEXEXTRACT($E12,""journal *= *{(.+)}""), REGEXEXTRACT($E12,""booktitle *= *{(.+)}"")), ""-"")"),"-") -> -
A13: =IFERROR(__xludf.DUMMYFUNCTION("IF(ISBLANK(E13), ""(no BibTex)"", CONCATENATE(REGEXEXTRACT(SUBSTITUTE($E13, ""_"", """"),""@.+{(.+)\d{4}""),"", "",REGEXEXTRACT($E13,""@.+{.+(\d{4}.*),"")))"),"(no BibTex)") -> (no BibTex) | B13: =IF(ISBLANK(D13),IF(ISBLANK(K13),"-",HYPERLINK(K13,"DOC(alt)")), HYPERLINK(CONCAT("https://www.doi.org/",D13),"DOC")) -> - | C13: =IF(ISBLANK(D13),"(no DOI)", HYPERLINK(CONCAT("https://www.doi2bib.org/bib/",D13),"BIB")) -> (no DOI) | G13: =IFERROR(__xludf.DUMMYFUNCTION("IF(ISBLANK(E13),""(no BibTex)"",PROPER(REGEXEXTRACT($E13,""@(.+){"")))"),"(no BibTex)") -> (no BibTex) | H13: =IFERROR(__xludf.DUMMYFUNCTION("IF(ISBLANK(E13),""(no BibTex)"",SUBSTITUTE(IFNA(REGEXEXTRACT($E13,""author += +{(.+)}""),REGEXEXTRACT($E13,""editor *= *{(.+)}"")),"" and"", "",""))"),"(no BibTex)") -> (no BibTex) | I13: =IFERROR(__xludf.DUMMYFUNCTION("IF(ISBLANK(E13),""(no BibTex)"",REGEXEXTRACT($E13,""title *= *{(.+)}""))"),"(no BibTex)") -> (no BibTex) | J13: =IFERROR(__xludf.DUMMYFUNCTION("IFNA(IFNA(REGEXEXTRACT($E13,""journal *= *{(.+)}""), REGEXEXTRACT($E13,""booktitle *= *{(.+)}"")), ""-"")"),"-") -> -
A14: =IFERROR(__xludf.DUMMYFUNCTION("IF(ISBLANK(E14), ""(no BibTex)"", CONCATENATE(REGEXEXTRACT(SUBSTITUTE($E14, ""_"", """"),""@.+{(.+)\d{4}""),"", "",REGEXEXTRACT($E14,""@.+{.+(\d{4}.*),"")))"),"(no BibTex)") -> (no BibTex) | B14: =IF(ISBLANK(D14),IF(ISBLANK(K14),"-",HYPERLINK(K14,"DOC(alt)")), HYPERLINK(CONCAT("https://www.doi.org/",D14),"DOC")) -> - | C14: =IF(ISBLANK(D14),"(no DOI)", HYPERLINK(CONCAT("https://www.doi2bib.org/bib/",D14),"BIB")) -> (no DOI) | G14: =IFERROR(__xludf.DUMMYFUNCTION("IF(ISBLANK(E14),""(no BibTex)"",PROPER(REGEXEXTRACT($E14,""@(.+){"")))"),"(no BibTex)") -> (no BibTex) | H14: =IFERROR(__xludf.DUMMYFUNCTION("IF(ISBLANK(E14),""(no BibTex)"",SUBSTITUTE(IFNA(REGEXEXTRACT($E14,""author += +{(.+)}""),REGEXEXTRACT($E14,""editor *= *{(.+)}"")),"" and"", "",""))"),"(no BibTex)") -> (no BibTex) | I14: =IFERROR(__xludf.DUMMYFUNCTION("IF(ISBLANK(E14),""(no BibTex)"",REGEXEXTRACT($E14,""title *= *{(.+)}""))"),"(no BibTex)") -> (no BibTex) | J14: =IFERROR(__xludf.DUMMYFUNCTION("IFNA(IFNA(REGEXEXTRACT($E14,""journal *= *{(.+)}""), REGEXEXTRACT($E14,""booktitle *= *{(.+)}"")), ""-"")"),"-") -> -
A15: =IFERROR(__xludf.DUMMYFUNCTION("IF(ISBLANK(E15), ""(no BibTex)"", CONCATENATE(REGEXEXTRACT(SUBSTITUTE($E15, ""_"", """"),""@.+{(.+)\d{4}""),"", "",REGEXEXTRACT($E15,""@.+{.+(\d{4}.*),"")))"),"(no BibTex)") -> (no BibTex) | B15: =IF(ISBLANK(D15),IF(ISBLANK(K15),"-",HYPERLINK(K15,"DOC(alt)")), HYPERLINK(CONCAT("https://www.doi.org/",D15),"DOC")) -> - | C15: =IF(ISBLANK(D15),"(no DOI)", HYPERLINK(CONCAT("https://www.doi2bib.org/bib/",D15),"BIB")) -> (no DOI) | G15: =IFERROR(__xludf.DUMMYFUNCTION("IF(ISBLANK(E15),""(no BibTex)"",PROPER(REGEXEXTRACT($E15,""@(.+){"")))"),"(no BibTex)") -> (no BibTex) | H15: =IFERROR(__xludf.DUMMYFUNCTION("IF(ISBLANK(E15),""(no BibTex)"",SUBSTITUTE(IFNA(REGEXEXTRACT($E15,""author += +{(.+)}""),REGEXEXTRACT($E15,""editor *= *{(.+)}"")),"" and"", "",""))"),"(no BibTex)") -> (no BibTex) | I15: =IFERROR(__xludf.DUMMYFUNCTION("IF(ISBLANK(E15),""(no BibTex)"",REGEXEXTRACT($E15,""title *= *{(.+)}""))"),"(no BibTex)") -> (no BibTex) | J15: =IFERROR(__xludf.DUMMYFUNCTION("IFNA(IFNA(REGEXEXTRACT($E15,""journal *= *{(.+)}""), REGEXEXTRACT($E15,""booktitle *= *{(.+)}"")), ""-"")"),"-") -> -
A16: =IFERROR(__xludf.DUMMYFUNCTION("IF(ISBLANK(E16), ""(no BibTex)"", CONCATENATE(REGEXEXTRACT(SUBSTITUTE($E16, ""_"", """"),""@.+{(.+)\d{4}""),"", "",REGEXEXTRACT($E16,""@.+{.+(\d{4}.*),"")))"),"(no BibTex)") -> (no BibTex) | B16: =IF(ISBLANK(D16),IF(ISBLANK(K16),"-",HYPERLINK(K16,"DOC(alt)")), HYPERLINK(CONCAT("https://www.doi.org/",D16),"DOC")) -> - | C16: =IF(ISBLANK(D16),"(no DOI)", HYPERLINK(CONCAT("https://www.doi2bib.org/bib/",D16),"BIB")) -> (no DOI) | G16: =IFERROR(__xludf.DUMMYFUNCTION("IF(ISBLANK(E16),""(no BibTex)"",PROPER(REGEXEXTRACT($E16,""@(.+){"")))"),"(no BibTex)") -> (no BibTex) | H16: =IFERROR(__xludf.DUMMYFUNCTION("IF(ISBLANK(E16),""(no BibTex)"",SUBSTITUTE(IFNA(REGEXEXTRACT($E16,""author += +{(.+)}""),REGEXEXTRACT($E16,""editor *= *{(.+)}"")),"" and"", "",""))"),"(no BibTex)") -> (no BibTex) | I16: =IFERROR(__xludf.DUMMYFUNCTION("IF(ISBLANK(E16),""(no BibTex)"",REGEXEXTRACT($E16,""title *= *{(.+)}""))"),"(no BibTex)") -> (no BibTex) | J16: =IFERROR(__xludf.DUMMYFUNCTION("IFNA(IFNA(REGEXEXTRACT($E16,""journal *= *{(.+)}""), REGEXEXTRACT($E16,""booktitle *= *{(.+)}"")), ""-"")"),"-") -> -
A17: =IFERROR(__xludf.DUMMYFUNCTION("IF(ISBLANK(E17), ""(no BibTex)"", CONCATENATE(REGEXEXTRACT(SUBSTITUTE($E17, ""_"", """"),""@.+{(.+)\d{4}""),"", "",REGEXEXTRACT($E17,""@.+{.+(\d{4}.*),"")))"),"(no BibTex)") -> (no BibTex) | B17: =IF(ISBLANK(D17),IF(ISBLANK(K17),"-",HYPERLINK(K17,"DOC(alt)")), HYPERLINK(CONCAT("https://www.doi.org/",D17),"DOC")) -> - | C17: =IF(ISBLANK(D17),"(no DOI)", HYPERLINK(CONCAT("https://www.doi2bib.org/bib/",D17),"BIB")) -> (no DOI) | G17: =IFERROR(__xludf.DUMMYFUNCTION("IF(ISBLANK(E17),""(no BibTex)"",PROPER(REGEXEXTRACT($E17,""@(.+){"")))"),"(no BibTex)") -> (no BibTex) | H17: =IFERROR(__xludf.DUMMYFUNCTION("IF(ISBLANK(E17),""(no BibTex)"",SUBSTITUTE(IFNA(REGEXEXTRACT($E17,""author += +{(.+)}""),REGEXEXTRACT($E17,""editor *= *{(.+)}"")),"" and"", "",""))"),"(no BibTex)") -> (no BibTex) | I17: =IFERROR(__xludf.DUMMYFUNCTION("IF(ISBLANK(E17),""(no BibTex)"",REGEXEXTRACT($E17,""title *= *{(.+)}""))"),"(no BibTex)") -> (no BibTex) | J17: =IFERROR(__xludf.DUMMYFUNCTION("IFNA(IFNA(REGEXEXTRACT($E17,""journal *= *{(.+)}""), REGEXEXTRACT($E17,""booktitle *= *{(.+)}"")), ""-"")"),"-") -> -
A18: =IFERROR(__xludf.DUMMYFUNCTION("IF(ISBLANK(E18), ""(no BibTex)"", CONCATENATE(REGEXEXTRACT(SUBSTITUTE($E18, ""_"", """"),""@.+{(.+)\d{4}""),"", "",REGEXEXTRACT($E18,""@.+{.+(\d{4}.*),"")))"),"(no BibTex)") -> (no BibTex) | B18: =IF(ISBLANK(D18),IF(ISBLANK(K18),"-",HYPERLINK(K18,"DOC(alt)")), HYPERLINK(CONCAT("https://www.doi.org/",D18),"DOC")) -> - | C18: =IF(ISBLANK(D18),"(no DOI)", HYPERLINK(CONCAT("https://www.doi2bib.org/bib/",D18),"BIB")) -> (no DOI) | G18: =IFERROR(__xludf.DUMMYFUNCTION("IF(ISBLANK(E18),""(no BibTex)"",PROPER(REGEXEXTRACT($E18,""@(.+){"")))"),"(no BibTex)") -> (no BibTex) | H18: =IFERROR(__xludf.DUMMYFUNCTION("IF(ISBLANK(E18),""(no BibTex)"",SUBSTITUTE(IFNA(REGEXEXTRACT($E18,""author += +{(.+)}""),REGEXEXTRACT($E18,""editor *= *{(.+)}"")),"" and"", "",""))"),"(no BibTex)") -> (no BibTex) | I18: =IFERROR(__xludf.DUMMYFUNCTION("IF(ISBLANK(E18),""(no BibTex)"",REGEXEXTRACT($E18,""title *= *{(.+)}""))"),"(no BibTex)") -> (no BibTex) | J18: =IFERROR(__xludf.DUMMYFUNCTION("IFNA(IFNA(REGEXEXTRACT($E18,""journal *= *{(.+)}""), REGEXEXTRACT($E18,""booktitle *= *{(.+)}"")), ""-"")"),"-") -> -
A19: =IFERROR(__xludf.DUMMYFUNCTION("IF(ISBLANK(E19), ""(no BibTex)"", CONCATENATE(REGEXEXTRACT(SUBSTITUTE($E19, ""_"", """"),""@.+{(.+)\d{4}""),"", "",REGEXEXTRACT($E19,""@.+{.+(\d{4}.*),"")))"),"(no BibTex)") -> (no BibTex) | B19: =IF(ISBLANK(D19),IF(ISBLANK(K19),"-",HYPERLINK(K19,"DOC(alt)")), HYPERLINK(CONCAT("https://www.doi.org/",D19),"DOC")) -> - | C19: =IF(ISBLANK(D19),"(no DOI)", HYPERLINK(CONCAT("https://www.doi2bib.org/bib/",D19),"BIB")) -> (no DOI) | G19: =IFERROR(__xludf.DUMMYFUNCTION("IF(ISBLANK(E19),""(no BibTex)"",PROPER(REGEXEXTRACT($E19,""@(.+){"")))"),"(no BibTex)") -> (no BibTex) | H19: =IFERROR(__xludf.DUMMYFUNCTION("IF(ISBLANK(E19),""(no BibTex)"",SUBSTITUTE(IFNA(REGEXEXTRACT($E19,""author += +{(.+)}""),REGEXEXTRACT($E19,""editor *= *{(.+)}"")),"" and"", "",""))"),"(no BibTex)") -> (no BibTex) | I19: =IFERROR(__xludf.DUMMYFUNCTION("IF(ISBLANK(E19),""(no BibTex)"",REGEXEXTRACT($E19,""title *= *{(.+)}""))"),"(no BibTex)") -> (no BibTex) | J19: =IFERROR(__xludf.DUMMYFUNCTION("IFNA(IFNA(REGEXEXTRACT($E19,""journal *= *{(.+)}""), REGEXEXTRACT($E19,""booktitle *= *{(.+)}"")), ""-"")"),"-") -> -
A20: =IFERROR(__xludf.DUMMYFUNCTION("IF(ISBLANK(E20), ""(no BibTex)"", CONCATENATE(REGEXEXTRACT(SUBSTITUTE($E20, ""_"", """"),""@.+{(.+)\d{4}""),"", "",REGEXEXTRACT($E20,""@.+{.+(\d{4}.*),"")))"),"(no BibTex)") -> (no BibTex) | B20: =IF(ISBLANK(D20),IF(ISBLANK(K20),"-",HYPERLINK(K20,"DOC(alt)")), HYPERLINK(CONCAT("https://www.doi.org/",D20),"DOC")) -> - | C20: =IF(ISBLANK(D20),"(no DOI)", HYPERLINK(CONCAT("https://www.doi2bib.org/bib/",D20),"BIB")) -> (no DOI) | G20: =IFERROR(__xludf.DUMMYFUNCTION("IF(ISBLANK(E20),""(no BibTex)"",PROPER(REGEXEXTRACT($E20,""@(.+){"")))"),"(no BibTex)") -> (no BibTex) | H20: =IFERROR(__xludf.DUMMYFUNCTION("IF(ISBLANK(E20),""(no BibTex)"",SUBSTITUTE(IFNA(REGEXEXTRACT($E20,""author += +{(.+)}""),REGEXEXTRACT($E20,""editor *= *{(.+)}"")),"" and"", "",""))"),"(no BibTex)") -> (no BibTex) | I20: =IFERROR(__xludf.DUMMYFUNCTION("IF(ISBLANK(E20),""(no BibTex)"",REGEXEXTRACT($E20,""title *= *{(.+)}""))"),"(no BibTex)") -> (no BibTex) | J20: =IFERROR(__xludf.DUMMYFUNCTION("IFNA(IFNA(REGEXEXTRACT($E20,""journal *= *{(.+)}""), REGEXEXTRACT($E20,""booktitle *= *{(.+)}"")), ""-"")"),"-") -> -
A21: =IFERROR(__xludf.DUMMYFUNCTION("IF(ISBLANK(E21), ""(no BibTex)"", CONCATENATE(REGEXEXTRACT(SUBSTITUTE($E21, ""_"", """"),""@.+{(.+)\d{4}""),"", "",REGEXEXTRACT($E21,""@.+{.+(\d{4}.*),"")))"),"(no BibTex)") -> (no BibTex) | B21: =IF(ISBLANK(D21),IF(ISBLANK(K21),"-",HYPERLINK(K21,"DOC(alt)")), HYPERLINK(CONCAT("https://www.doi.org/",D21),"DOC")) -> - | C21: =IF(ISBLANK(D21),"(no DOI)", HYPERLINK(CONCAT("https://www.doi2bib.org/bib/",D21),"BIB")) -> (no DOI) | G21: =IFERROR(__xludf.DUMMYFUNCTION("IF(ISBLANK(E21),""(no BibTex)"",PROPER(REGEXEXTRACT($E21,""@(.+){"")))"),"(no BibTex)") -> (no BibTex) | H21: =IFERROR(__xludf.DUMMYFUNCTION("IF(ISBLANK(E21),""(no BibTex)"",SUBSTITUTE(IFNA(REGEXEXTRACT($E21,""author += +{(.+)}""),REGEXEXTRACT($E21,""editor *= *{(.+)}"")),"" and"", "",""))"),"(no BibTex)") -> (no BibTex) | I21: =IFERROR(__xludf.DUMMYFUNCTION("IF(ISBLANK(E21),""(no BibTex)"",REGEXEXTRACT($E21,""title *= *{(.+)}""))"),"(no BibTex)") -> (no BibTex) | J21: =IFERROR(__xludf.DUMMYFUNCTION("IFNA(IFNA(REGEXEXTRACT($E21,""journal *= *{(.+)}""), REGEXEXTRACT($E21,""booktitle *= *{(.+)}"")), ""-"")"),"-") -> -
A22: =IFERROR(__xludf.DUMMYFUNCTION("IF(ISBLANK(E22), ""(no BibTex)"", CONCATENATE(REGEXEXTRACT(SUBSTITUTE($E22, ""_"", """"),""@.+{(.+)\d{4}""),"", "",REGEXEXTRACT($E22,""@.+{.+(\d{4}.*),"")))"),"(no BibTex)") -> (no BibTex) | B22: =IF(ISBLANK(D22),IF(ISBLANK(K22),"-",HYPERLINK(K22,"DOC(alt)")), HYPERLINK(CONCAT("https://www.doi.org/",D22),"DOC")) -> - | C22: =IF(ISBLANK(D22),"(no DOI)", HYPERLINK(CONCAT("https://www.doi2bib.org/bib/",D22),"BIB")) -> (no DOI) | G22: =IFERROR(__xludf.DUMMYFUNCTION("IF(ISBLANK(E22),""(no BibTex)"",PROPER(REGEXEXTRACT($E22,""@(.+){"")))"),"(no BibTex)") -> (no BibTex) | H22: =IFERROR(__xludf.DUMMYFUNCTION("IF(ISBLANK(E22),""(no BibTex)"",SUBSTITUTE(IFNA(REGEXEXTRACT($E22,""author += +{(.+)}""),REGEXEXTRACT($E22,""editor *= *{(.+)}"")),"" and"", "",""))"),"(no BibTex)") -> (no BibTex) | I22: =IFERROR(__xludf.DUMMYFUNCTION("IF(ISBLANK(E22),""(no BibTex)"",REGEXEXTRACT($E22,""title *= *{(.+)}""))"),"(no BibTex)") -> (no BibTex) | J22: =IFERROR(__xludf.DUMMYFUNCTION("IFNA(IFNA(REGEXEXTRACT($E22,""journal *= *{(.+)}""), REGEXEXTRACT($E22,""booktitle *= *{(.+)}"")), ""-"")"),"-") -> -
A23: =IFERROR(__xludf.DUMMYFUNCTION("IF(ISBLANK(E23), ""(no BibTex)"", CONCATENATE(REGEXEXTRACT(SUBSTITUTE($E23, ""_"", """"),""@.+{(.+)\d{4}""),"", "",REGEXEXTRACT($E23,""@.+{.+(\d{4}.*),"")))"),"(no BibTex)") -> (no BibTex) | B23: =IF(ISBLANK(D23),IF(ISBLANK(K23),"-",HYPERLINK(K23,"DOC(alt)")), HYPERLINK(CONCAT("https://www.doi.org/",D23),"DOC")) -> - | C23: =IF(ISBLANK(D23),"(no DOI)", HYPERLINK(CONCAT("https://www.doi2bib.org/bib/",D23),"BIB")) -> (no DOI) | G23: =IFERROR(__xludf.DUMMYFUNCTION("IF(ISBLANK(E23),""(no BibTex)"",PROPER(REGEXEXTRACT($E23,""@(.+){"")))"),"(no BibTex)") -> (no BibTex) | H23: =IFERROR(__xludf.DUMMYFUNCTION("IF(ISBLANK(E23),""(no BibTex)"",SUBSTITUTE(IFNA(REGEXEXTRACT($E23,""author += +{(.+)}""),REGEXEXTRACT($E23,""editor *= *{(.+)}"")),"" and"", "",""))"),"(no BibTex)") -> (no BibTex) | I23: =IFERROR(__xludf.DUMMYFUNCTION("IF(ISBLANK(E23),""(no BibTex)"",REGEXEXTRACT($E23,""title *= *{(.+)}""))"),"(no BibTex)") -> (no BibTex) | J23: =IFERROR(__xludf.DUMMYFUNCTION("IFNA(IFNA(REGEXEXTRACT($E23,""journal *= *{(.+)}""), REGEXEXTRACT($E23,""booktitle *= *{(.+)}"")), ""-"")"),"-") -> -
A24: =IFERROR(__xludf.DUMMYFUNCTION("IF(ISBLANK(E24), ""(no BibTex)"", CONCATENATE(REGEXEXTRACT(SUBSTITUTE($E24, ""_"", """"),""@.+{(.+)\d{4}""),"", "",REGEXEXTRACT($E24,""@.+{.+(\d{4}.*),"")))"),"(no BibTex)") -> (no BibTex) | B24: =IF(ISBLANK(D24),IF(ISBLANK(K24),"-",HYPERLINK(K24,"DOC(alt)")), HYPERLINK(CONCAT("https://www.doi.org/",D24),"DOC")) -> - | C24: =IF(ISBLANK(D24),"(no DOI)", HYPERLINK(CONCAT("https://www.doi2bib.org/bib/",D24),"BIB")) -> (no DOI) | G24: =IFERROR(__xludf.DUMMYFUNCTION("IF(ISBLANK(E24),""(no BibTex)"",PROPER(REGEXEXTRACT($E24,""@(.+){"")))"),"(no BibTex)") -> (no BibTex) | H24: =IFERROR(__xludf.DUMMYFUNCTION("IF(ISBLANK(E24),""(no BibTex)"",SUBSTITUTE(IFNA(REGEXEXTRACT($E24,""author += +{(.+)}""),REGEXEXTRACT($E24,""editor *= *{(.+)}"")),"" and"", "",""))"),"(no BibTex)") -> (no BibTex) | I24: =IFERROR(__xludf.DUMMYFUNCTION("IF(ISBLANK(E24),""(no BibTex)"",REGEXEXTRACT($E24,""title *= *{(.+)}""))"),"(no BibTex)") -> (no BibTex) | J24: =IFERROR(__xludf.DUMMYFUNCTION("IFNA(IFNA(REGEXEXTRACT($E24,""journal *= *{(.+)}""), REGEXEXTRACT($E24,""booktitle *= *{(.+)}"")), ""-"")"),"-") -> -
A25: =IFERROR(__xludf.DUMMYFUNCTION("IF(ISBLANK(E25), ""(no BibTex)"", CONCATENATE(REGEXEXTRACT(SUBSTITUTE($E25, ""_"", """"),""@.+{(.+)\d{4}""),"", "",REGEXEXTRACT($E25,""@.+{.+(\d{4}.*),"")))"),"(no BibTex)") -> (no BibTex) | B25: =IF(ISBLANK(D25),IF(ISBLANK(K25),"-",HYPERLINK(K25,"DOC(alt)")), HYPERLINK(CONCAT("https://www.doi.org/",D25),"DOC")) -> - | C25: =IF(ISBLANK(D25),"(no DOI)", HYPERLINK(CONCAT("https://www.doi2bib.org/bib/",D25),"BIB")) -> (no DOI) | G25: =IFERROR(__xludf.DUMMYFUNCTION("IF(ISBLANK(E25),""(no BibTex)"",PROPER(REGEXEXTRACT($E25,""@(.+){"")))"),"(no BibTex)") -> (no BibTex) | H25: =IFERROR(__xludf.DUMMYFUNCTION("IF(ISBLANK(E25),""(no BibTex)"",SUBSTITUTE(IFNA(REGEXEXTRACT($E25,""author += +{(.+)}""),REGEXEXTRACT($E25,""editor *= *{(.+)}"")),"" and"", "",""))"),"(no BibTex)") -> (no BibTex) | I25: =IFERROR(__xludf.DUMMYFUNCTION("IF(ISBLANK(E25),""(no BibTex)"",REGEXEXTRACT($E25,""title *= *{(.+)}""))"),"(no BibTex)") -> (no BibTex) | J25: =IFERROR(__xludf.DUMMYFUNCTION("IFNA(IFNA(REGEXEXTRACT($E25,""journal *= *{(.+)}""), REGEXEXTRACT($E25,""booktitle *= *{(.+)}"")), ""-"")"),"-") -> -
A26: =IFERROR(__xludf.DUMMYFUNCTION("IF(ISBLANK(E26), ""(no BibTex)"", CONCATENATE(REGEXEXTRACT(SUBSTITUTE($E26, ""_"", """"),""@.+{(.+)\d{4}""),"", "",REGEXEXTRACT($E26,""@.+{.+(\d{4}.*),"")))"),"(no BibTex)") -> (no BibTex) | B26: =IF(ISBLANK(D26),IF(ISBLANK(K26),"-",HYPERLINK(K26,"DOC(alt)")), HYPERLINK(CONCAT("https://www.doi.org/",D26),"DOC")) -> - | C26: =IF(ISBLANK(D26),"(no DOI)", HYPERLINK(CONCAT("https://www.doi2bib.org/bib/",D26),"BIB")) -> (no DOI) | G26: =IFERROR(__xludf.DUMMYFUNCTION("IF(ISBLANK(E26),""(no BibTex)"",PROPER(REGEXEXTRACT($E26,""@(.+){"")))"),"(no BibTex)") -> (no BibTex) | H26: =IFERROR(__xludf.DUMMYFUNCTION("IF(ISBLANK(E26),""(no BibTex)"",SUBSTITUTE(IFNA(REGEXEXTRACT($E26,""author += +{(.+)}""),REGEXEXTRACT($E26,""editor *= *{(.+)}"")),"" and"", "",""))"),"(no BibTex)") -> (no BibTex) | I26: =IFERROR(__xludf.DUMMYFUNCTION("IF(ISBLANK(E26),""(no BibTex)"",REGEXEXTRACT($E26,""title *= *{(.+)}""))"),"(no BibTex)") -> (no BibTex) | J26: =IFERROR(__xludf.DUMMYFUNCTION("IFNA(IFNA(REGEXEXTRACT($E26,""journal *= *{(.+)}""), REGEXEXTRACT($E26,""booktitle *= *{(.+)}"")), ""-"")"),"-") -> -
A27: =IFERROR(__xludf.DUMMYFUNCTION("IF(ISBLANK(E27), ""(no BibTex)"", CONCATENATE(REGEXEXTRACT(SUBSTITUTE($E27, ""_"", """"),""@.+{(.+)\d{4}""),"", "",REGEXEXTRACT($E27,""@.+{.+(\d{4}.*),"")))"),"(no BibTex)") -> (no BibTex) | B27: =IF(ISBLANK(D27),IF(ISBLANK(K27),"-",HYPERLINK(K27,"DOC(alt)")), HYPERLINK(CONCAT("https://www.doi.org/",D27),"DOC")) -> - | C27: =IF(ISBLANK(D27),"(no DOI)", HYPERLINK(CONCAT("https://www.doi2bib.org/bib/",D27),"BIB")) -> (no DOI) | G27: =IFERROR(__xludf.DUMMYFUNCTION("IF(ISBLANK(E27),""(no BibTex)"",PROPER(REGEXEXTRACT($E27,""@(.+){"")))"),"(no BibTex)") -> (no BibTex) | H27: =IFERROR(__xludf.DUMMYFUNCTION("IF(ISBLANK(E27),""(no BibTex)"",SUBSTITUTE(IFNA(REGEXEXTRACT($E27,""author += +{(.+)}""),REGEXEXTRACT($E27,""editor *= *{(.+)}"")),"" and"", "",""))"),"(no BibTex)") -> (no BibTex) | I27: =IFERROR(__xludf.DUMMYFUNCTION("IF(ISBLANK(E27),""(no BibTex)"",REGEXEXTRACT($E27,""title *= *{(.+)}""))"),"(no BibTex)") -> (no BibTex) | J27: =IFERROR(__xludf.DUMMYFUNCTION("IFNA(IFNA(REGEXEXTRACT($E27,""journal *= *{(.+)}""), REGEXEXTRACT($E27,""booktitle *= *{(.+)}"")), ""-"")"),"-") -> -
A28: =IFERROR(__xludf.DUMMYFUNCTION("IF(ISBLANK(E28), ""(no BibTex)"", CONCATENATE(REGEXEXTRACT(SUBSTITUTE($E28, ""_"", """"),""@.+{(.+)\d{4}""),"", "",REGEXEXTRACT($E28,""@.+{.+(\d{4}.*),"")))"),"(no BibTex)") -> (no BibTex) | B28: =IF(ISBLANK(D28),IF(ISBLANK(K28),"-",HYPERLINK(K28,"DOC(alt)")), HYPERLINK(CONCAT("https://www.doi.org/",D28),"DOC")) -> - | C28: =IF(ISBLANK(D28),"(no DOI)", HYPERLINK(CONCAT("https://www.doi2bib.org/bib/",D28),"BIB")) -> (no DOI) | G28: =IFERROR(__xludf.DUMMYFUNCTION("IF(ISBLANK(E28),""(no BibTex)"",PROPER(REGEXEXTRACT($E28,""@(.+){"")))"),"(no BibTex)") -> (no BibTex) | H28: =IFERROR(__xludf.DUMMYFUNCTION("IF(ISBLANK(E28),""(no BibTex)"",SUBSTITUTE(IFNA(REGEXEXTRACT($E28,""author += +{(.+)}""),REGEXEXTRACT($E28,""editor *= *{(.+)}"")),"" and"", "",""))"),"(no BibTex)") -> (no BibTex) | I28: =IFERROR(__xludf.DUMMYFUNCTION("IF(ISBLANK(E28),""(no BibTex)"",REGEXEXTRACT($E28,""title *= *{(.+)}""))"),"(no BibTex)") -> (no BibTex) | J28: =IFERROR(__xludf.DUMMYFUNCTION("IFNA(IFNA(REGEXEXTRACT($E28,""journal *= *{(.+)}""), REGEXEXTRACT($E28,""booktitle *= *{(.+)}"")), ""-"")"),"-") -> -
A29: =IFERROR(__xludf.DUMMYFUNCTION("IF(ISBLANK(E29), ""(no BibTex)"", CONCATENATE(REGEXEXTRACT(SUBSTITUTE($E29, ""_"", """"),""@.+{(.+)\d{4}""),"", "",REGEXEXTRACT($E29,""@.+{.+(\d{4}.*),"")))"),"(no BibTex)") -> (no BibTex) | B29: =IF(ISBLANK(D29),IF(ISBLANK(K29),"-",HYPERLINK(K29,"DOC(alt)")), HYPERLINK(CONCAT("https://www.doi.org/",D29),"DOC")) -> - | C29: =IF(ISBLANK(D29),"(no DOI)", HYPERLINK(CONCAT("https://www.doi2bib.org/bib/",D29),"BIB")) -> (no DOI) | G29: =IFERROR(__xludf.DUMMYFUNCTION("IF(ISBLANK(E29),""(no BibTex)"",PROPER(REGEXEXTRACT($E29,""@(.+){"")))"),"(no BibTex)") -> (no BibTex) | H29: =IFERROR(__xludf.DUMMYFUNCTION("IF(ISBLANK(E29),""(no BibTex)"",SUBSTITUTE(IFNA(REGEXEXTRACT($E29,""author += +{(.+)}""),REGEXEXTRACT($E29,""editor *= *{(.+)}"")),"" and"", "",""))"),"(no BibTex)") -> (no BibTex) | I29: =IFERROR(__xludf.DUMMYFUNCTION("IF(ISBLANK(E29),""(no BibTex)"",REGEXEXTRACT($E29,""title *= *{(.+)}""))"),"(no BibTex)") -> (no BibTex) | J29: =IFERROR(__xludf.DUMMYFUNCTION("IFNA(IFNA(REGEXEXTRACT($E29,""journal *= *{(.+)}""), REGEXEXTRACT($E29,""booktitle *= *{(.+)}"")), ""-"")"),"-") -> -
A31: =IFERROR(__xludf.DUMMYFUNCTION("IMPORTRANGE(Settings!$A$2,""wbReferences!A2:W200"")"),"Zhaoping, 2016") -> Zhaoping, 2016 | B31: =IFERROR(__xludf.DUMMYFUNCTION("""COMPUTED_VALUE"""),"DOC") -> DOC | C31: =IFERROR(__xludf.DUMMYFUNCTION("""COMPUTED_VALUE"""),"BIB") -> BIB | D31: =IFERROR(__xludf.DUMMYFUNCTION("""COMPUTED_VALUE"""),"10.1016/j.conb.2016.06.017") -> 10.1016/j.conb.2016.06.017 | E31: =IFERROR(__xludf.DUMMYFUNCTION("""COMPUTED_VALUE"""),"@article{Zhaoping_2016, doi = {10.1016/j.conb.2016.06.017}, url = {https://doi.org/10.1016%2Fj.conb.2016.06.017}, year = 2016, month = {oct}, publisher = {Elsevier {BV}}, volume = {40}, pages = {94--102}, author = {Li Zhaoping}, title = {From the"&" optic tectum to the primary visual cortex: migration through evolution of the saliency map for exogenous attentional guidance}, journal = {Current Opinion in Neurobiology} }") -> @article{Zhaoping_2016, doi = {10.1016/j.conb.2016.06.017}, url = {https://doi.org/10.1016%2Fj.conb.2016.06.017}, year = 2016, month = {oct}, publisher = {Elsevier {BV}}, volume = {40}, pages = {94--102}, author = {Li Zhaoping}, title = {From the optic tectum to the primary visual cortex: migration through evolution of the saliency map for exogenous attentional guidance}, journal = {Current Opinion in Neurobiology} } | G31: =IFERROR(__xludf.DUMMYFUNCTION("""COMPUTED_VALUE"""),"Article") -> Article | H31: =IFERROR(__xludf.DUMMYFUNCTION("""COMPUTED_VALUE"""),"Li Zhaoping") -> Li Zhaoping | I31: =IFERROR(__xludf.DUMMYFUNCTION("""COMPUTED_VALUE"""),"From the optic tectum to the primary visual cortex: migration through evolution of the saliency map for exogenous attentional guidance") -> From the optic tectum to the primary visual cortex: migration through evolution of the saliency map for exogenous attentional guidance | J31: =IFERROR(__xludf.DUMMYFUNCTION("""COMPUTED_VALUE"""),"Current Opinion in Neurobiology") -> Current Opinion in Neurobiology
A32: =IFERROR(__xludf.DUMMYFUNCTION("""COMPUTED_VALUE"""),"Zhang, 2019") -> Zhang, 2019 | B32: =IFERROR(__xludf.DUMMYFUNCTION("""COMPUTED_VALUE"""),"DOC") -> DOC | C32: =IFERROR(__xludf.DUMMYFUNCTION("""COMPUTED_VALUE"""),"BIB") -> BIB | D32: =IFERROR(__xludf.DUMMYFUNCTION("""COMPUTED_VALUE"""),"10.1073/pnas.1817689116") -> 10.1073/pnas.1817689116 | E32: =IFERROR(__xludf.DUMMYFUNCTION("""COMPUTED_VALUE"""),"@article{Zhang_2019, doi = {10.1073/pnas.1817689116}, url = {https://doi.org/10.1073%2Fpnas.1817689116}, year = 2019, month = {jun}, publisher = {Proceedings of the National Academy of Sciences}, volume = {116}, number = {27}, pages = {13592--1360"&"1}, author = {Xu Zhang and Sabato Santaniello}, title = {Role of cerebellar {GABAergic} dysfunctions in the origins of essential tremor}, journal = {Proceedings of the National Academy of Sciences} }") -> @article{Zhang_2019, doi = {10.1073/pnas.1817689116}, url = {https://doi.org/10.1073%2Fpnas.1817689116}, year = 2019, month = {jun}, publisher = {Proceedings of the National Academy of Sciences}, volume = {116}, number = {27}, pages = {13592--13601}, author = {Xu Zhang and Sabato Santaniello}, title = {Role of cerebellar {GABAergic} dysfunctions in the origins of essential tremor}, journal = {Proceedings of the National Academy of Sciences} } | G32: =IFERROR(__xludf.DUMMYFUNCTION("""COMPUTED_VALUE"""),"Article") -> Article | H32: =IFERROR(__xludf.DUMMYFUNCTION("""COMPUTED_VALUE"""),"Xu Zhang, Sabato Santaniello") -> Xu Zhang, Sabato Santaniello | I32: =IFERROR(__xludf.DUMMYFUNCTION("""COMPUTED_VALUE"""),"Role of cerebellar {GABAergic} dysfunctions in the origins of essential tremor") -> Role of cerebellar {GABAergic} dysfunctions in the origins of essential tremor | J32: =IFERROR(__xludf.DUMMYFUNCTION("""COMPUTED_VALUE"""),"Proceedings of the National Academy of Sciences") -> Proceedings of the National Academy of Sciences | L32: =IFERROR(__xludf.DUMMYFUNCTION("""COMPUTED_VALUE"""),"Hiroshi Yamakawa") -> Hiroshi Yamakawa | M32: =IFERROR(__xludf.DUMMYFUNCTION("""COMPUTED_VALUE"""),"HY20Cerebellum") -> HY20Cerebellum
A33: =IFERROR(__xludf.DUMMYFUNCTION("""COMPUTED_VALUE"""),"Zhang, 2016") -> Zhang, 2016 | B33: =IFERROR(__xludf.DUMMYFUNCTION("""COMPUTED_VALUE"""),"DOC") -> DOC | C33: =IFERROR(__xludf.DUMMYFUNCTION("""COMPUTED_VALUE"""),"BIB") -> BIB | D33: =IFERROR(__xludf.DUMMYFUNCTION("""COMPUTED_VALUE"""),"10.1186/s40673-016-0047-1") -> 10.1186/s40673-016-0047-1 | E33: =IFERROR(__xludf.DUMMYFUNCTION("""COMPUTED_VALUE"""),"@article{Zhang_2016, doi = {10.1186/s40673-016-0047-1}, url = {https://doi.org/10.1186%2Fs40673-016-0047-1}, year = 2016, month = {may}, publisher = {Springer Science and Business Media {LLC}}, volume = {3},"&" number = {1}, author = {Xiao-Yang Zhang and Jian-Jun Wang and Jing-Ning Zhu}, title = {Cerebellar fastigial nucleus: from anatomic construction to physiological functions}, journal = {Cerebellum & Ataxias} }") -> @article{Zhang_2016, doi = {10.1186/s40673-016-0047-1}, url = {https://doi.org/10.1186%2Fs40673-016-0047-1}, year = 2016, month = {may}, publisher = {Springer Science and Business Media {LLC}}, volume = {3}, number = {1}, author = {Xiao-Yang Zhang and Jian-Jun Wang and Jing-Ning Zhu}, title = {Cerebellar fastigial nucleus: from anatomic construction to physiological functions}, journal = {Cerebellum & Ataxias} } | G33: =IFERROR(__xludf.DUMMYFUNCTION("""COMPUTED_VALUE"""),"Article") -> Article | H33: =IFERROR(__xludf.DUMMYFUNCTION("""COMPUTED_VALUE"""),"Xiao-Yang Zhang, Jian-Jun Wang, Jing-Ning Zhu") -> Xiao-Yang Zhang, Jian-Jun Wang, Jing-Ning Zhu | I33: =IFERROR(__xludf.DUMMYFUNCTION("""COMPUTED_VALUE"""),"Cerebellar fastigial nucleus: from anatomic construction to physiological functions") -> Cerebellar fastigial nucleus: from anatomic construction to physiological functions | J33: =IFERROR(__xludf.DUMMYFUNCTION("""COMPUTED_VALUE"""),"Cerebellum & Ataxias") -> Cerebellum & Ataxias | L33: =IFERROR(__xludf.DUMMYFUNCTION("""COMPUTED_VALUE"""),"Yoshinasa Tawatsji") -> Yoshinasa Tawatsji | M33: =IFERROR(__xludf.DUMMYFUNCTION("""COMPUTED_VALUE"""),"Oculomotor") -> Oculomotor
A34: =IFERROR(__xludf.DUMMYFUNCTION("""COMPUTED_VALUE"""),"Yamakawa, 2020") -> Yamakawa, 2020 | B34: =IFERROR(__xludf.DUMMYFUNCTION("""COMPUTED_VALUE"""),"DOC") -> DOC | C34: =IFERROR(__xludf.DUMMYFUNCTION("""COMPUTED_VALUE"""),"BIB") -> BIB | D34: =IFERROR(__xludf.DUMMYFUNCTION("""COMPUTED_VALUE"""),"10.3389/fncom.2020.00074") -> 10.3389/fncom.2020.00074 | E34: =IFERROR(__xludf.DUMMYFUNCTION("""COMPUTED_VALUE"""),"@article{Yamakawa_2020, doi = {10.3389/fncom.2020.00074}, url = {https://doi.org/10.3389%2Ffncom.2020.00074}, year = 2020, month = {aug}, publisher = {Frontiers Media {SA}}, volume = {14}, author = {Hiroshi Yamakawa}, title = {Revealing the Comput"&"ational Meaning of Neocortical Interarea Signals}, journal = {Frontiers in Computational Neuroscience} }") -> @article{Yamakawa_2020, doi = {10.3389/fncom.2020.00074}, url = {https://doi.org/10.3389%2Ffncom.2020.00074}, year = 2020, month = {aug}, publisher = {Frontiers Media {SA}}, volume = {14}, author = {Hiroshi Yamakawa}, title = {Revealing the Computational Meaning of Neocortical Interarea Signals}, journal = {Frontiers in Computational Neuroscience} } | G34: =IFERROR(__xludf.DUMMYFUNCTION("""COMPUTED_VALUE"""),"Article") -> Article | H34: =IFERROR(__xludf.DUMMYFUNCTION("""COMPUTED_VALUE"""),"Hiroshi Yamakawa") -> Hiroshi Yamakawa | I34: =IFERROR(__xludf.DUMMYFUNCTION("""COMPUTED_VALUE"""),"Revealing the Computational Meaning of Neocortical Interarea Signals") -> Revealing the Computational Meaning of Neocortical Interarea Signals | J34: =IFERROR(__xludf.DUMMYFUNCTION("""COMPUTED_VALUE"""),"Frontiers in Computational Neuroscience") -> Frontiers in Computational Neuroscience | K34: =IFERROR(__xludf.DUMMYFUNCTION("""COMPUTED_VALUE"""),"https://www.frontiersin.org/articles/10.3389/fncom.2020.00074/full") -> https://www.frontiersin.org/articles/10.3389/fncom.2020.00074/full | L34: =IFERROR(__xludf.DUMMYFUNCTION("""COMPUTED_VALUE"""),"Hiroshi Yamakawa") -> Hiroshi Yamakawa | M34: =IFERROR(__xludf.DUMMYFUNCTION("""COMPUTED_VALUE"""),"HY18NeocorticalInterareaSignals") -> HY18NeocorticalInterareaSignals
A35: =IFERROR(__xludf.DUMMYFUNCTION("""COMPUTED_VALUE"""),"Yamakawa, 2020a") -> Yamakawa, 2020a | B35: =IFERROR(__xludf.DUMMYFUNCTION("""COMPUTED_VALUE"""),"DOC") -> DOC | C35: =IFERROR(__xludf.DUMMYFUNCTION("""COMPUTED_VALUE"""),"BIB") -> BIB | D35: =IFERROR(__xludf.DUMMYFUNCTION("""COMPUTED_VALUE"""),"10.1007/s00354-019-00081-z") -> 10.1007/s00354-019-00081-z | E35: =IFERROR(__xludf.DUMMYFUNCTION("""COMPUTED_VALUE"""),"@article{Yamakawa_2020a, doi = {10.1007/s00354-019-00081-z}, url = {https://doi.org/10.1007%2Fs00354-019-00081-z}, year = 2020, month = {jan}, publisher = {Springer Science and Business Media {LLC}}, volume "&"= {38}, number = {1}, pages = {49--64}, author = {Hiroshi Yamakawa}, title = {Attentional Reinforcement Learning in the Brain}, journal = {New Generation Computing} }") -> @article{Yamakawa_2020a, doi = {10.1007/s00354-019-00081-z}, url = {https://doi.org/10.1007%2Fs00354-019-00081-z}, year = 2020, month = {jan}, publisher = {Springer Science and Business Media {LLC}}, volume = {38}, number = {1}, pages = {49--64}, author = {Hiroshi Yamakawa}, title = {Attentional Reinforcement Learning in the Brain}, journal = {New Generation Computing} } | F35: =IFERROR(__xludf.DUMMYFUNCTION("""COMPUTED_VALUE"""),"Hypothesis") -> Hypothesis | G35: =IFERROR(__xludf.DUMMYFUNCTION("""COMPUTED_VALUE"""),"Article") -> Article | H35: =IFERROR(__xludf.DUMMYFUNCTION("""COMPUTED_VALUE"""),"Hiroshi Yamakawa") -> Hiroshi Yamakawa | I35: =IFERROR(__xludf.DUMMYFUNCTION("""COMPUTED_VALUE"""),"Attentional Reinforcement Learning in the Brain") -> Attentional Reinforcement Learning in the Brain | J35: =IFERROR(__xludf.DUMMYFUNCTION("""COMPUTED_VALUE"""),"New Generation Computing") -> New Generation Computing | L35: =IFERROR(__xludf.DUMMYFUNCTION("""COMPUTED_VALUE"""),"Hiroshi Yamakawa") -> Hiroshi Yamakawa | M35: =IFERROR(__xludf.DUMMYFUNCTION("""COMPUTED_VALUE"""),"HY18NeocorticalInterareaSignals") -> HY18NeocorticalInterareaSignals
A36: =IFERROR(__xludf.DUMMYFUNCTION("""COMPUTED_VALUE"""),"Wolpert, 1998") -> Wolpert, 1998 | B36: =IFERROR(__xludf.DUMMYFUNCTION("""COMPUTED_VALUE"""),"DOC") -> DOC | C36: =IFERROR(__xludf.DUMMYFUNCTION("""COMPUTED_VALUE"""),"BIB") -> BIB | D36: =IFERROR(__xludf.DUMMYFUNCTION("""COMPUTED_VALUE"""),"10.1016/S1364-6613(98)01221-2") -> 10.1016/S1364-6613(98)01221-2 | E36: =IFERROR(__xludf.DUMMYFUNCTION("""COMPUTED_VALUE"""),"@article{Wolpert_1998, doi = {10.1016/s1364-6613(98)01221-2}, url = {https://doi.org/10.1016%2Fs1364-6613%2898%2901221-2}, year = 1998, month = {sep}, publisher = {Elsevier {BV}}, volume = {2}, number = {9}, pages = {338--347}, author = {Daniel M"&" Wolpert and R.Chris Miall and Mitsuo Kawato}, title = {Internal models in the cerebellum}, journal = {Trends in Cognitive Sciences} }") -> @article{Wolpert_1998, doi = {10.1016/s1364-6613(98)01221-2}, url = {https://doi.org/10.1016%2Fs1364-6613%2898%2901221-2}, year = 1998, month = {sep}, publisher = {Elsevier {BV}}, volume = {2}, number = {9}, pages = {338--347}, author = {Daniel M Wolpert and R.Chris Miall and Mitsuo Kawato}, title = {Internal models in the cerebellum}, journal = {Trends in Cognitive Sciences} } | G36: =IFERROR(__xludf.DUMMYFUNCTION("""COMPUTED_VALUE"""),"Article") -> Article | H36: =IFERROR(__xludf.DUMMYFUNCTION("""COMPUTED_VALUE"""),"Daniel M Wolpert, R.Chris Miall, Mitsuo Kawato") -> Daniel M Wolpert, R.Chris Miall, Mitsuo Kawato | I36: =IFERROR(__xludf.DUMMYFUNCTION("""COMPUTED_VALUE"""),"Internal models in the cerebellum") -> Internal models in the cerebellum | J36: =IFERROR(__xludf.DUMMYFUNCTION("""COMPUTED_VALUE"""),"Trends in Cognitive Sciences") -> Trends in Cognitive Sciences | L36: =IFERROR(__xludf.DUMMYFUNCTION("""COMPUTED_VALUE"""),"Hiroshi Yamakawa") -> Hiroshi Yamakawa | M36: =IFERROR(__xludf.DUMMYFUNCTION("""COMPUTED_VALUE"""),"HY20Cerebellum") -> HY20Cerebellum
A37: =IFERROR(__xludf.DUMMYFUNCTION("""COMPUTED_VALUE"""),"Witter, 2000") -> Witter, 2000 | B37: =IFERROR(__xludf.DUMMYFUNCTION("""COMPUTED_VALUE"""),"DOC") -> DOC | C37: =IFERROR(__xludf.DUMMYFUNCTION("""COMPUTED_VALUE"""),"BIB") -> BIB | D37: =IFERROR(__xludf.DUMMYFUNCTION("""COMPUTED_VALUE"""),"10.1002/1098-1063(2000)10:4<398::aid-hipo6>3.0.co;2-k") -> 10.1002/1098-1063(2000)10:4<398::aid-hipo6>3.0.co;2-k | E37: =IFERROR(__xludf.DUMMYFUNCTION("""COMPUTED_VALUE"""),"@article{Witter_2000, doi = {10.1002/1098-1063(2000)10:4<398::aid-hipo6>3.0.co;2-k}, url = {https://doi.org/10.1002%2F1098-1063%282000%2910%3A4%3C398%3A%3Aaid-hipo6%3E3.0.co%3B2-k}, year = 2000, publisher = {Wiley}, volume = {10}, number = {4}, pag"&"es = {398--410}, author = {Menno P. Witter and Pieterke A. Naber and Theo van Haeften and Willem C.M. Machielsen and Serge A.R.B. Rombouts and Frederik Barkhof and Philip Scheltens and Fernando H. Lopes da Silva}, title = {Cortico-hippocampal communicat"&"ion by way of parallel parahippocampal-subicular pathways}, journal = {Hippocampus} }") -> @article{Witter_2000, doi = {10.1002/1098-1063(2000)10:4<398::aid-hipo6>3.0.co;2-k}, url = {https://doi.org/10.1002%2F1098-1063%282000%2910%3A4%3C398%3A%3Aaid-hipo6%3E3.0.co%3B2-k}, year = 2000, publisher = {Wiley}, volume = {10}, number = {4}, pages = {398--410}, author = {Menno P. Witter and Pieterke A. Naber and Theo van Haeften and Willem C.M. Machielsen and Serge A.R.B. Rombouts and Frederik Barkhof and Philip Scheltens and Fernando H. Lopes da Silva}, title = {Cortico-hippocampal communication by way of parallel parahippocampal-subicular pathways}, journal = {Hippocampus} } | F37: =IFERROR(__xludf.DUMMYFUNCTION("""COMPUTED_VALUE"""),"Review") -> Review | G37: =IFERROR(__xludf.DUMMYFUNCTION("""COMPUTED_VALUE"""),"Article") -> Article | H37: =IFERROR(__xludf.DUMMYFUNCTION("""COMPUTED_VALUE"""),"Menno P. Witter, Pieterke A. Naber, Theo van Haeften, Willem C.M. Machielsen, Serge A.R.B. Rombouts, Frederik Barkhof, Philip Scheltens, Fernando H. Lopes da Silva") -> Menno P. Witter, Pieterke A. Naber, Theo van Haeften, Willem C.M. Machielsen, Serge A.R.B. Rombouts, Frederik Barkhof, Philip Scheltens, Fernando H. Lopes da Silva | I37: =IFERROR(__xludf.DUMMYFUNCTION("""COMPUTED_VALUE"""),"Cortico-hippocampal communication by way of parallel parahippocampal-subicular pathways") -> Cortico-hippocampal communication by way of parallel parahippocampal-subicular pathways | J37: =IFERROR(__xludf.DUMMYFUNCTION("""COMPUTED_VALUE"""),"Hippocampus") -> Hippocampus | L37: =IFERROR(__xludf.DUMMYFUNCTION("""COMPUTED_VALUE"""),"Ayako Fukawa") -> Ayako Fukawa | M37: =IFERROR(__xludf.DUMMYFUNCTION("""COMPUTED_VALUE"""),"AT20HippocampalFormation") -> AT20HippocampalFormation
A38: =IFERROR(__xludf.DUMMYFUNCTION("""COMPUTED_VALUE"""),"White, 2017") -> White, 2017 | B38: =IFERROR(__xludf.DUMMYFUNCTION("""COMPUTED_VALUE"""),"DOC") -> DOC | C38: =IFERROR(__xludf.DUMMYFUNCTION("""COMPUTED_VALUE"""),"BIB") -> BIB | D38: =IFERROR(__xludf.DUMMYFUNCTION("""COMPUTED_VALUE"""),"10.1073/pnas.1701003114") -> 10.1073/pnas.1701003114 | E38: =IFERROR(__xludf.DUMMYFUNCTION("""COMPUTED_VALUE"""),"@article{White_2017, doi = {10.1073/pnas.1701003114}, url = {https://doi.org/10.1073%2Fpnas.1701003114}, year = 2017, month = {aug}, publisher = {Proceedings of the National Academy of Sciences}, volume = {114}, number = {35}, pages = {9451--9456}"&", author = {Brian J. White and Janis Y. Kan and Ron Levy and Laurent Itti and Douglas P. Munoz}, title = {Superior colliculus encodes visual saliency before the primary visual cortex}, journal = {Proceedings of the National Academy of Sciences} }") -> @article{White_2017, doi = {10.1073/pnas.1701003114}, url = {https://doi.org/10.1073%2Fpnas.1701003114}, year = 2017, month = {aug}, publisher = {Proceedings of the National Academy of Sciences}, volume = {114}, number = {35}, pages = {9451--9456}, author = {Brian J. White and Janis Y. Kan and Ron Levy and Laurent Itti and Douglas P. Munoz}, title = {Superior colliculus encodes visual saliency before the primary visual cortex}, journal = {Proceedings of the National Academy of Sciences} } | G38: =IFERROR(__xludf.DUMMYFUNCTION("""COMPUTED_VALUE"""),"Article") -> Article | H38: =IFERROR(__xludf.DUMMYFUNCTION("""COMPUTED_VALUE"""),"Brian J. White, Janis Y. Kan, Ron Levy, Laurent Itti, Douglas P. Munoz") -> Brian J. White, Janis Y. Kan, Ron Levy, Laurent Itti, Douglas P. Munoz | I38: =IFERROR(__xludf.DUMMYFUNCTION("""COMPUTED_VALUE"""),"Superior colliculus encodes visual saliency before the primary visual cortex") -> Superior colliculus encodes visual saliency before the primary visual cortex | J38: =IFERROR(__xludf.DUMMYFUNCTION("""COMPUTED_VALUE"""),"Proceedings of the National Academy of Sciences") -> Proceedings of the National Academy of Sciences
A39: =IFERROR(__xludf.DUMMYFUNCTION("""COMPUTED_VALUE"""),"Wei, 2016") -> Wei, 2016 | B39: =IFERROR(__xludf.DUMMYFUNCTION("""COMPUTED_VALUE"""),"DOC") -> DOC | C39: =IFERROR(__xludf.DUMMYFUNCTION("""COMPUTED_VALUE"""),"BIB") -> BIB | D39: =IFERROR(__xludf.DUMMYFUNCTION("""COMPUTED_VALUE"""),"10.1523/JNEUROSCI.3648-15.2016") -> 10.1523/JNEUROSCI.3648-15.2016 | E39: =IFERROR(__xludf.DUMMYFUNCTION("""COMPUTED_VALUE"""),"@article{Wei_2016, doi = {10.1523/jneurosci.3648-15.2016}, url = {https://doi.org/10.1523%2Fjneurosci.3648-15.2016}, year = 2016, month = {apr}, publisher = {Society for Neuroscience}, volume = {36}, number = {15}, pages = {4231--4247}, author = "&"{Yina Wei and Giri P. Krishnan and Maxim Bazhenov}, title = {Synaptic Mechanisms of Memory Consolidation during Sleep Slow Oscillations}, journal = {The Journal of Neuroscience} }") -> @article{Wei_2016, doi = {10.1523/jneurosci.3648-15.2016}, url = {https://doi.org/10.1523%2Fjneurosci.3648-15.2016}, year = 2016, month = {apr}, publisher = {Society for Neuroscience}, volume = {36}, number = {15}, pages = {4231--4247}, author = {Yina Wei and Giri P. Krishnan and Maxim Bazhenov}, title = {Synaptic Mechanisms of Memory Consolidation during Sleep Slow Oscillations}, journal = {The Journal of Neuroscience} } | G39: =IFERROR(__xludf.DUMMYFUNCTION("""COMPUTED_VALUE"""),"Article") -> Article | H39: =IFERROR(__xludf.DUMMYFUNCTION("""COMPUTED_VALUE"""),"Yina Wei, Giri P. Krishnan, Maxim Bazhenov") -> Yina Wei, Giri P. Krishnan, Maxim Bazhenov | I39: =IFERROR(__xludf.DUMMYFUNCTION("""COMPUTED_VALUE"""),"Synaptic Mechanisms of Memory Consolidation during Sleep Slow Oscillations") -> Synaptic Mechanisms of Memory Consolidation during Sleep Slow Oscillations | J39: =IFERROR(__xludf.DUMMYFUNCTION("""COMPUTED_VALUE"""),"The Journal of Neuroscience") -> The Journal of Neuroscience | K39: =IFERROR(__xludf.DUMMYFUNCTION("""COMPUTED_VALUE"""),"Fig.1") -> Fig.1 | L39: =IFERROR(__xludf.DUMMYFUNCTION("""COMPUTED_VALUE"""),"Hiroshi Yamakawa") -> Hiroshi Yamakawa | M39: =IFERROR(__xludf.DUMMYFUNCTION("""COMPUTED_VALUE"""),"HY18NeocorticalInterareaSignals") -> HY18NeocorticalInterareaSignals
A40: =IFERROR(__xludf.DUMMYFUNCTION("""COMPUTED_VALUE"""),"Wang, 2021") -> Wang, 2021 | B40: =IFERROR(__xludf.DUMMYFUNCTION("""COMPUTED_VALUE"""),"DOC") -> DOC | C40: =IFERROR(__xludf.DUMMYFUNCTION("""COMPUTED_VALUE"""),"BIB") -> BIB | D40: =IFERROR(__xludf.DUMMYFUNCTION("""COMPUTED_VALUE"""),"10.1002/jnr.24993") -> 10.1002/jnr.24993 | E40: =IFERROR(__xludf.DUMMYFUNCTION("""COMPUTED_VALUE"""),"@article{Wang2021, doi = {10.1002/jnr.24993}, url = {https://doi.org/10.1002/jnr.24993}, year = {2021}, month = dec, publisher = {Wiley}, volume = {100}, number = {2}, pages = {620--637}, author = {Xiaolu Wang and Manuele Novell"&"o and Zhenyu Gao and Tom J. H. Ruigrok and Chris I. De Zeeuw}, title = {Input and output organization of the mesodiencephalic junction for cerebro-cerebellar communication}, journal = {Journal of Neuroscience Research} }") -> @article{Wang2021, doi = {10.1002/jnr.24993}, url = {https://doi.org/10.1002/jnr.24993}, year = {2021}, month = dec, publisher = {Wiley}, volume = {100}, number = {2}, pages = {620--637}, author = {Xiaolu Wang and Manuele Novello and Zhenyu Gao and Tom J. H. Ruigrok and Chris I. De Zeeuw}, title = {Input and output organization of the mesodiencephalic junction for cerebro-cerebellar communication}, journal = {Journal of Neuroscience Research} } | G40: =IFERROR(__xludf.DUMMYFUNCTION("""COMPUTED_VALUE"""),"Article") -> Article | H40: =IFERROR(__xludf.DUMMYFUNCTION("""COMPUTED_VALUE"""),"Xiaolu Wang, Manuele Novello, Zhenyu Gao, Tom J. H. Ruigrok, Chris I. De Zeeuw") -> Xiaolu Wang, Manuele Novello, Zhenyu Gao, Tom J. H. Ruigrok, Chris I. De Zeeuw | I40: =IFERROR(__xludf.DUMMYFUNCTION("""COMPUTED_VALUE"""),"Input and output organization of the mesodiencephalic junction for cerebro-cerebellar communication") -> Input and output organization of the mesodiencephalic junction for cerebro-cerebellar communication | J40: =IFERROR(__xludf.DUMMYFUNCTION("""COMPUTED_VALUE"""),"Journal of Neuroscience Research") -> Journal of Neuroscience Research | L40: =IFERROR(__xludf.DUMMYFUNCTION("""COMPUTED_VALUE"""),"Hiroshi Yamakawa") -> Hiroshi Yamakawa | M40: =IFERROR(__xludf.DUMMYFUNCTION("""COMPUTED_VALUE"""),"HY20Cerebellum") -> HY20Cerebellum
A41: =IFERROR(__xludf.DUMMYFUNCTION("""COMPUTED_VALUE"""),"Wang, 2020") -> Wang, 2020 | B41: =IFERROR(__xludf.DUMMYFUNCTION("""COMPUTED_VALUE"""),"DOC") -> DOC | C41: =IFERROR(__xludf.DUMMYFUNCTION("""COMPUTED_VALUE"""),"BIB") -> BIB | D41: =IFERROR(__xludf.DUMMYFUNCTION("""COMPUTED_VALUE"""),"10.1016/j.cell.2020.04.007") -> 10.1016/j.cell.2020.04.007 | E41: =IFERROR(__xludf.DUMMYFUNCTION("""COMPUTED_VALUE"""),"@article{Wang_2020, doi = {10.1016/j.cell.2020.04.007}, url = {https://doi.org/10.1016%2Fj.cell.2020.04.007}, year = 2020, month = {may}, publisher = {Elsevier {BV}}, volume = {181}, number = {4}, pages = {936--953.e20}, author = {Quanxin Wang an"&"d Song-Lin Ding and Yang Li and Josh Royall and David Feng and Phil Lesnar and Nile Graddis and Maitham Naeemi and Benjamin Facer and Anh Ho and Tim Dolbeare and Brandon Blanchard and Nick Dee and Wayne Wakeman and Karla E. Hirokawa and Aaron Szafer and S"&"usan M. Sunkin and Seung Wook Oh and Amy Bernard and John W. Phillips and Michael Hawrylycz and Christof Koch and Hongkui Zeng and Julie A. Harris and Lydia Ng}, title = {The Allen Mouse Brain Common Coordinate Framework: A 3D Reference Atlas}, journal "&"= {Cell} }") -> @article{Wang_2020, doi = {10.1016/j.cell.2020.04.007}, url = {https://doi.org/10.1016%2Fj.cell.2020.04.007}, year = 2020, month = {may}, publisher = {Elsevier {BV}}, volume = {181}, number = {4}, pages = {936--953.e20}, author = {Quanxin Wang and Song-Lin Ding and Yang Li and Josh Royall and David Feng and Phil Lesnar and Nile Graddis and Maitham Naeemi and Benjamin Facer and Anh Ho and Tim Dolbeare and Brandon Blanchard and Nick Dee and Wayne Wakeman and Karla E. Hirokawa and Aaron Szafer and Susan M. Sunkin and Seung Wook Oh and Amy Bernard and John W. Phillips and Michael Hawrylycz and Christof Koch and Hongkui Zeng and Julie A. Harris and Lydia Ng}, title = {The Allen Mouse Brain Common Coordinate Framework: A 3D Reference Atlas}, journal = {Cell} } | G41: =IFERROR(__xludf.DUMMYFUNCTION("""COMPUTED_VALUE"""),"Article") -> Article | H41: =IFERROR(__xludf.DUMMYFUNCTION("""COMPUTED_VALUE"""),"Quanxin Wang, Song-Lin Ding, Yang Li, Josh Royall, David Feng, Phil Lesnar, Nile Graddis, Maitham Naeemi, Benjamin Facer, Anh Ho, Tim Dolbeare, Brandon Blanchard, Nick Dee, Wayne Wakeman, Karla E. Hirokawa, Aaron Szafer, Susan M. Sunkin, Seung Wook Oh, Am"&"y Bernard, John W. Phillips, Michael Hawrylycz, Christof Koch, Hongkui Zeng, Julie A. Harris, Lydia Ng") -> Quanxin Wang, Song-Lin Ding, Yang Li, Josh Royall, David Feng, Phil Lesnar, Nile Graddis, Maitham Naeemi, Benjamin Facer, Anh Ho, Tim Dolbeare, Brandon Blanchard, Nick Dee, Wayne Wakeman, Karla E. Hirokawa, Aaron Szafer, Susan M. Sunkin, Seung Wook Oh, Amy Bernard, John W. Phillips, Michael Hawrylycz, Christof Koch, Hongkui Zeng, Julie A. Harris, Lydia Ng | I41: =IFERROR(__xludf.DUMMYFUNCTION("""COMPUTED_VALUE"""),"The Allen Mouse Brain Common Coordinate Framework: A 3D Reference Atlas") -> The Allen Mouse Brain Common Coordinate Framework: A 3D Reference Atlas | J41: =IFERROR(__xludf.DUMMYFUNCTION("""COMPUTED_VALUE"""),"Cell") -> Cell
A42: =IFERROR(__xludf.DUMMYFUNCTION("""COMPUTED_VALUE"""),"Wang, 2013") -> Wang, 2013 | B42: =IFERROR(__xludf.DUMMYFUNCTION("""COMPUTED_VALUE"""),"DOC") -> DOC | C42: =IFERROR(__xludf.DUMMYFUNCTION("""COMPUTED_VALUE"""),"BIB") -> BIB | D42: =IFERROR(__xludf.DUMMYFUNCTION("""COMPUTED_VALUE"""),"10.1523/JNEUROSCI.2726-11.2013") -> 10.1523/JNEUROSCI.2726-11.2013 | E42: =IFERROR(__xludf.DUMMYFUNCTION("""COMPUTED_VALUE"""),"@article{Wang_2013, doi = {10.1523/jneurosci.2726-11.2013}, url = {https://doi.org/10.1523%2Fjneurosci.2726-11.2013}, year = 2013, month = {oct}, publisher = {Society for Neuroscience}, volume = {33}, number = {41}, pages = {16285--16296}, author"&" = {N. Wang and E. Perkins and L. Zhou and S. Warren and P. J. May}, title = {Anatomical Evidence that the Superior Colliculus Controls Saccades through Central Mesencephalic Reticular Formation Gating of Omnipause Neuron Activity}, journal = {Journal o"&"f Neuroscience} }") -> @article{Wang_2013, doi = {10.1523/jneurosci.2726-11.2013}, url = {https://doi.org/10.1523%2Fjneurosci.2726-11.2013}, year = 2013, month = {oct}, publisher = {Society for Neuroscience}, volume = {33}, number = {41}, pages = {16285--16296}, author = {N. Wang and E. Perkins and L. Zhou and S. Warren and P. J. May}, title = {Anatomical Evidence that the Superior Colliculus Controls Saccades through Central Mesencephalic Reticular Formation Gating of Omnipause Neuron Activity}, journal = {Journal of Neuroscience} } | G42: =IFERROR(__xludf.DUMMYFUNCTION("""COMPUTED_VALUE"""),"Article") -> Article | H42: =IFERROR(__xludf.DUMMYFUNCTION("""COMPUTED_VALUE"""),"N. Wang, E. Perkins, L. Zhou, S. Warren, P. J. May") -> N. Wang, E. Perkins, L. Zhou, S. Warren, P. J. May | I42: =IFERROR(__xludf.DUMMYFUNCTION("""COMPUTED_VALUE"""),"Anatomical Evidence that the Superior Colliculus Controls Saccades through Central Mesencephalic Reticular Formation Gating of Omnipause Neuron Activity") -> Anatomical Evidence that the Superior Colliculus Controls Saccades through Central Mesencephalic Reticular Formation Gating of Omnipause Neuron Activity | J42: =IFERROR(__xludf.DUMMYFUNCTION("""COMPUTED_VALUE"""),"Journal of Neuroscience") -> Journal of Neuroscience | K42: =IFERROR(__xludf.DUMMYFUNCTION("""COMPUTED_VALUE"""),"https://www.jneurosci.org/content/33/41/16285") -> https://www.jneurosci.org/content/33/41/16285 | L42: =IFERROR(__xludf.DUMMYFUNCTION("""COMPUTED_VALUE"""),"Yoshinasa Tawatsji") -> Yoshinasa Tawatsji | M42: =IFERROR(__xludf.DUMMYFUNCTION("""COMPUTED_VALUE"""),"Oculomotor") -> Oculomotor
A43: =IFERROR(__xludf.DUMMYFUNCTION("""COMPUTED_VALUE"""),"Wagner, 2020") -> Wagner, 2020 | B43: =IFERROR(__xludf.DUMMYFUNCTION("""COMPUTED_VALUE"""),"DOC") -> DOC | C43: =IFERROR(__xludf.DUMMYFUNCTION("""COMPUTED_VALUE"""),"BIB") -> BIB | D43: =IFERROR(__xludf.DUMMYFUNCTION("""COMPUTED_VALUE"""),"10.1016/j.tins.2019.11.002") -> 10.1016/j.tins.2019.11.002 | E43: =IFERROR(__xludf.DUMMYFUNCTION("""COMPUTED_VALUE"""),"@article{Wagner_2020, doi = {10.1016/j.tins.2019.11.002}, url = {https://doi.org/10.1016%2Fj.tins.2019.11.002}, year = 2020, month = {jan}, publisher = {Elsevier {BV}}, volume = {43}, number = {1}, "&" pages = {42--54}, author = {Mark J. Wagner and Liqun Luo}, title = {Neocortex{\textendash}Cerebellum Circuits for Cognitive Processing}, journal = {Trends in Neurosciences} }") -> @article{Wagner_2020, doi = {10.1016/j.tins.2019.11.002}, url = {https://doi.org/10.1016%2Fj.tins.2019.11.002}, year = 2020, month = {jan}, publisher = {Elsevier {BV}}, volume = {43}, number = {1}, pages = {42--54}, author = {Mark J. Wagner and Liqun Luo}, title = {Neocortex{\textendash}Cerebellum Circuits for Cognitive Processing}, journal = {Trends in Neurosciences} } | G43: =IFERROR(__xludf.DUMMYFUNCTION("""COMPUTED_VALUE"""),"Article") -> Article | H43: =IFERROR(__xludf.DUMMYFUNCTION("""COMPUTED_VALUE"""),"Mark J. Wagner, Liqun Luo") -> Mark J. Wagner, Liqun Luo | I43: =IFERROR(__xludf.DUMMYFUNCTION("""COMPUTED_VALUE"""),"Neocortex{\textendash}Cerebellum Circuits for Cognitive Processing") -> Neocortex{\textendash}Cerebellum Circuits for Cognitive Processing | J43: =IFERROR(__xludf.DUMMYFUNCTION("""COMPUTED_VALUE"""),"Trends in Neurosciences") -> Trends in Neurosciences | L43: =IFERROR(__xludf.DUMMYFUNCTION("""COMPUTED_VALUE"""),"Hiroshi Yamakawa") -> Hiroshi Yamakawa | M43: =IFERROR(__xludf.DUMMYFUNCTION("""COMPUTED_VALUE"""),"HY20Cerebellum") -> HY20Cerebellum
A44: =IFERROR(__xludf.DUMMYFUNCTION("""COMPUTED_VALUE"""),"Verwer, 1997") -> Verwer, 1997 | B44: =IFERROR(__xludf.DUMMYFUNCTION("""COMPUTED_VALUE"""),"DOC") -> DOC | C44: =IFERROR(__xludf.DUMMYFUNCTION("""COMPUTED_VALUE"""),"BIB") -> BIB | D44: =IFERROR(__xludf.DUMMYFUNCTION("""COMPUTED_VALUE"""),"10.1002/(SICI)1098-1063(1997)7:4<397::AID-HIPO5>3.0.CO;2-G") -> 10.1002/(SICI)1098-1063(1997)7:4<397::AID-HIPO5>3.0.CO;2-G | E44: =IFERROR(__xludf.DUMMYFUNCTION("""COMPUTED_VALUE"""),"@article{Verwer_1997, doi = {10.1002/(sici)1098-1063(1997)7:4<397::aid-hipo5>3.0.co;2-g}, url = {https://doi.org/10.1002%2F%28sici%291098-1063%281997%297%3A4%3C397%3A%3Aaid-hipo5%3E3.0.co%3B2-g}, year = 1997, publisher = {Wiley}, volume = {7}, numbe"&"r = {4}, pages = {397--402}, author = {Ronald W.H. Verwer and Ron J. Meijer and Hannie F.M. Van Uum and Menno P. Witter}, title = {Collateral projections from the rat hippocampal formation to the lateral and medial prefrontal cortex}, journal = {Hippo"&"campus} }") -> @article{Verwer_1997, doi = {10.1002/(sici)1098-1063(1997)7:4<397::aid-hipo5>3.0.co;2-g}, url = {https://doi.org/10.1002%2F%28sici%291098-1063%281997%297%3A4%3C397%3A%3Aaid-hipo5%3E3.0.co%3B2-g}, year = 1997, publisher = {Wiley}, volume = {7}, number = {4}, pages = {397--402}, author = {Ronald W.H. Verwer and Ron J. Meijer and Hannie F.M. Van Uum and Menno P. Witter}, title = {Collateral projections from the rat hippocampal formation to the lateral and medial prefrontal cortex}, journal = {Hippocampus} } | G44: =IFERROR(__xludf.DUMMYFUNCTION("""COMPUTED_VALUE"""),"Article") -> Article | H44: =IFERROR(__xludf.DUMMYFUNCTION("""COMPUTED_VALUE"""),"Ronald W.H. Verwer, Ron J. Meijer, Hannie F.M. Van Uum, Menno P. Witter") -> Ronald W.H. Verwer, Ron J. Meijer, Hannie F.M. Van Uum, Menno P. Witter | I44: =IFERROR(__xludf.DUMMYFUNCTION("""COMPUTED_VALUE"""),"Collateral projections from the rat hippocampal formation to the lateral and medial prefrontal cortex") -> Collateral projections from the rat hippocampal formation to the lateral and medial prefrontal cortex | J44: =IFERROR(__xludf.DUMMYFUNCTION("""COMPUTED_VALUE"""),"Hippocampus") -> Hippocampus | L44: =IFERROR(__xludf.DUMMYFUNCTION("""COMPUTED_VALUE"""),"Ayako Fukawa") -> Ayako Fukawa | M44: =IFERROR(__xludf.DUMMYFUNCTION("""COMPUTED_VALUE"""),"AT20HippocampalFormation Claustrum") -> AT20HippocampalFormation Claustrum
A45: =IFERROR(__xludf.DUMMYFUNCTION("""COMPUTED_VALUE"""),"Tanji, 2008") -> Tanji, 2008 | B45: =IFERROR(__xludf.DUMMYFUNCTION("""COMPUTED_VALUE"""),"DOC") -> DOC | C45: =IFERROR(__xludf.DUMMYFUNCTION("""COMPUTED_VALUE"""),"BIB") -> BIB | D45: =IFERROR(__xludf.DUMMYFUNCTION("""COMPUTED_VALUE"""),"10.1152/physrev.00014.2007") -> 10.1152/physrev.00014.2007 | E45: =IFERROR(__xludf.DUMMYFUNCTION("""COMPUTED_VALUE"""),"@article{Tanji_2008, doi = {10.1152/physrev.00014.2007}, url = {https://doi.org/10.1152%2Fphysrev.00014.2007}, year = 2008, month = {jan}, publisher = {American Physiological Society}, volume = {88}, number = {1}, pages = {37--57}, author = {Jun "&"Tanji and Eiji Hoshi}, title = {Role of the Lateral Prefrontal Cortex in Executive Behavioral Control}, journal = {Physiological Reviews} }") -> @article{Tanji_2008, doi = {10.1152/physrev.00014.2007}, url = {https://doi.org/10.1152%2Fphysrev.00014.2007}, year = 2008, month = {jan}, publisher = {American Physiological Society}, volume = {88}, number = {1}, pages = {37--57}, author = {Jun Tanji and Eiji Hoshi}, title = {Role of the Lateral Prefrontal Cortex in Executive Behavioral Control}, journal = {Physiological Reviews} } | G45: =IFERROR(__xludf.DUMMYFUNCTION("""COMPUTED_VALUE"""),"Article") -> Article | H45: =IFERROR(__xludf.DUMMYFUNCTION("""COMPUTED_VALUE"""),"Jun Tanji, Eiji Hoshi") -> Jun Tanji, Eiji Hoshi | I45: =IFERROR(__xludf.DUMMYFUNCTION("""COMPUTED_VALUE"""),"Role of the Lateral Prefrontal Cortex in Executive Behavioral Control") -> Role of the Lateral Prefrontal Cortex in Executive Behavioral Control | J45: =IFERROR(__xludf.DUMMYFUNCTION("""COMPUTED_VALUE"""),"Physiological Reviews") -> Physiological Reviews
A46: =IFERROR(__xludf.DUMMYFUNCTION("""COMPUTED_VALUE"""),"Tamamaki, 1993") -> Tamamaki, 1993 | B46: =IFERROR(__xludf.DUMMYFUNCTION("""COMPUTED_VALUE"""),"DOC") -> DOC | C46: =IFERROR(__xludf.DUMMYFUNCTION("""COMPUTED_VALUE"""),"BIB") -> BIB | D46: =IFERROR(__xludf.DUMMYFUNCTION("""COMPUTED_VALUE"""),"10.1002/hipo.450030408") -> 10.1002/hipo.450030408 | E46: =IFERROR(__xludf.DUMMYFUNCTION("""COMPUTED_VALUE"""),"@article{Tamamaki_1993, doi = {10.1002/hipo.450030408}, url = {https://doi.org/10.1002%2Fhipo.450030408}, year = 1993, month = {oct}, publisher = {Wiley}, volume = {3}, number = {4}, pages = {471--480}, author = {Nobuaki Tamamaki and Yoshiaki Noj"&"yo}, title = {Projection of the entorhinal layer {II} neurons in the rat as revealed by intracellular pressure-injection of neurobiotin}, journal = {Hippocampus} }") -> @article{Tamamaki_1993, doi = {10.1002/hipo.450030408}, url = {https://doi.org/10.1002%2Fhipo.450030408}, year = 1993, month = {oct}, publisher = {Wiley}, volume = {3}, number = {4}, pages = {471--480}, author = {Nobuaki Tamamaki and Yoshiaki Nojyo}, title = {Projection of the entorhinal layer {II} neurons in the rat as revealed by intracellular pressure-injection of neurobiotin}, journal = {Hippocampus} } | F46: =IFERROR(__xludf.DUMMYFUNCTION("""COMPUTED_VALUE"""),"Experimental results") -> Experimental results | G46: =IFERROR(__xludf.DUMMYFUNCTION("""COMPUTED_VALUE"""),"Article") -> Article | H46: =IFERROR(__xludf.DUMMYFUNCTION("""COMPUTED_VALUE"""),"Nobuaki Tamamaki, Yoshiaki Nojyo") -> Nobuaki Tamamaki, Yoshiaki Nojyo | I46: =IFERROR(__xludf.DUMMYFUNCTION("""COMPUTED_VALUE"""),"Projection of the entorhinal layer {II} neurons in the rat as revealed by intracellular pressure-injection of neurobiotin") -> Projection of the entorhinal layer {II} neurons in the rat as revealed by intracellular pressure-injection of neurobiotin | J46: =IFERROR(__xludf.DUMMYFUNCTION("""COMPUTED_VALUE"""),"Hippocampus") -> Hippocampus | L46: =IFERROR(__xludf.DUMMYFUNCTION("""COMPUTED_VALUE"""),"Yuske Shibata") -> Yuske Shibata | M46: =IFERROR(__xludf.DUMMYFUNCTION("""COMPUTED_VALUE"""),"YS21CredibilityCheck") -> YS21CredibilityCheck
A47: =IFERROR(__xludf.DUMMYFUNCTION("""COMPUTED_VALUE"""),"Takahashi, 2021") -> Takahashi, 2021 | B47: =IFERROR(__xludf.DUMMYFUNCTION("""COMPUTED_VALUE"""),"DOC") -> DOC | C47: =IFERROR(__xludf.DUMMYFUNCTION("""COMPUTED_VALUE"""),"BIB") -> BIB | D47: =IFERROR(__xludf.DUMMYFUNCTION("""COMPUTED_VALUE"""),"10.1523/JNEUROSCI.1731-21.2021") -> 10.1523/JNEUROSCI.1731-21.2021 | E47: =IFERROR(__xludf.DUMMYFUNCTION("""COMPUTED_VALUE"""),"@article{Takahashi_2021, doi = {10.1523/jneurosci.1731-21.2021}, url = {https://doi.org/10.1523%2Fjneurosci.1731-21.2021}, year = 2021, month = {dec}, publisher = {Society for Neuroscience}, volume = {42}, number = {5}, pages = {789--803}, author"&" = {Mayu Takahashi and Yuriko Sugiuchi and Jie Na and Yoshikazu Shinoda}, title = {Brainstem Circuits Triggering Saccades and Fixation}, journal = {The Journal of Neuroscience} }") -> @article{Takahashi_2021, doi = {10.1523/jneurosci.1731-21.2021}, url = {https://doi.org/10.1523%2Fjneurosci.1731-21.2021}, year = 2021, month = {dec}, publisher = {Society for Neuroscience}, volume = {42}, number = {5}, pages = {789--803}, author = {Mayu Takahashi and Yuriko Sugiuchi and Jie Na and Yoshikazu Shinoda}, title = {Brainstem Circuits Triggering Saccades and Fixation}, journal = {The Journal of Neuroscience} } | G47: =IFERROR(__xludf.DUMMYFUNCTION("""COMPUTED_VALUE"""),"Article") -> Article | H47: =IFERROR(__xludf.DUMMYFUNCTION("""COMPUTED_VALUE"""),"Mayu Takahashi, Yuriko Sugiuchi, Jie Na, Yoshikazu Shinoda") -> Mayu Takahashi, Yuriko Sugiuchi, Jie Na, Yoshikazu Shinoda | I47: =IFERROR(__xludf.DUMMYFUNCTION("""COMPUTED_VALUE"""),"Brainstem Circuits Triggering Saccades and Fixation") -> Brainstem Circuits Triggering Saccades and Fixation | J47: =IFERROR(__xludf.DUMMYFUNCTION("""COMPUTED_VALUE"""),"The Journal of Neuroscience") -> The Journal of Neuroscience | L47: =IFERROR(__xludf.DUMMYFUNCTION("""COMPUTED_VALUE"""),"Yoshinasa Tawatsji") -> Yoshinasa Tawatsji | M47: =IFERROR(__xludf.DUMMYFUNCTION("""COMPUTED_VALUE"""),"Oculomotor") -> Oculomotor
A48: =IFERROR(__xludf.DUMMYFUNCTION("""COMPUTED_VALUE"""),"Takahashi, 2018") -> Takahashi, 2018 | B48: =IFERROR(__xludf.DUMMYFUNCTION("""COMPUTED_VALUE"""),"DOC") -> DOC | C48: =IFERROR(__xludf.DUMMYFUNCTION("""COMPUTED_VALUE"""),"BIB") -> BIB | D48: =IFERROR(__xludf.DUMMYFUNCTION("""COMPUTED_VALUE"""),"10.1016/j.neuroscience.2018.08.027") -> 10.1016/j.neuroscience.2018.08.027 | E48: =IFERROR(__xludf.DUMMYFUNCTION("""COMPUTED_VALUE"""),"@article{Takahashi_2018, doi = {10.1016/j.neuroscience.2018.08.027}, url = {https://doi.org/10.1016%2Fj.neuroscience.2018.08.027}, year = 2018, month = {nov}, publisher = {Elsevier {BV}}, volume = {392}, pages = {281--328}, author = {Mayu Takahash"&"i and Yoshikazu Shinoda}, title = {Brain Stem Neural Circuits of Horizontal and Vertical Saccade Systems and their Frame of Reference}, journal = {Neuroscience} }") -> @article{Takahashi_2018, doi = {10.1016/j.neuroscience.2018.08.027}, url = {https://doi.org/10.1016%2Fj.neuroscience.2018.08.027}, year = 2018, month = {nov}, publisher = {Elsevier {BV}}, volume = {392}, pages = {281--328}, author = {Mayu Takahashi and Yoshikazu Shinoda}, title = {Brain Stem Neural Circuits of Horizontal and Vertical Saccade Systems and their Frame of Reference}, journal = {Neuroscience} } | G48: =IFERROR(__xludf.DUMMYFUNCTION("""COMPUTED_VALUE"""),"Article") -> Article | H48: =IFERROR(__xludf.DUMMYFUNCTION("""COMPUTED_VALUE"""),"Mayu Takahashi, Yoshikazu Shinoda") -> Mayu Takahashi, Yoshikazu Shinoda | I48: =IFERROR(__xludf.DUMMYFUNCTION("""COMPUTED_VALUE"""),"Brain Stem Neural Circuits of Horizontal and Vertical Saccade Systems and their Frame of Reference") -> Brain Stem Neural Circuits of Horizontal and Vertical Saccade Systems and their Frame of Reference | J48: =IFERROR(__xludf.DUMMYFUNCTION("""COMPUTED_VALUE"""),"Neuroscience") -> Neuroscience | L48: =IFERROR(__xludf.DUMMYFUNCTION("""COMPUTED_VALUE"""),"Yoshinasa Tawatsji") -> Yoshinasa Tawatsji | M48: =IFERROR(__xludf.DUMMYFUNCTION("""COMPUTED_VALUE"""),"Oculomotor") -> Oculomotor
A49: =IFERROR(__xludf.DUMMYFUNCTION("""COMPUTED_VALUE"""),"Sugiuchi, 2013") -> Sugiuchi, 2013 | B49: =IFERROR(__xludf.DUMMYFUNCTION("""COMPUTED_VALUE"""),"DOC") -> DOC | C49: =IFERROR(__xludf.DUMMYFUNCTION("""COMPUTED_VALUE"""),"BIB") -> BIB | D49: =IFERROR(__xludf.DUMMYFUNCTION("""COMPUTED_VALUE"""),"10.1152/jn.01045.2012") -> 10.1152/jn.01045.2012 | E49: =IFERROR(__xludf.DUMMYFUNCTION("""COMPUTED_VALUE"""),"@article{Sugiuchi_2013, doi = {10.1152/jn.01045.2012}, url = {https://doi.org/10.1152%2Fjn.01045.2012}, year = 2013, month = {aug}, publisher = {American Physiological Society}, volume = {110}, number = {3}, pages = {640--657}, author = {Y. Sugiu"&"chi and M. Takahashi and Y. Shinoda}, title = {Input-output organization of inhibitory neurons in the interstitial nucleus of Cajal projecting to the contralateral trochlear and oculomotor nucleus}, journal = {Journal of Neurophysiology} }") -> @article{Sugiuchi_2013, doi = {10.1152/jn.01045.2012}, url = {https://doi.org/10.1152%2Fjn.01045.2012}, year = 2013, month = {aug}, publisher = {American Physiological Society}, volume = {110}, number = {3}, pages = {640--657}, author = {Y. Sugiuchi and M. Takahashi and Y. Shinoda}, title = {Input-output organization of inhibitory neurons in the interstitial nucleus of Cajal projecting to the contralateral trochlear and oculomotor nucleus}, journal = {Journal of Neurophysiology} } | G49: =IFERROR(__xludf.DUMMYFUNCTION("""COMPUTED_VALUE"""),"Article") -> Article | H49: =IFERROR(__xludf.DUMMYFUNCTION("""COMPUTED_VALUE"""),"Y. Sugiuchi, M. Takahashi, Y. Shinoda") -> Y. Sugiuchi, M. Takahashi, Y. Shinoda | I49: =IFERROR(__xludf.DUMMYFUNCTION("""COMPUTED_VALUE"""),"Input-output organization of inhibitory neurons in the interstitial nucleus of Cajal projecting to the contralateral trochlear and oculomotor nucleus") -> Input-output organization of inhibitory neurons in the interstitial nucleus of Cajal projecting to the contralateral trochlear and oculomotor nucleus | J49: =IFERROR(__xludf.DUMMYFUNCTION("""COMPUTED_VALUE"""),"Journal of Neurophysiology") -> Journal of Neurophysiology | L49: =IFERROR(__xludf.DUMMYFUNCTION("""COMPUTED_VALUE"""),"Yoshinasa Tawatsji") -> Yoshinasa Tawatsji | M49: =IFERROR(__xludf.DUMMYFUNCTION("""COMPUTED_VALUE"""),"Oculomotor") -> Oculomotor
A50: =IFERROR(__xludf.DUMMYFUNCTION("""COMPUTED_VALUE"""),"Sugiuchi, 2011") -> Sugiuchi, 2011 | B50: =IFERROR(__xludf.DUMMYFUNCTION("""COMPUTED_VALUE"""),"DOC") -> DOC | C50: =IFERROR(__xludf.DUMMYFUNCTION("""COMPUTED_VALUE"""),"BIB") -> BIB | D50: =IFERROR(__xludf.DUMMYFUNCTION("""COMPUTED_VALUE"""),"10.3757/jser.70.89") -> 10.3757/jser.70.89 | E50: =IFERROR(__xludf.DUMMYFUNCTION("""COMPUTED_VALUE"""),"@article{Sugiuchi_2011, doi = {10.3757/jser.70.89}, url = {https://doi.org/10.3757%2Fjser.70.89}, year = 2011, publisher = {Japan Society of Equilibrium Research}, volume = {70}, number = {2}, pages = {89--94}, author = {Yuriko Sugiuchi and Mayu T"&"akahashi}, title = {Neural mechanisms of saccadic eye movements: common ground with the vestibular system}, journal = {Equilibrium Research} }") -> @article{Sugiuchi_2011, doi = {10.3757/jser.70.89}, url = {https://doi.org/10.3757%2Fjser.70.89}, year = 2011, publisher = {Japan Society of Equilibrium Research}, volume = {70}, number = {2}, pages = {89--94}, author = {Yuriko Sugiuchi and Mayu Takahashi}, title = {Neural mechanisms of saccadic eye movements: common ground with the vestibular system}, journal = {Equilibrium Research} } | G50: =IFERROR(__xludf.DUMMYFUNCTION("""COMPUTED_VALUE"""),"Article") -> Article | H50: =IFERROR(__xludf.DUMMYFUNCTION("""COMPUTED_VALUE"""),"Yuriko Sugiuchi, Mayu Takahashi") -> Yuriko Sugiuchi, Mayu Takahashi | I50: =IFERROR(__xludf.DUMMYFUNCTION("""COMPUTED_VALUE"""),"Neural mechanisms of saccadic eye movements: common ground with the vestibular system") -> Neural mechanisms of saccadic eye movements: common ground with the vestibular system | J50: =IFERROR(__xludf.DUMMYFUNCTION("""COMPUTED_VALUE"""),"Equilibrium Research") -> Equilibrium Research | L50: =IFERROR(__xludf.DUMMYFUNCTION("""COMPUTED_VALUE"""),"Yoshinasa Tawatsji") -> Yoshinasa Tawatsji | M50: =IFERROR(__xludf.DUMMYFUNCTION("""COMPUTED_VALUE"""),"Oculomotor") -> Oculomotor
A51: =IFERROR(__xludf.DUMMYFUNCTION("""COMPUTED_VALUE"""),"Solari, 2011") -> Solari, 2011 | B51: =IFERROR(__xludf.DUMMYFUNCTION("""COMPUTED_VALUE"""),"DOC") -> DOC | C51: =IFERROR(__xludf.DUMMYFUNCTION("""COMPUTED_VALUE"""),"BIB") -> BIB | D51: =IFERROR(__xludf.DUMMYFUNCTION("""COMPUTED_VALUE"""),"10.3389/fnana.2011.00065") -> 10.3389/fnana.2011.00065 | E51: =IFERROR(__xludf.DUMMYFUNCTION("""COMPUTED_VALUE"""),"@article{Solari_2011, doi = {10.3389/fnana.2011.00065}, url = {https://doi.org/10.3389%2Ffnana.2011.00065}, year = 2011, publisher = {Frontiers Media {SA}}, author = {Solari}, title = {Cognitive consilience: Primate non-primary neuroanatomical circu"&"its underlying cognition}, journal = {Frontiers in Neuroanatomy} }") -> @article{Solari_2011, doi = {10.3389/fnana.2011.00065}, url = {https://doi.org/10.3389%2Ffnana.2011.00065}, year = 2011, publisher = {Frontiers Media {SA}}, author = {Solari}, title = {Cognitive consilience: Primate non-primary neuroanatomical circuits underlying cognition}, journal = {Frontiers in Neuroanatomy} } | G51: =IFERROR(__xludf.DUMMYFUNCTION("""COMPUTED_VALUE"""),"Article") -> Article | H51: =IFERROR(__xludf.DUMMYFUNCTION("""COMPUTED_VALUE"""),"Solari") -> Solari | I51: =IFERROR(__xludf.DUMMYFUNCTION("""COMPUTED_VALUE"""),"Cognitive consilience: Primate non-primary neuroanatomical circuits underlying cognition") -> Cognitive consilience: Primate non-primary neuroanatomical circuits underlying cognition | J51: =IFERROR(__xludf.DUMMYFUNCTION("""COMPUTED_VALUE"""),"Frontiers in Neuroanatomy") -> Frontiers in Neuroanatomy | L51: =IFERROR(__xludf.DUMMYFUNCTION("""COMPUTED_VALUE"""),"Hiroshi Yamakawa") -> Hiroshi Yamakawa | M51: =IFERROR(__xludf.DUMMYFUNCTION("""COMPUTED_VALUE"""),"HY18NeocorticalInterareaSignals") -> HY18NeocorticalInterareaSignals
A52: =IFERROR(__xludf.DUMMYFUNCTION("""COMPUTED_VALUE"""),"Smith, 2011") -> Smith, 2011 | B52: =IFERROR(__xludf.DUMMYFUNCTION("""COMPUTED_VALUE"""),"DOC") -> DOC | C52: =IFERROR(__xludf.DUMMYFUNCTION("""COMPUTED_VALUE"""),"BIB") -> BIB | D52: =IFERROR(__xludf.DUMMYFUNCTION("""COMPUTED_VALUE"""),"10.1016/b978-1-4160-5316-3.00074-5") -> 10.1016/b978-1-4160-5316-3.00074-5 | E52: =IFERROR(__xludf.DUMMYFUNCTION("""COMPUTED_VALUE"""),"@incollection{Smith_2011, doi = {10.1016/b978-1-4160-5316-3.00074-5}, url = {https://doi.org/10.1016%2Fb978-1-4160-5316-3.00074-5}, year = 2011, publisher = {Elsevier}, pages = {854--863}, author = {Yoland S"&"mith}, title = {Anatomy and Synaptic Connectivity of the Basal Ganglia}, booktitle = {Youmans Neurological Surgery} }") -> @incollection{Smith_2011, doi = {10.1016/b978-1-4160-5316-3.00074-5}, url = {https://doi.org/10.1016%2Fb978-1-4160-5316-3.00074-5}, year = 2011, publisher = {Elsevier}, pages = {854--863}, author = {Yoland Smith}, title = {Anatomy and Synaptic Connectivity of the Basal Ganglia}, booktitle = {Youmans Neurological Surgery} } | G52: =IFERROR(__xludf.DUMMYFUNCTION("""COMPUTED_VALUE"""),"Incollection") -> Incollection | H52: =IFERROR(__xludf.DUMMYFUNCTION("""COMPUTED_VALUE"""),"Yoland Smith") -> Yoland Smith | I52: =IFERROR(__xludf.DUMMYFUNCTION("""COMPUTED_VALUE"""),"Anatomy and Synaptic Connectivity of the Basal Ganglia") -> Anatomy and Synaptic Connectivity of the Basal Ganglia | J52: =IFERROR(__xludf.DUMMYFUNCTION("""COMPUTED_VALUE"""),"Youmans Neurological Surgery") -> Youmans Neurological Surgery | K52: =IFERROR(__xludf.DUMMYFUNCTION("""COMPUTED_VALUE"""),"https://clinicalgate.com/anatomy-and-synaptic-connectivity-of-the-basal-ganglia/") -> https://clinicalgate.com/anatomy-and-synaptic-connectivity-of-the-basal-ganglia/ | L52: =IFERROR(__xludf.DUMMYFUNCTION("""COMPUTED_VALUE"""),"Yuske Shibata") -> Yuske Shibata | M52: =IFERROR(__xludf.DUMMYFUNCTION("""COMPUTED_VALUE"""),"YS21BgLoop") -> YS21BgLoop
A53: =IFERROR(__xludf.DUMMYFUNCTION("""COMPUTED_VALUE"""),"Shook, 1990") -> Shook, 1990 | B53: =IFERROR(__xludf.DUMMYFUNCTION("""COMPUTED_VALUE"""),"DOC") -> DOC | C53: =IFERROR(__xludf.DUMMYFUNCTION("""COMPUTED_VALUE"""),"BIB") -> BIB | D53: =IFERROR(__xludf.DUMMYFUNCTION("""COMPUTED_VALUE"""),"10.1002/cne.903010410") -> 10.1002/cne.903010410 | E53: =IFERROR(__xludf.DUMMYFUNCTION("""COMPUTED_VALUE"""),"@article{Shook_1990, doi = {10.1002/cne.903010410}, url = {https://doi.org/10.1002%2Fcne.903010410}, year = 1990, month = {nov}, publisher = {Wiley}, volume = {301}, number = {4}, pages = {618--642}, author = {B. L. Shook and M. Schlag-Rey and J."&" Schlag}, title = {Primate supplementary eye field: I. Comparative aspects of mesencephalic and pontine connections}, journal = {The Journal of Comparative Neurology} }") -> @article{Shook_1990, doi = {10.1002/cne.903010410}, url = {https://doi.org/10.1002%2Fcne.903010410}, year = 1990, month = {nov}, publisher = {Wiley}, volume = {301}, number = {4}, pages = {618--642}, author = {B. L. Shook and M. Schlag-Rey and J. Schlag}, title = {Primate supplementary eye field: I. Comparative aspects of mesencephalic and pontine connections}, journal = {The Journal of Comparative Neurology} } | G53: =IFERROR(__xludf.DUMMYFUNCTION("""COMPUTED_VALUE"""),"Article") -> Article | H53: =IFERROR(__xludf.DUMMYFUNCTION("""COMPUTED_VALUE"""),"B. L. Shook, M. Schlag-Rey, J. Schlag") -> B. L. Shook, M. Schlag-Rey, J. Schlag | I53: =IFERROR(__xludf.DUMMYFUNCTION("""COMPUTED_VALUE"""),"Primate supplementary eye field: I. Comparative aspects of mesencephalic and pontine connections") -> Primate supplementary eye field: I. Comparative aspects of mesencephalic and pontine connections | J53: =IFERROR(__xludf.DUMMYFUNCTION("""COMPUTED_VALUE"""),"The Journal of Comparative Neurology") -> The Journal of Comparative Neurology | L53: =IFERROR(__xludf.DUMMYFUNCTION("""COMPUTED_VALUE"""),"Yoshinasa Tawatsji") -> Yoshinasa Tawatsji | M53: =IFERROR(__xludf.DUMMYFUNCTION("""COMPUTED_VALUE"""),"Oculomotor") -> Oculomotor
A54: =IFERROR(__xludf.DUMMYFUNCTION("""COMPUTED_VALUE"""),"Shin, 2011") -> Shin, 2011 | B54: =IFERROR(__xludf.DUMMYFUNCTION("""COMPUTED_VALUE"""),"DOC") -> DOC | C54: =IFERROR(__xludf.DUMMYFUNCTION("""COMPUTED_VALUE"""),"BIB") -> BIB | D54: =IFERROR(__xludf.DUMMYFUNCTION("""COMPUTED_VALUE"""),"10.1523/JNEUROSCI.0768-11.2011") -> 10.1523/JNEUROSCI.0768-11.2011 | E54: =IFERROR(__xludf.DUMMYFUNCTION("""COMPUTED_VALUE"""),"@article{Shin_2011, doi = {10.1523/jneurosci.0768-11.2011}, url = {https://doi.org/10.1523%2Fjneurosci.0768-11.2011}, year = 2011, month = {jul}, publisher = {Society for Neuroscience}, volume = {31}, number = {30}, pages = {10776--10786}, author"&" = {M. Shin and S. H. Moghadam and C. Sekirnjak and M. W. Bagnall and K. E. Kolkman and R. Jacobs and M. Faulstich and S. du Lac}, title = {Multiple Types of Cerebellar Target Neurons and Their Circuitry in the Vestibulo-ocular Reflex}, journal = {Journ"&"al of Neuroscience} }") -> @article{Shin_2011, doi = {10.1523/jneurosci.0768-11.2011}, url = {https://doi.org/10.1523%2Fjneurosci.0768-11.2011}, year = 2011, month = {jul}, publisher = {Society for Neuroscience}, volume = {31}, number = {30}, pages = {10776--10786}, author = {M. Shin and S. H. Moghadam and C. Sekirnjak and M. W. Bagnall and K. E. Kolkman and R. Jacobs and M. Faulstich and S. du Lac}, title = {Multiple Types of Cerebellar Target Neurons and Their Circuitry in the Vestibulo-ocular Reflex}, journal = {Journal of Neuroscience} } | G54: =IFERROR(__xludf.DUMMYFUNCTION("""COMPUTED_VALUE"""),"Article") -> Article | H54: =IFERROR(__xludf.DUMMYFUNCTION("""COMPUTED_VALUE"""),"M. Shin, S. H. Moghadam, C. Sekirnjak, M. W. Bagnall, K. E. Kolkman, R. Jacobs, M. Faulstich, S. du Lac") -> M. Shin, S. H. Moghadam, C. Sekirnjak, M. W. Bagnall, K. E. Kolkman, R. Jacobs, M. Faulstich, S. du Lac | I54: =IFERROR(__xludf.DUMMYFUNCTION("""COMPUTED_VALUE"""),"Multiple Types of Cerebellar Target Neurons and Their Circuitry in the Vestibulo-ocular Reflex") -> Multiple Types of Cerebellar Target Neurons and Their Circuitry in the Vestibulo-ocular Reflex | J54: =IFERROR(__xludf.DUMMYFUNCTION("""COMPUTED_VALUE"""),"Journal of Neuroscience") -> Journal of Neuroscience | L54: =IFERROR(__xludf.DUMMYFUNCTION("""COMPUTED_VALUE"""),"Hiroshi Yamakawa") -> Hiroshi Yamakawa | M54: =IFERROR(__xludf.DUMMYFUNCTION("""COMPUTED_VALUE"""),"HY20Cerebellum") -> HY20Cerebellum
A55: =IFERROR(__xludf.DUMMYFUNCTION("""COMPUTED_VALUE"""),"Shepherd, 2017") -> Shepherd, 2017 | B55: =IFERROR(__xludf.DUMMYFUNCTION("""COMPUTED_VALUE"""),"DOC") -> DOC | C55: =IFERROR(__xludf.DUMMYFUNCTION("""COMPUTED_VALUE"""),"BIB") -> BIB | D55: =IFERROR(__xludf.DUMMYFUNCTION("""COMPUTED_VALUE"""),"10.1093/med/9780190636111.001.0001") -> 10.1093/med/9780190636111.001.0001 | E55: =IFERROR(__xludf.DUMMYFUNCTION("""COMPUTED_VALUE"""),"@book{Shepherd2017, doi = {10.1093/med/9780190636111.001.0001}, url = {https://doi.org/10.1093/med/9780190636111.001.0001}, year = {2017}, month = dec, publisher = {Oxford University Press}, editor = {Gordon M Shepherd and Sten Grillner}, ti"&"tle = {Handbook of Brain Microcircuits} }") -> @book{Shepherd2017, doi = {10.1093/med/9780190636111.001.0001}, url = {https://doi.org/10.1093/med/9780190636111.001.0001}, year = {2017}, month = dec, publisher = {Oxford University Press}, editor = {Gordon M Shepherd and Sten Grillner}, title = {Handbook of Brain Microcircuits} } | F55: =IFERROR(__xludf.DUMMYFUNCTION("""COMPUTED_VALUE"""),"Textbook") -> Textbook | G55: =IFERROR(__xludf.DUMMYFUNCTION("""COMPUTED_VALUE"""),"Book") -> Book | H55: =IFERROR(__xludf.DUMMYFUNCTION("""COMPUTED_VALUE"""),"Gordon M Shepherd, Sten Grillner") -> Gordon M Shepherd, Sten Grillner | I55: =IFERROR(__xludf.DUMMYFUNCTION("""COMPUTED_VALUE"""),"Handbook of Brain Microcircuits") -> Handbook of Brain Microcircuits | J55: =IFERROR(__xludf.DUMMYFUNCTION("""COMPUTED_VALUE"""),"-") -> -
A56: =IFERROR(__xludf.DUMMYFUNCTION("""COMPUTED_VALUE"""),"Shepherd, 2013") -> Shepherd, 2013 | B56: =IFERROR(__xludf.DUMMYFUNCTION("""COMPUTED_VALUE"""),"DOC") -> DOC | C56: =IFERROR(__xludf.DUMMYFUNCTION("""COMPUTED_VALUE"""),"BIB") -> BIB | D56: =IFERROR(__xludf.DUMMYFUNCTION("""COMPUTED_VALUE"""),"10.1038/nrn3469") -> 10.1038/nrn3469 | E56: =IFERROR(__xludf.DUMMYFUNCTION("""COMPUTED_VALUE"""),"@article{Shepherd_2013, doi = {10.1038/nrn3469}, url = {https://doi.org/10.1038%2Fnrn3469}, year = 2013, month = {mar}, publisher = {Springer Science and Business Media {LLC}}, volume = {14}, number = {4}, pages = {278--291}, author = {Gordon M. "&"G. Shepherd}, title = {Corticostriatal connectivity and its role in disease}, journal = {Nature Reviews Neuroscience} }") -> @article{Shepherd_2013, doi = {10.1038/nrn3469}, url = {https://doi.org/10.1038%2Fnrn3469}, year = 2013, month = {mar}, publisher = {Springer Science and Business Media {LLC}}, volume = {14}, number = {4}, pages = {278--291}, author = {Gordon M. G. Shepherd}, title = {Corticostriatal connectivity and its role in disease}, journal = {Nature Reviews Neuroscience} } | G56: =IFERROR(__xludf.DUMMYFUNCTION("""COMPUTED_VALUE"""),"Article") -> Article | H56: =IFERROR(__xludf.DUMMYFUNCTION("""COMPUTED_VALUE"""),"Gordon M. G. Shepherd") -> Gordon M. G. Shepherd | I56: =IFERROR(__xludf.DUMMYFUNCTION("""COMPUTED_VALUE"""),"Corticostriatal connectivity and its role in disease") -> Corticostriatal connectivity and its role in disease | J56: =IFERROR(__xludf.DUMMYFUNCTION("""COMPUTED_VALUE"""),"Nature Reviews Neuroscience") -> Nature Reviews Neuroscience | L56: =IFERROR(__xludf.DUMMYFUNCTION("""COMPUTED_VALUE"""),"Yuske Shibata") -> Yuske Shibata | M56: =IFERROR(__xludf.DUMMYFUNCTION("""COMPUTED_VALUE"""),"YS21BgLoop") -> YS21BgLoop
A57: =IFERROR(__xludf.DUMMYFUNCTION("""COMPUTED_VALUE"""),"Shepherd, 2013") -> Shepherd, 2013 | B57: =IFERROR(__xludf.DUMMYFUNCTION("""COMPUTED_VALUE"""),"DOC") -> DOC | C57: =IFERROR(__xludf.DUMMYFUNCTION("""COMPUTED_VALUE"""),"BIB") -> BIB | D57: =IFERROR(__xludf.DUMMYFUNCTION("""COMPUTED_VALUE"""),"10.1038/nrn3469") -> 10.1038/nrn3469 | E57: =IFERROR(__xludf.DUMMYFUNCTION("""COMPUTED_VALUE"""),"@article{Shepherd_2013, doi = {10.1038/nrn3469}, url = {https://doi.org/10.1038%2Fnrn3469}, year = 2013, month = {mar}, publisher = {Springer Science and Business Media {LLC}}, volume = {14}, number = {4}, pages = {278--291}, author = {Gordon M. "&"G. Shepherd}, title = {Corticostriatal connectivity and its role in disease}, journal = {Nature Reviews Neuroscience} }") -> @article{Shepherd_2013, doi = {10.1038/nrn3469}, url = {https://doi.org/10.1038%2Fnrn3469}, year = 2013, month = {mar}, publisher = {Springer Science and Business Media {LLC}}, volume = {14}, number = {4}, pages = {278--291}, author = {Gordon M. G. Shepherd}, title = {Corticostriatal connectivity and its role in disease}, journal = {Nature Reviews Neuroscience} } | G57: =IFERROR(__xludf.DUMMYFUNCTION("""COMPUTED_VALUE"""),"Article") -> Article | H57: =IFERROR(__xludf.DUMMYFUNCTION("""COMPUTED_VALUE"""),"Gordon M. G. Shepherd") -> Gordon M. G. Shepherd | I57: =IFERROR(__xludf.DUMMYFUNCTION("""COMPUTED_VALUE"""),"Corticostriatal connectivity and its role in disease") -> Corticostriatal connectivity and its role in disease | J57: =IFERROR(__xludf.DUMMYFUNCTION("""COMPUTED_VALUE"""),"Nature Reviews Neuroscience") -> Nature Reviews Neuroscience
A58: =IFERROR(__xludf.DUMMYFUNCTION("""COMPUTED_VALUE"""),"Scott, 2017") -> Scott, 2017 | B58: =IFERROR(__xludf.DUMMYFUNCTION("""COMPUTED_VALUE"""),"DOC") -> DOC | C58: =IFERROR(__xludf.DUMMYFUNCTION("""COMPUTED_VALUE"""),"BIB") -> BIB | D58: =IFERROR(__xludf.DUMMYFUNCTION("""COMPUTED_VALUE"""),"10.1002/cne.24283") -> 10.1002/cne.24283 | E58: =IFERROR(__xludf.DUMMYFUNCTION("""COMPUTED_VALUE"""),"@article{Scott_2017, doi = {10.1002/cne.24283}, url = {https://doi.org/10.1002%2Fcne.24283}, year = 2017, month = {jul}, publisher = {Wiley}, volume = {525}, number = {16}, pages = {3488--3513}, author = {Brian H. Scott and Kadharbatcha S. Saleem"&" and Yukiko Kikuchi and Makoto Fukushima and Mortimer Mishkin and Richard C. Saunders}, title = {Thalamic connections of the core auditory cortex and rostral supratemporal plane in the macaque monkey}, journal = {Journal of Comparative Neurology} }") -> @article{Scott_2017, doi = {10.1002/cne.24283}, url = {https://doi.org/10.1002%2Fcne.24283}, year = 2017, month = {jul}, publisher = {Wiley}, volume = {525}, number = {16}, pages = {3488--3513}, author = {Brian H. Scott and Kadharbatcha S. Saleem and Yukiko Kikuchi and Makoto Fukushima and Mortimer Mishkin and Richard C. Saunders}, title = {Thalamic connections of the core auditory cortex and rostral supratemporal plane in the macaque monkey}, journal = {Journal of Comparative Neurology} } | F58: =IFERROR(__xludf.DUMMYFUNCTION("""COMPUTED_VALUE"""),"Experimental results") -> Experimental results | G58: =IFERROR(__xludf.DUMMYFUNCTION("""COMPUTED_VALUE"""),"Article") -> Article | H58: =IFERROR(__xludf.DUMMYFUNCTION("""COMPUTED_VALUE"""),"Brian H. Scott, Kadharbatcha S. Saleem, Yukiko Kikuchi, Makoto Fukushima, Mortimer Mishkin, Richard C. Saunders") -> Brian H. Scott, Kadharbatcha S. Saleem, Yukiko Kikuchi, Makoto Fukushima, Mortimer Mishkin, Richard C. Saunders | I58: =IFERROR(__xludf.DUMMYFUNCTION("""COMPUTED_VALUE"""),"Thalamic connections of the core auditory cortex and rostral supratemporal plane in the macaque monkey") -> Thalamic connections of the core auditory cortex and rostral supratemporal plane in the macaque monkey | J58: =IFERROR(__xludf.DUMMYFUNCTION("""COMPUTED_VALUE"""),"Journal of Comparative Neurology") -> Journal of Comparative Neurology | L58: =IFERROR(__xludf.DUMMYFUNCTION("""COMPUTED_VALUE"""),"Hiroshi Yamakawa") -> Hiroshi Yamakawa | M58: =IFERROR(__xludf.DUMMYFUNCTION("""COMPUTED_VALUE"""),"HY22DAA") -> HY22DAA
A59: =IFERROR(__xludf.DUMMYFUNCTION("""COMPUTED_VALUE"""),"Schnyder, 1985") -> Schnyder, 1985 | B59: =IFERROR(__xludf.DUMMYFUNCTION("""COMPUTED_VALUE"""),"DOC") -> DOC | C59: =IFERROR(__xludf.DUMMYFUNCTION("""COMPUTED_VALUE"""),"BIB") -> BIB | D59: =IFERROR(__xludf.DUMMYFUNCTION("""COMPUTED_VALUE"""),"10.1016/0006-8993(85)90520-7") -> 10.1016/0006-8993(85)90520-7 | E59: =IFERROR(__xludf.DUMMYFUNCTION("""COMPUTED_VALUE"""),"@article{Schnyder_1985, doi = {10.1016/0006-8993(85)90520-7}, url = {https://doi.org/10.1016%2F0006-8993%2885%2990520-7}, year = 1985, month = {mar}, publisher = {Elsevier {BV}}, volume = {329}, number = {1-2}, pages = {151--160}, author = {H. Sc"&"hnyder and H. Reisine and K. Hepp and V. Henn}, title = {Frontal eye field projection to the paramedian pontine reticular formation traced with wheat germ agglutinin in the monkey}, journal = {Brain Research} }") -> @article{Schnyder_1985, doi = {10.1016/0006-8993(85)90520-7}, url = {https://doi.org/10.1016%2F0006-8993%2885%2990520-7}, year = 1985, month = {mar}, publisher = {Elsevier {BV}}, volume = {329}, number = {1-2}, pages = {151--160}, author = {H. Schnyder and H. Reisine and K. Hepp and V. Henn}, title = {Frontal eye field projection to the paramedian pontine reticular formation traced with wheat germ agglutinin in the monkey}, journal = {Brain Research} } | G59: =IFERROR(__xludf.DUMMYFUNCTION("""COMPUTED_VALUE"""),"Article") -> Article | H59: =IFERROR(__xludf.DUMMYFUNCTION("""COMPUTED_VALUE"""),"H. Schnyder, H. Reisine, K. Hepp, V. Henn") -> H. Schnyder, H. Reisine, K. Hepp, V. Henn | I59: =IFERROR(__xludf.DUMMYFUNCTION("""COMPUTED_VALUE"""),"Frontal eye field projection to the paramedian pontine reticular formation traced with wheat germ agglutinin in the monkey") -> Frontal eye field projection to the paramedian pontine reticular formation traced with wheat germ agglutinin in the monkey | J59: =IFERROR(__xludf.DUMMYFUNCTION("""COMPUTED_VALUE"""),"Brain Research") -> Brain Research | L59: =IFERROR(__xludf.DUMMYFUNCTION("""COMPUTED_VALUE"""),"Yoshinasa Tawatsji") -> Yoshinasa Tawatsji | M59: =IFERROR(__xludf.DUMMYFUNCTION("""COMPUTED_VALUE"""),"Oculomotor") -> Oculomotor
A60: =IFERROR(__xludf.DUMMYFUNCTION("""COMPUTED_VALUE"""),"Saga, 2017") -> Saga, 2017 | B60: =IFERROR(__xludf.DUMMYFUNCTION("""COMPUTED_VALUE"""),"DOC") -> DOC | C60: =IFERROR(__xludf.DUMMYFUNCTION("""COMPUTED_VALUE"""),"BIB") -> BIB | D60: =IFERROR(__xludf.DUMMYFUNCTION("""COMPUTED_VALUE"""),"10.3389/fnana.2017.00030") -> 10.3389/fnana.2017.00030 | E60: =IFERROR(__xludf.DUMMYFUNCTION("""COMPUTED_VALUE"""),"@article{Saga_2017, doi = {10.3389/fnana.2017.00030}, url = {https://doi.org/10.3389%2Ffnana.2017.00030}, year = 2017, month = {apr}, publisher = {Frontiers Media {SA}}, volume = {11}, author = {Yosuke Saga and Eiji Hoshi and L{\'{e}}on Tremblay}, "&" title = {Roles of Multiple Globus Pallidus Territories of Monkeys and Humans in Motivation, Cognition and Action: An Anatomical, Physiological and Pathophysiological Review}, journal = {Frontiers in Neuroanatomy} }") -> @article{Saga_2017, doi = {10.3389/fnana.2017.00030}, url = {https://doi.org/10.3389%2Ffnana.2017.00030}, year = 2017, month = {apr}, publisher = {Frontiers Media {SA}}, volume = {11}, author = {Yosuke Saga and Eiji Hoshi and L{\'{e}}on Tremblay}, title = {Roles of Multiple Globus Pallidus Territories of Monkeys and Humans in Motivation, Cognition and Action: An Anatomical, Physiological and Pathophysiological Review}, journal = {Frontiers in Neuroanatomy} } | G60: =IFERROR(__xludf.DUMMYFUNCTION("""COMPUTED_VALUE"""),"Article") -> Article | H60: =IFERROR(__xludf.DUMMYFUNCTION("""COMPUTED_VALUE"""),"Yosuke Saga, Eiji Hoshi, L{\'{e}}on Tremblay") -> Yosuke Saga, Eiji Hoshi, L{\'{e}}on Tremblay | I60: =IFERROR(__xludf.DUMMYFUNCTION("""COMPUTED_VALUE"""),"Roles of Multiple Globus Pallidus Territories of Monkeys and Humans in Motivation, Cognition and Action: An Anatomical, Physiological and Pathophysiological Review") -> Roles of Multiple Globus Pallidus Territories of Monkeys and Humans in Motivation, Cognition and Action: An Anatomical, Physiological and Pathophysiological Review | J60: =IFERROR(__xludf.DUMMYFUNCTION("""COMPUTED_VALUE"""),"Frontiers in Neuroanatomy") -> Frontiers in Neuroanatomy | L60: =IFERROR(__xludf.DUMMYFUNCTION("""COMPUTED_VALUE"""),"Yuske Shibata") -> Yuske Shibata | M60: =IFERROR(__xludf.DUMMYFUNCTION("""COMPUTED_VALUE"""),"YS21BgLoop") -> YS21BgLoop
A61: =IFERROR(__xludf.DUMMYFUNCTION("""COMPUTED_VALUE"""),"Saga, 2017") -> Saga, 2017 | B61: =IFERROR(__xludf.DUMMYFUNCTION("""COMPUTED_VALUE"""),"DOC") -> DOC | C61: =IFERROR(__xludf.DUMMYFUNCTION("""COMPUTED_VALUE"""),"BIB") -> BIB | D61: =IFERROR(__xludf.DUMMYFUNCTION("""COMPUTED_VALUE"""),"10.3389/fnana.2017.00030") -> 10.3389/fnana.2017.00030 | E61: =IFERROR(__xludf.DUMMYFUNCTION("""COMPUTED_VALUE"""),"@article{Saga_2017, doi = {10.3389/fnana.2017.00030}, url = {https://doi.org/10.3389%2Ffnana.2017.00030}, year = 2017, month = {apr}, publisher = {Frontiers Media {SA}}, volume = {11}, author = {Yosuke Saga and Eiji Hoshi and L{\'{e}}on Tremblay}, "&" title = {Roles of Multiple Globus Pallidus Territories of Monkeys and Humans in Motivation, Cognition and Action: An Anatomical, Physiological and Pathophysiological Review}, journal = {Frontiers in Neuroanatomy} }") -> @article{Saga_2017, doi = {10.3389/fnana.2017.00030}, url = {https://doi.org/10.3389%2Ffnana.2017.00030}, year = 2017, month = {apr}, publisher = {Frontiers Media {SA}}, volume = {11}, author = {Yosuke Saga and Eiji Hoshi and L{\'{e}}on Tremblay}, title = {Roles of Multiple Globus Pallidus Territories of Monkeys and Humans in Motivation, Cognition and Action: An Anatomical, Physiological and Pathophysiological Review}, journal = {Frontiers in Neuroanatomy} } | G61: =IFERROR(__xludf.DUMMYFUNCTION("""COMPUTED_VALUE"""),"Article") -> Article | H61: =IFERROR(__xludf.DUMMYFUNCTION("""COMPUTED_VALUE"""),"Yosuke Saga, Eiji Hoshi, L{\'{e}}on Tremblay") -> Yosuke Saga, Eiji Hoshi, L{\'{e}}on Tremblay | I61: =IFERROR(__xludf.DUMMYFUNCTION("""COMPUTED_VALUE"""),"Roles of Multiple Globus Pallidus Territories of Monkeys and Humans in Motivation, Cognition and Action: An Anatomical, Physiological and Pathophysiological Review") -> Roles of Multiple Globus Pallidus Territories of Monkeys and Humans in Motivation, Cognition and Action: An Anatomical, Physiological and Pathophysiological Review | J61: =IFERROR(__xludf.DUMMYFUNCTION("""COMPUTED_VALUE"""),"Frontiers in Neuroanatomy") -> Frontiers in Neuroanatomy
A62: =IFERROR(__xludf.DUMMYFUNCTION("""COMPUTED_VALUE"""),"Rowland, 2013") -> Rowland, 2013 | B62: =IFERROR(__xludf.DUMMYFUNCTION("""COMPUTED_VALUE"""),"DOC") -> DOC | C62: =IFERROR(__xludf.DUMMYFUNCTION("""COMPUTED_VALUE"""),"BIB") -> BIB | D62: =IFERROR(__xludf.DUMMYFUNCTION("""COMPUTED_VALUE"""),"10.1523/JNEUROSCI.1046-13.2013") -> 10.1523/JNEUROSCI.1046-13.2013 | E62: =IFERROR(__xludf.DUMMYFUNCTION("""COMPUTED_VALUE"""),"@article{Rowland_2013, doi = {10.1523/jneurosci.1046-13.2013}, url = {https://doi.org/10.1523%2Fjneurosci.1046-13.2013}, year = 2013, month = {sep}, publisher = {Society for Neuroscience}, volume = {33}, number = {37}, pages = {14889--14898}, aut"&"hor = {D. C. Rowland and A. P. Weible and I. R. Wickersham and H. Wu and M. Mayford and M. P. Witter and C. G. Kentros}, title = {Transgenically Targeted Rabies Virus Demonstrates a Major Monosynaptic Projection from Hippocampal Area {CA}2 to Medial Ento"&"rhinal Layer {II} Neurons}, journal = {Journal of Neuroscience} }") -> @article{Rowland_2013, doi = {10.1523/jneurosci.1046-13.2013}, url = {https://doi.org/10.1523%2Fjneurosci.1046-13.2013}, year = 2013, month = {sep}, publisher = {Society for Neuroscience}, volume = {33}, number = {37}, pages = {14889--14898}, author = {D. C. Rowland and A. P. Weible and I. R. Wickersham and H. Wu and M. Mayford and M. P. Witter and C. G. Kentros}, title = {Transgenically Targeted Rabies Virus Demonstrates a Major Monosynaptic Projection from Hippocampal Area {CA}2 to Medial Entorhinal Layer {II} Neurons}, journal = {Journal of Neuroscience} } | F62: =IFERROR(__xludf.DUMMYFUNCTION("""COMPUTED_VALUE"""),"Experimental results") -> Experimental results | G62: =IFERROR(__xludf.DUMMYFUNCTION("""COMPUTED_VALUE"""),"Article") -> Article | H62: =IFERROR(__xludf.DUMMYFUNCTION("""COMPUTED_VALUE"""),"D. C. Rowland, A. P. Weible, I. R. Wickersham, H. Wu, M. Mayford, M. P. Witter, C. G. Kentros") -> D. C. Rowland, A. P. Weible, I. R. Wickersham, H. Wu, M. Mayford, M. P. Witter, C. G. Kentros | I62: =IFERROR(__xludf.DUMMYFUNCTION("""COMPUTED_VALUE"""),"Transgenically Targeted Rabies Virus Demonstrates a Major Monosynaptic Projection from Hippocampal Area {CA}2 to Medial Entorhinal Layer {II} Neurons") -> Transgenically Targeted Rabies Virus Demonstrates a Major Monosynaptic Projection from Hippocampal Area {CA}2 to Medial Entorhinal Layer {II} Neurons | J62: =IFERROR(__xludf.DUMMYFUNCTION("""COMPUTED_VALUE"""),"Journal of Neuroscience") -> Journal of Neuroscience | L62: =IFERROR(__xludf.DUMMYFUNCTION("""COMPUTED_VALUE"""),"Yuske Shibata") -> Yuske Shibata | M62: =IFERROR(__xludf.DUMMYFUNCTION("""COMPUTED_VALUE"""),"YS21CredibilityCheck") -> YS21CredibilityCheck
A63: =IFERROR(__xludf.DUMMYFUNCTION("""COMPUTED_VALUE"""),"Rondi-Reig, 2014") -> Rondi-Reig, 2014 | B63: =IFERROR(__xludf.DUMMYFUNCTION("""COMPUTED_VALUE"""),"DOC") -> DOC | C63: =IFERROR(__xludf.DUMMYFUNCTION("""COMPUTED_VALUE"""),"BIB") -> BIB | D63: =IFERROR(__xludf.DUMMYFUNCTION("""COMPUTED_VALUE"""),"10.3389/fnsys.2014.00205") -> 10.3389/fnsys.2014.00205 | E63: =IFERROR(__xludf.DUMMYFUNCTION("""COMPUTED_VALUE"""),"@article{Rondi-Reig_2014, doi = {10.3389/fnsys.2014.00205}, url = {https://doi.org/10.3389%2Ffnsys.2014.00205}, year = 2014, month = {nov}, publisher = {Frontiers Media {SA}}, volume = {8}, author = "&"{Laure Rondi-Reig and Anne-Lise Paradis and Julie M. Lefort and Benedicte M. Babayan and Christine Tobin}, title = {How the cerebellum may monitor sensory information for spatial representation}, journal = {Frontiers in Systems Neuroscienc"&"e} }") -> @article{Rondi-Reig_2014, doi = {10.3389/fnsys.2014.00205}, url = {https://doi.org/10.3389%2Ffnsys.2014.00205}, year = 2014, month = {nov}, publisher = {Frontiers Media {SA}}, volume = {8}, author = {Laure Rondi-Reig and Anne-Lise Paradis and Julie M. Lefort and Benedicte M. Babayan and Christine Tobin}, title = {How the cerebellum may monitor sensory information for spatial representation}, journal = {Frontiers in Systems Neuroscience} } | G63: =IFERROR(__xludf.DUMMYFUNCTION("""COMPUTED_VALUE"""),"Article") -> Article | H63: =IFERROR(__xludf.DUMMYFUNCTION("""COMPUTED_VALUE"""),"Laure Rondi-Reig, Anne-Lise Paradis, Julie M. Lefort, Benedicte M. Babayan, Christine Tobin") -> Laure Rondi-Reig, Anne-Lise Paradis, Julie M. Lefort, Benedicte M. Babayan, Christine Tobin | I63: =IFERROR(__xludf.DUMMYFUNCTION("""COMPUTED_VALUE"""),"How the cerebellum may monitor sensory information for spatial representation") -> How the cerebellum may monitor sensory information for spatial representation | J63: =IFERROR(__xludf.DUMMYFUNCTION("""COMPUTED_VALUE"""),"Frontiers in Systems Neuroscience") -> Frontiers in Systems Neuroscience | L63: =IFERROR(__xludf.DUMMYFUNCTION("""COMPUTED_VALUE"""),"Hiroshi Yamakawa") -> Hiroshi Yamakawa | M63: =IFERROR(__xludf.DUMMYFUNCTION("""COMPUTED_VALUE"""),"HY20Cerebellum") -> HY20Cerebellum
A64: =IFERROR(__xludf.DUMMYFUNCTION("""COMPUTED_VALUE"""),"Romanski, 2009") -> Romanski, 2009 | B64: =IFERROR(__xludf.DUMMYFUNCTION("""COMPUTED_VALUE"""),"DOC") -> DOC | C64: =IFERROR(__xludf.DUMMYFUNCTION("""COMPUTED_VALUE"""),"BIB") -> BIB | D64: =IFERROR(__xludf.DUMMYFUNCTION("""COMPUTED_VALUE"""),"10.1146/annurev.neuro.051508.135431") -> 10.1146/annurev.neuro.051508.135431 | E64: =IFERROR(__xludf.DUMMYFUNCTION("""COMPUTED_VALUE"""),"@article{Romanski_2009, doi = {10.1146/annurev.neuro.051508.135431}, url = {https://doi.org/10.1146%2Fannurev.neuro.051508.135431}, year = 2009, month = {jun}, publisher = {Annual Reviews}, volume = {32}, number = {1}, pages = {315--346}, author "&"= {Lizabeth M. Romanski and Bruno B. Averbeck}, title = {The Primate Cortical Auditory System and Neural Representation of Conspecific Vocalizations}, journal = {Annual Review of Neuroscience} }") -> @article{Romanski_2009, doi = {10.1146/annurev.neuro.051508.135431}, url = {https://doi.org/10.1146%2Fannurev.neuro.051508.135431}, year = 2009, month = {jun}, publisher = {Annual Reviews}, volume = {32}, number = {1}, pages = {315--346}, author = {Lizabeth M. Romanski and Bruno B. Averbeck}, title = {The Primate Cortical Auditory System and Neural Representation of Conspecific Vocalizations}, journal = {Annual Review of Neuroscience} } | G64: =IFERROR(__xludf.DUMMYFUNCTION("""COMPUTED_VALUE"""),"Article") -> Article | H64: =IFERROR(__xludf.DUMMYFUNCTION("""COMPUTED_VALUE"""),"Lizabeth M. Romanski, Bruno B. Averbeck") -> Lizabeth M. Romanski, Bruno B. Averbeck | I64: =IFERROR(__xludf.DUMMYFUNCTION("""COMPUTED_VALUE"""),"The Primate Cortical Auditory System and Neural Representation of Conspecific Vocalizations") -> The Primate Cortical Auditory System and Neural Representation of Conspecific Vocalizations | J64: =IFERROR(__xludf.DUMMYFUNCTION("""COMPUTED_VALUE"""),"Annual Review of Neuroscience") -> Annual Review of Neuroscience | L64: =IFERROR(__xludf.DUMMYFUNCTION("""COMPUTED_VALUE"""),"Hiroshi Yamakawa") -> Hiroshi Yamakawa | M64: =IFERROR(__xludf.DUMMYFUNCTION("""COMPUTED_VALUE"""),"HY22DAA") -> HY22DAA
A65: =IFERROR(__xludf.DUMMYFUNCTION("""COMPUTED_VALUE"""),"Rolls, 2013") -> Rolls, 2013 | B65: =IFERROR(__xludf.DUMMYFUNCTION("""COMPUTED_VALUE"""),"DOC") -> DOC | C65: =IFERROR(__xludf.DUMMYFUNCTION("""COMPUTED_VALUE"""),"BIB") -> BIB | D65: =IFERROR(__xludf.DUMMYFUNCTION("""COMPUTED_VALUE"""),"10.3389/fnsys.2013.00074") -> 10.3389/fnsys.2013.00074 | E65: =IFERROR(__xludf.DUMMYFUNCTION("""COMPUTED_VALUE"""),"@article{Rolls_2013, doi = {10.3389/fnsys.2013.00074}, url = {https://doi.org/10.3389%2Ffnsys.2013.00074}, year = 2013, publisher = {Frontiers Media {SA}}, volume = {7}, author = {Edmund T. Rolls}, title = {The mechanisms for pattern completion and"&" pattern separation in the hippocampus}, journal = {Frontiers in Systems Neuroscience} }") -> @article{Rolls_2013, doi = {10.3389/fnsys.2013.00074}, url = {https://doi.org/10.3389%2Ffnsys.2013.00074}, year = 2013, publisher = {Frontiers Media {SA}}, volume = {7}, author = {Edmund T. Rolls}, title = {The mechanisms for pattern completion and pattern separation in the hippocampus}, journal = {Frontiers in Systems Neuroscience} } | G65: =IFERROR(__xludf.DUMMYFUNCTION("""COMPUTED_VALUE"""),"Article") -> Article | H65: =IFERROR(__xludf.DUMMYFUNCTION("""COMPUTED_VALUE"""),"Edmund T. Rolls") -> Edmund T. Rolls | I65: =IFERROR(__xludf.DUMMYFUNCTION("""COMPUTED_VALUE"""),"The mechanisms for pattern completion and pattern separation in the hippocampus") -> The mechanisms for pattern completion and pattern separation in the hippocampus | J65: =IFERROR(__xludf.DUMMYFUNCTION("""COMPUTED_VALUE"""),"Frontiers in Systems Neuroscience") -> Frontiers in Systems Neuroscience | L65: =IFERROR(__xludf.DUMMYFUNCTION("""COMPUTED_VALUE"""),"Ayako Fukawa") -> Ayako Fukawa | M65: =IFERROR(__xludf.DUMMYFUNCTION("""COMPUTED_VALUE"""),"AT20HippocampalFormation") -> AT20HippocampalFormation
A66: =IFERROR(__xludf.DUMMYFUNCTION("""COMPUTED_VALUE"""),"Rolls, 2013") -> Rolls, 2013 | B66: =IFERROR(__xludf.DUMMYFUNCTION("""COMPUTED_VALUE"""),"DOC") -> DOC | C66: =IFERROR(__xludf.DUMMYFUNCTION("""COMPUTED_VALUE"""),"BIB") -> BIB | D66: =IFERROR(__xludf.DUMMYFUNCTION("""COMPUTED_VALUE"""),"10.3389/fnsys.2013.00074") -> 10.3389/fnsys.2013.00074 | E66: =IFERROR(__xludf.DUMMYFUNCTION("""COMPUTED_VALUE"""),"@article{Rolls_2013, doi = {10.3389/fnsys.2013.00074}, url = {https://doi.org/10.3389%2Ffnsys.2013.00074}, year = 2013, publisher = {Frontiers Media {SA}}, volume = {7}, author = {Edmund T. Rolls}, title = {The mechanisms for pattern completion and"&" pattern separation in the hippocampus}, journal = {Frontiers in Systems Neuroscience} }") -> @article{Rolls_2013, doi = {10.3389/fnsys.2013.00074}, url = {https://doi.org/10.3389%2Ffnsys.2013.00074}, year = 2013, publisher = {Frontiers Media {SA}}, volume = {7}, author = {Edmund T. Rolls}, title = {The mechanisms for pattern completion and pattern separation in the hippocampus}, journal = {Frontiers in Systems Neuroscience} } | G66: =IFERROR(__xludf.DUMMYFUNCTION("""COMPUTED_VALUE"""),"Article") -> Article | H66: =IFERROR(__xludf.DUMMYFUNCTION("""COMPUTED_VALUE"""),"Edmund T. Rolls") -> Edmund T. Rolls | I66: =IFERROR(__xludf.DUMMYFUNCTION("""COMPUTED_VALUE"""),"The mechanisms for pattern completion and pattern separation in the hippocampus") -> The mechanisms for pattern completion and pattern separation in the hippocampus | J66: =IFERROR(__xludf.DUMMYFUNCTION("""COMPUTED_VALUE"""),"Frontiers in Systems Neuroscience") -> Frontiers in Systems Neuroscience
A67: =IFERROR(__xludf.DUMMYFUNCTION("""COMPUTED_VALUE"""),"Rolls, 2013") -> Rolls, 2013 | B67: =IFERROR(__xludf.DUMMYFUNCTION("""COMPUTED_VALUE"""),"DOC") -> DOC | C67: =IFERROR(__xludf.DUMMYFUNCTION("""COMPUTED_VALUE"""),"BIB") -> BIB | D67: =IFERROR(__xludf.DUMMYFUNCTION("""COMPUTED_VALUE"""),"10.3389/fnsys.2013.00074") -> 10.3389/fnsys.2013.00074 | E67: =IFERROR(__xludf.DUMMYFUNCTION("""COMPUTED_VALUE"""),"@article{Rolls_2013, doi = {10.3389/fnsys.2013.00074}, url = {https://doi.org/10.3389%2Ffnsys.2013.00074}, year = 2013, publisher = {Frontiers Media {SA}}, volume = {7}, author = {Edmund T. Rolls}, title = {The mechanisms for pattern completion and"&" pattern separation in the hippocampus}, journal = {Frontiers in Systems Neuroscience} }") -> @article{Rolls_2013, doi = {10.3389/fnsys.2013.00074}, url = {https://doi.org/10.3389%2Ffnsys.2013.00074}, year = 2013, publisher = {Frontiers Media {SA}}, volume = {7}, author = {Edmund T. Rolls}, title = {The mechanisms for pattern completion and pattern separation in the hippocampus}, journal = {Frontiers in Systems Neuroscience} } | G67: =IFERROR(__xludf.DUMMYFUNCTION("""COMPUTED_VALUE"""),"Article") -> Article | H67: =IFERROR(__xludf.DUMMYFUNCTION("""COMPUTED_VALUE"""),"Edmund T. Rolls") -> Edmund T. Rolls | I67: =IFERROR(__xludf.DUMMYFUNCTION("""COMPUTED_VALUE"""),"The mechanisms for pattern completion and pattern separation in the hippocampus") -> The mechanisms for pattern completion and pattern separation in the hippocampus | J67: =IFERROR(__xludf.DUMMYFUNCTION("""COMPUTED_VALUE"""),"Frontiers in Systems Neuroscience") -> Frontiers in Systems Neuroscience
A68: =IFERROR(__xludf.DUMMYFUNCTION("""COMPUTED_VALUE"""),"Rolls, 2007") -> Rolls, 2007 | B68: =IFERROR(__xludf.DUMMYFUNCTION("""COMPUTED_VALUE"""),"DOC") -> DOC | C68: =IFERROR(__xludf.DUMMYFUNCTION("""COMPUTED_VALUE"""),"BIB") -> BIB | D68: =IFERROR(__xludf.DUMMYFUNCTION("""COMPUTED_VALUE"""),"10.1101/lm.631207 ") -> 10.1101/lm.631207 | E68: =IFERROR(__xludf.DUMMYFUNCTION("""COMPUTED_VALUE"""),"@article{Rolls_2007, doi = {10.1101/lm.631207}, url = {https://doi.org/10.1101%2Flm.631207}, year = 2007, month = {nov}, publisher = {Cold Spring Harbor Laboratory}, volume = {14}, number = {11}, pages = {714--731}, author = {E. T. Rolls}, title"&" = {An attractor network in the hippocampus: Theory and neurophysiology}, journal = {Learning {\&}amp$\mathsemicolon$ Memory} }") -> @article{Rolls_2007, doi = {10.1101/lm.631207}, url = {https://doi.org/10.1101%2Flm.631207}, year = 2007, month = {nov}, publisher = {Cold Spring Harbor Laboratory}, volume = {14}, number = {11}, pages = {714--731}, author = {E. T. Rolls}, title = {An attractor network in the hippocampus: Theory and neurophysiology}, journal = {Learning {\&}amp$\mathsemicolon$ Memory} } | G68: =IFERROR(__xludf.DUMMYFUNCTION("""COMPUTED_VALUE"""),"Article") -> Article | H68: =IFERROR(__xludf.DUMMYFUNCTION("""COMPUTED_VALUE"""),"E. T. Rolls") -> E. T. Rolls | I68: =IFERROR(__xludf.DUMMYFUNCTION("""COMPUTED_VALUE"""),"An attractor network in the hippocampus: Theory and neurophysiology") -> An attractor network in the hippocampus: Theory and neurophysiology | J68: =IFERROR(__xludf.DUMMYFUNCTION("""COMPUTED_VALUE"""),"Learning {\&}amp$\mathsemicolon$ Memory") -> Learning {\&}amp$\mathsemicolon$ Memory | L68: =IFERROR(__xludf.DUMMYFUNCTION("""COMPUTED_VALUE"""),"Ayako Fukawa") -> Ayako Fukawa | M68: =IFERROR(__xludf.DUMMYFUNCTION("""COMPUTED_VALUE"""),"AT20HippocampalFormation") -> AT20HippocampalFormation
A69: =IFERROR(__xludf.DUMMYFUNCTION("""COMPUTED_VALUE"""),"Rolls, 2007") -> Rolls, 2007 | B69: =IFERROR(__xludf.DUMMYFUNCTION("""COMPUTED_VALUE"""),"DOC") -> DOC | C69: =IFERROR(__xludf.DUMMYFUNCTION("""COMPUTED_VALUE"""),"BIB") -> BIB | D69: =IFERROR(__xludf.DUMMYFUNCTION("""COMPUTED_VALUE"""),"10.1101/lm.631207") -> 10.1101/lm.631207 | E69: =IFERROR(__xludf.DUMMYFUNCTION("""COMPUTED_VALUE"""),"@article{Rolls_2007, doi = {10.1101/lm.631207}, url = {https://doi.org/10.1101%2Flm.631207}, year = 2007, month = {nov}, publisher = {Cold Spring Harbor Laboratory}, volume = {14}, number = {11}, pages = {714--731}, author = {E. T. Rolls}, title"&" = {An attractor network in the hippocampus: Theory and neurophysiology}, journal = {Learning {\&}amp$\mathsemicolon$ Memory} }") -> @article{Rolls_2007, doi = {10.1101/lm.631207}, url = {https://doi.org/10.1101%2Flm.631207}, year = 2007, month = {nov}, publisher = {Cold Spring Harbor Laboratory}, volume = {14}, number = {11}, pages = {714--731}, author = {E. T. Rolls}, title = {An attractor network in the hippocampus: Theory and neurophysiology}, journal = {Learning {\&}amp$\mathsemicolon$ Memory} } | G69: =IFERROR(__xludf.DUMMYFUNCTION("""COMPUTED_VALUE"""),"Article") -> Article | H69: =IFERROR(__xludf.DUMMYFUNCTION("""COMPUTED_VALUE"""),"E. T. Rolls") -> E. T. Rolls | I69: =IFERROR(__xludf.DUMMYFUNCTION("""COMPUTED_VALUE"""),"An attractor network in the hippocampus: Theory and neurophysiology") -> An attractor network in the hippocampus: Theory and neurophysiology | J69: =IFERROR(__xludf.DUMMYFUNCTION("""COMPUTED_VALUE"""),"Learning {\&}amp$\mathsemicolon$ Memory") -> Learning {\&}amp$\mathsemicolon$ Memory
A70: =IFERROR(__xludf.DUMMYFUNCTION("""COMPUTED_VALUE"""),"Rolls, 1998") -> Rolls, 1998 | B70: =IFERROR(__xludf.DUMMYFUNCTION("""COMPUTED_VALUE"""),"DOC") -> DOC | C70: =IFERROR(__xludf.DUMMYFUNCTION("""COMPUTED_VALUE"""),"BIB") -> BIB | D70: =IFERROR(__xludf.DUMMYFUNCTION("""COMPUTED_VALUE"""),"10.1152/jn.1998.79.4.1797") -> 10.1152/jn.1998.79.4.1797 | E70: =IFERROR(__xludf.DUMMYFUNCTION("""COMPUTED_VALUE"""),"@article{Rolls_1998, doi = {10.1152/jn.1998.79.4.1797}, url = {https://doi.org/10.1152%2Fjn.1998.79.4.1797}, year = 1998, month = {apr}, publisher = {American Physiological Society}, volume = {79}, number = {4}, pages = {1797--1813}, author = {Ed"&"mund T. Rolls and Alessandro Treves and Robert G. Robertson and Pierre Georges-Fran{\c{c}}ois and Stefano Panzeri}, title = {Information About Spatial View in an Ensemble of Primate Hippocampal Cells}, journal = {Journal of Neurophysiology} }") -> @article{Rolls_1998, doi = {10.1152/jn.1998.79.4.1797}, url = {https://doi.org/10.1152%2Fjn.1998.79.4.1797}, year = 1998, month = {apr}, publisher = {American Physiological Society}, volume = {79}, number = {4}, pages = {1797--1813}, author = {Edmund T. Rolls and Alessandro Treves and Robert G. Robertson and Pierre Georges-Fran{\c{c}}ois and Stefano Panzeri}, title = {Information About Spatial View in an Ensemble of Primate Hippocampal Cells}, journal = {Journal of Neurophysiology} } | G70: =IFERROR(__xludf.DUMMYFUNCTION("""COMPUTED_VALUE"""),"Article") -> Article | H70: =IFERROR(__xludf.DUMMYFUNCTION("""COMPUTED_VALUE"""),"Edmund T. Rolls, Alessandro Treves, Robert G. Robertson, Pierre Georges-Fran{\c{c}}ois, Stefano Panzeri") -> Edmund T. Rolls, Alessandro Treves, Robert G. Robertson, Pierre Georges-Fran{\c{c}}ois, Stefano Panzeri | I70: =IFERROR(__xludf.DUMMYFUNCTION("""COMPUTED_VALUE"""),"Information About Spatial View in an Ensemble of Primate Hippocampal Cells") -> Information About Spatial View in an Ensemble of Primate Hippocampal Cells | J70: =IFERROR(__xludf.DUMMYFUNCTION("""COMPUTED_VALUE"""),"Journal of Neurophysiology") -> Journal of Neurophysiology | L70: =IFERROR(__xludf.DUMMYFUNCTION("""COMPUTED_VALUE"""),"Yuske Shibata") -> Yuske Shibata | M70: =IFERROR(__xludf.DUMMYFUNCTION("""COMPUTED_VALUE"""),"YS21CredibilityCheck") -> YS21CredibilityCheck
A71: =IFERROR(__xludf.DUMMYFUNCTION("""COMPUTED_VALUE"""),"Rolls, 1998") -> Rolls, 1998 | B71: =IFERROR(__xludf.DUMMYFUNCTION("""COMPUTED_VALUE"""),"DOC") -> DOC | C71: =IFERROR(__xludf.DUMMYFUNCTION("""COMPUTED_VALUE"""),"BIB") -> BIB | D71: =IFERROR(__xludf.DUMMYFUNCTION("""COMPUTED_VALUE"""),"10.1152/jn.1998.79.4.1797") -> 10.1152/jn.1998.79.4.1797 | E71: =IFERROR(__xludf.DUMMYFUNCTION("""COMPUTED_VALUE"""),"@article{Rolls_1998, doi = {10.1152/jn.1998.79.4.1797}, url = {https://doi.org/10.1152%2Fjn.1998.79.4.1797}, year = 1998, month = {apr}, publisher = {American Physiological Society}, volume = {79}, number = {4}, pages = {1797--1813}, author = {Ed"&"mund T. Rolls and Alessandro Treves and Robert G. Robertson and Pierre Georges-Fran{\c{c}}ois and Stefano Panzeri}, title = {Information About Spatial View in an Ensemble of Primate Hippocampal Cells}, journal = {Journal of Neurophysiology} }") -> @article{Rolls_1998, doi = {10.1152/jn.1998.79.4.1797}, url = {https://doi.org/10.1152%2Fjn.1998.79.4.1797}, year = 1998, month = {apr}, publisher = {American Physiological Society}, volume = {79}, number = {4}, pages = {1797--1813}, author = {Edmund T. Rolls and Alessandro Treves and Robert G. Robertson and Pierre Georges-Fran{\c{c}}ois and Stefano Panzeri}, title = {Information About Spatial View in an Ensemble of Primate Hippocampal Cells}, journal = {Journal of Neurophysiology} } | G71: =IFERROR(__xludf.DUMMYFUNCTION("""COMPUTED_VALUE"""),"Article") -> Article | H71: =IFERROR(__xludf.DUMMYFUNCTION("""COMPUTED_VALUE"""),"Edmund T. Rolls, Alessandro Treves, Robert G. Robertson, Pierre Georges-Fran{\c{c}}ois, Stefano Panzeri") -> Edmund T. Rolls, Alessandro Treves, Robert G. Robertson, Pierre Georges-Fran{\c{c}}ois, Stefano Panzeri | I71: =IFERROR(__xludf.DUMMYFUNCTION("""COMPUTED_VALUE"""),"Information About Spatial View in an Ensemble of Primate Hippocampal Cells") -> Information About Spatial View in an Ensemble of Primate Hippocampal Cells | J71: =IFERROR(__xludf.DUMMYFUNCTION("""COMPUTED_VALUE"""),"Journal of Neurophysiology") -> Journal of Neurophysiology | L71: =IFERROR(__xludf.DUMMYFUNCTION("""COMPUTED_VALUE"""),"Ayako Fukawa") -> Ayako Fukawa | M71: =IFERROR(__xludf.DUMMYFUNCTION("""COMPUTED_VALUE"""),"AT20HippocampalFormation") -> AT20HippocampalFormation
A72: =IFERROR(__xludf.DUMMYFUNCTION("""COMPUTED_VALUE"""),"Rolls, 1998") -> Rolls, 1998 | B72: =IFERROR(__xludf.DUMMYFUNCTION("""COMPUTED_VALUE"""),"DOC") -> DOC | C72: =IFERROR(__xludf.DUMMYFUNCTION("""COMPUTED_VALUE"""),"BIB") -> BIB | D72: =IFERROR(__xludf.DUMMYFUNCTION("""COMPUTED_VALUE"""),"10.1152/jn.1998.79.4.1797") -> 10.1152/jn.1998.79.4.1797 | E72: =IFERROR(__xludf.DUMMYFUNCTION("""COMPUTED_VALUE"""),"@article{Rolls_1998, doi = {10.1152/jn.1998.79.4.1797}, url = {https://doi.org/10.1152%2Fjn.1998.79.4.1797}, year = 1998, month = {apr}, publisher = {American Physiological Society}, volume = {79}, number = {4}, pages = {1797--1813}, author = {Ed"&"mund T. Rolls and Alessandro Treves and Robert G. Robertson and Pierre Georges-Fran{\c{c}}ois and Stefano Panzeri}, title = {Information About Spatial View in an Ensemble of Primate Hippocampal Cells}, journal = {Journal of Neurophysiology} }") -> @article{Rolls_1998, doi = {10.1152/jn.1998.79.4.1797}, url = {https://doi.org/10.1152%2Fjn.1998.79.4.1797}, year = 1998, month = {apr}, publisher = {American Physiological Society}, volume = {79}, number = {4}, pages = {1797--1813}, author = {Edmund T. Rolls and Alessandro Treves and Robert G. Robertson and Pierre Georges-Fran{\c{c}}ois and Stefano Panzeri}, title = {Information About Spatial View in an Ensemble of Primate Hippocampal Cells}, journal = {Journal of Neurophysiology} } | G72: =IFERROR(__xludf.DUMMYFUNCTION("""COMPUTED_VALUE"""),"Article") -> Article | H72: =IFERROR(__xludf.DUMMYFUNCTION("""COMPUTED_VALUE"""),"Edmund T. Rolls, Alessandro Treves, Robert G. Robertson, Pierre Georges-Fran{\c{c}}ois, Stefano Panzeri") -> Edmund T. Rolls, Alessandro Treves, Robert G. Robertson, Pierre Georges-Fran{\c{c}}ois, Stefano Panzeri | I72: =IFERROR(__xludf.DUMMYFUNCTION("""COMPUTED_VALUE"""),"Information About Spatial View in an Ensemble of Primate Hippocampal Cells") -> Information About Spatial View in an Ensemble of Primate Hippocampal Cells | J72: =IFERROR(__xludf.DUMMYFUNCTION("""COMPUTED_VALUE"""),"Journal of Neurophysiology") -> Journal of Neurophysiology
A73: =IFERROR(__xludf.DUMMYFUNCTION("""COMPUTED_VALUE"""),"Rogers, 2013") -> Rogers, 2013 | B73: =IFERROR(__xludf.DUMMYFUNCTION("""COMPUTED_VALUE"""),"DOC") -> DOC | C73: =IFERROR(__xludf.DUMMYFUNCTION("""COMPUTED_VALUE"""),"BIB") -> BIB | D73: =IFERROR(__xludf.DUMMYFUNCTION("""COMPUTED_VALUE"""),"10.3389/fnsys.2013.00015") -> 10.3389/fnsys.2013.00015 | E73: =IFERROR(__xludf.DUMMYFUNCTION("""COMPUTED_VALUE"""),"@article{Rogers_2013, doi = {10.3389/fnsys.2013.00015}, url = {https://doi.org/10.3389%2Ffnsys.2013.00015}, year = 2013, publisher = {Frontiers Media {SA}}, volume = {7}, author = {Tiffany D. Rogers and Eric McKimm and Price E. Dickson and Dan Goldo"&"witz and Charles D. Blaha and Guy Mittleman}, title = {Is autism a disease of the cerebellum? An integration of clinical and pre-clinical research}, journal = {Frontiers in Systems Neuroscience} }") -> @article{Rogers_2013, doi = {10.3389/fnsys.2013.00015}, url = {https://doi.org/10.3389%2Ffnsys.2013.00015}, year = 2013, publisher = {Frontiers Media {SA}}, volume = {7}, author = {Tiffany D. Rogers and Eric McKimm and Price E. Dickson and Dan Goldowitz and Charles D. Blaha and Guy Mittleman}, title = {Is autism a disease of the cerebellum? An integration of clinical and pre-clinical research}, journal = {Frontiers in Systems Neuroscience} } | G73: =IFERROR(__xludf.DUMMYFUNCTION("""COMPUTED_VALUE"""),"Article") -> Article | H73: =IFERROR(__xludf.DUMMYFUNCTION("""COMPUTED_VALUE"""),"Tiffany D. Rogers, Eric McKimm, Price E. Dickson, Dan Goldowitz, Charles D. Blaha, Guy Mittleman") -> Tiffany D. Rogers, Eric McKimm, Price E. Dickson, Dan Goldowitz, Charles D. Blaha, Guy Mittleman | I73: =IFERROR(__xludf.DUMMYFUNCTION("""COMPUTED_VALUE"""),"Is autism a disease of the cerebellum? An integration of clinical and pre-clinical research") -> Is autism a disease of the cerebellum? An integration of clinical and pre-clinical research | J73: =IFERROR(__xludf.DUMMYFUNCTION("""COMPUTED_VALUE"""),"Frontiers in Systems Neuroscience") -> Frontiers in Systems Neuroscience | L73: =IFERROR(__xludf.DUMMYFUNCTION("""COMPUTED_VALUE"""),"Hiroshi Yamakawa") -> Hiroshi Yamakawa | M73: =IFERROR(__xludf.DUMMYFUNCTION("""COMPUTED_VALUE"""),"HY20Cerebellum") -> HY20Cerebellum
A74: =IFERROR(__xludf.DUMMYFUNCTION("""COMPUTED_VALUE"""),"Rodriguez, 2004") -> Rodriguez, 2004 | B74: =IFERROR(__xludf.DUMMYFUNCTION("""COMPUTED_VALUE"""),"DOC") -> DOC | C74: =IFERROR(__xludf.DUMMYFUNCTION("""COMPUTED_VALUE"""),"BIB") -> BIB | D74: =IFERROR(__xludf.DUMMYFUNCTION("""COMPUTED_VALUE"""),"10.1162/089892904970690") -> 10.1162/089892904970690 | E74: =IFERROR(__xludf.DUMMYFUNCTION("""COMPUTED_VALUE"""),"@article{Rodriguez_2004, doi = {10.1162/089892904970690}, url = {https://doi.org/10.1162%2F089892904970690}, year = 2004, month = {jun}, publisher = {{MIT} Press - Journals}, volume = {16}, number = {5}, pages = {856--877}, author = {A. Rodriguez"&" and J. Whitson and R. Granger}, title = {Derivation and Analysis of Basic Computational Operations of Thalamocortical Circuits}, journal = {Journal of Cognitive Neuroscience} }") -> @article{Rodriguez_2004, doi = {10.1162/089892904970690}, url = {https://doi.org/10.1162%2F089892904970690}, year = 2004, month = {jun}, publisher = {{MIT} Press - Journals}, volume = {16}, number = {5}, pages = {856--877}, author = {A. Rodriguez and J. Whitson and R. Granger}, title = {Derivation and Analysis of Basic Computational Operations of Thalamocortical Circuits}, journal = {Journal of Cognitive Neuroscience} } | G74: =IFERROR(__xludf.DUMMYFUNCTION("""COMPUTED_VALUE"""),"Article") -> Article | H74: =IFERROR(__xludf.DUMMYFUNCTION("""COMPUTED_VALUE"""),"A. Rodriguez, J. Whitson, R. Granger") -> A. Rodriguez, J. Whitson, R. Granger | I74: =IFERROR(__xludf.DUMMYFUNCTION("""COMPUTED_VALUE"""),"Derivation and Analysis of Basic Computational Operations of Thalamocortical Circuits") -> Derivation and Analysis of Basic Computational Operations of Thalamocortical Circuits | J74: =IFERROR(__xludf.DUMMYFUNCTION("""COMPUTED_VALUE"""),"Journal of Cognitive Neuroscience") -> Journal of Cognitive Neuroscience | K74: =IFERROR(__xludf.DUMMYFUNCTION("""COMPUTED_VALUE"""),"Fig.3") -> Fig.3 | L74: =IFERROR(__xludf.DUMMYFUNCTION("""COMPUTED_VALUE"""),"Hiroshi Yamakawa") -> Hiroshi Yamakawa | M74: =IFERROR(__xludf.DUMMYFUNCTION("""COMPUTED_VALUE"""),"HY18NeocorticalInterareaSignals") -> HY18NeocorticalInterareaSignals
A75: =IFERROR(__xludf.DUMMYFUNCTION("""COMPUTED_VALUE"""),"Rodrigo, 2018") -> Rodrigo, 2018 | B75: =IFERROR(__xludf.DUMMYFUNCTION("""COMPUTED_VALUE"""),"DOC") -> DOC | C75: =IFERROR(__xludf.DUMMYFUNCTION("""COMPUTED_VALUE"""),"BIB") -> BIB | D75: =IFERROR(__xludf.DUMMYFUNCTION("""COMPUTED_VALUE"""),"10.1111/jora.12342") -> 10.1111/jora.12342 | E75: =IFERROR(__xludf.DUMMYFUNCTION("""COMPUTED_VALUE"""),"@article{Rodrigo_2018, doi = {10.1111/jora.12342}, url = {https://doi.org/10.1111%2Fjora.12342}, year = 2018, month = {feb}, publisher = {Wiley}, volume = {28}, number = {1}, pages = {70--86}, author = {Mar{\'{\i}}a Jos{\'{e}} Rodrigo and Iv{\'{a"&"}}n Padr{\'{o}}n and Manuel de Vega and Evelyn Ferstl}, title = {Neural Substrates of Counterfactual Emotions After Risky Decisions in Late Adolescents and Young Adults}, journal = {Journal of Research on Adolescence} }") -> @article{Rodrigo_2018, doi = {10.1111/jora.12342}, url = {https://doi.org/10.1111%2Fjora.12342}, year = 2018, month = {feb}, publisher = {Wiley}, volume = {28}, number = {1}, pages = {70--86}, author = {Mar{\'{\i}}a Jos{\'{e}} Rodrigo and Iv{\'{a}}n Padr{\'{o}}n and Manuel de Vega and Evelyn Ferstl}, title = {Neural Substrates of Counterfactual Emotions After Risky Decisions in Late Adolescents and Young Adults}, journal = {Journal of Research on Adolescence} } | G75: =IFERROR(__xludf.DUMMYFUNCTION("""COMPUTED_VALUE"""),"Article") -> Article | H75: =IFERROR(__xludf.DUMMYFUNCTION("""COMPUTED_VALUE"""),"Mar{\'{\i}}a Jos{\'{e}} Rodrigo, Iv{\'{a}}n Padr{\'{o}}n, Manuel de Vega, Evelyn Ferstl") -> Mar{\'{\i}}a Jos{\'{e}} Rodrigo, Iv{\'{a}}n Padr{\'{o}}n, Manuel de Vega, Evelyn Ferstl | I75: =IFERROR(__xludf.DUMMYFUNCTION("""COMPUTED_VALUE"""),"Neural Substrates of Counterfactual Emotions After Risky Decisions in Late Adolescents and Young Adults") -> Neural Substrates of Counterfactual Emotions After Risky Decisions in Late Adolescents and Young Adults | J75: =IFERROR(__xludf.DUMMYFUNCTION("""COMPUTED_VALUE"""),"Journal of Research on Adolescence") -> Journal of Research on Adolescence | K75: =IFERROR(__xludf.DUMMYFUNCTION("""COMPUTED_VALUE"""),"https://onlinelibrary.wiley.com/doi/full/10.1111/jora.12342") -> https://onlinelibrary.wiley.com/doi/full/10.1111/jora.12342 | M75: =IFERROR(__xludf.DUMMYFUNCTION("""COMPUTED_VALUE"""),"Trust") -> Trust
A76: =IFERROR(__xludf.DUMMYFUNCTION("""COMPUTED_VALUE"""),"Robinson, 1972") -> Robinson, 1972 | B76: =IFERROR(__xludf.DUMMYFUNCTION("""COMPUTED_VALUE"""),"DOC") -> DOC | C76: =IFERROR(__xludf.DUMMYFUNCTION("""COMPUTED_VALUE"""),"BIB") -> BIB | D76: =IFERROR(__xludf.DUMMYFUNCTION("""COMPUTED_VALUE"""),"10.1016/0042-6989(72)90070-3") -> 10.1016/0042-6989(72)90070-3 | E76: =IFERROR(__xludf.DUMMYFUNCTION("""COMPUTED_VALUE"""),"@article{Robinson_1972, doi = {10.1016/0042-6989(72)90070-3}, url = {https://doi.org/10.1016%2F0042-6989%2872%2990070-3}, year = 1972, month = {nov}, publisher = {Elsevier {BV}}, volume = {12}, number = {11}, pages = {1795--1808}, author = {D.A. "&"Robinson}, title = {Eye movements evoked by collicular stimulation in the alert monkey}, journal = {Vision Research} }") -> @article{Robinson_1972, doi = {10.1016/0042-6989(72)90070-3}, url = {https://doi.org/10.1016%2F0042-6989%2872%2990070-3}, year = 1972, month = {nov}, publisher = {Elsevier {BV}}, volume = {12}, number = {11}, pages = {1795--1808}, author = {D.A. Robinson}, title = {Eye movements evoked by collicular stimulation in the alert monkey}, journal = {Vision Research} } | G76: =IFERROR(__xludf.DUMMYFUNCTION("""COMPUTED_VALUE"""),"Article") -> Article | H76: =IFERROR(__xludf.DUMMYFUNCTION("""COMPUTED_VALUE"""),"D.A. Robinson") -> D.A. Robinson | I76: =IFERROR(__xludf.DUMMYFUNCTION("""COMPUTED_VALUE"""),"Eye movements evoked by collicular stimulation in the alert monkey") -> Eye movements evoked by collicular stimulation in the alert monkey | J76: =IFERROR(__xludf.DUMMYFUNCTION("""COMPUTED_VALUE"""),"Vision Research") -> Vision Research | L76: =IFERROR(__xludf.DUMMYFUNCTION("""COMPUTED_VALUE"""),"Yoshinasa Tawatsji") -> Yoshinasa Tawatsji | M76: =IFERROR(__xludf.DUMMYFUNCTION("""COMPUTED_VALUE"""),"Oculomotor") -> Oculomotor
A77: =IFERROR(__xludf.DUMMYFUNCTION("""COMPUTED_VALUE"""),"Robertson, 1998") -> Robertson, 1998 | B77: =IFERROR(__xludf.DUMMYFUNCTION("""COMPUTED_VALUE"""),"DOC") -> DOC | C77: =IFERROR(__xludf.DUMMYFUNCTION("""COMPUTED_VALUE"""),"BIB") -> BIB | D77: =IFERROR(__xludf.DUMMYFUNCTION("""COMPUTED_VALUE"""),"10.1152/jn.1998.79.3.1145") -> 10.1152/jn.1998.79.3.1145 | E77: =IFERROR(__xludf.DUMMYFUNCTION("""COMPUTED_VALUE"""),"@article{Robertson_1998, doi = {10.1152/jn.1998.79.3.1145}, url = {https://doi.org/10.1152%2Fjn.1998.79.3.1145}, year = 1998, month = {mar}, publisher = {American Physiological Society}, volume = {79}, number = {3}, pages = {1145--1156}, author ="&" {Robert G. Robertson and Edmund T. Rolls and Pierre Georges-Fran{\c{c}}ois}, title = {Spatial View Cells in the Primate Hippocampus: Effects of Removal of View Details}, journal = {Journal of Neurophysiology} }") -> @article{Robertson_1998, doi = {10.1152/jn.1998.79.3.1145}, url = {https://doi.org/10.1152%2Fjn.1998.79.3.1145}, year = 1998, month = {mar}, publisher = {American Physiological Society}, volume = {79}, number = {3}, pages = {1145--1156}, author = {Robert G. Robertson and Edmund T. Rolls and Pierre Georges-Fran{\c{c}}ois}, title = {Spatial View Cells in the Primate Hippocampus: Effects of Removal of View Details}, journal = {Journal of Neurophysiology} } | G77: =IFERROR(__xludf.DUMMYFUNCTION("""COMPUTED_VALUE"""),"Article") -> Article | H77: =IFERROR(__xludf.DUMMYFUNCTION("""COMPUTED_VALUE"""),"Robert G. Robertson, Edmund T. Rolls, Pierre Georges-Fran{\c{c}}ois") -> Robert G. Robertson, Edmund T. Rolls, Pierre Georges-Fran{\c{c}}ois | I77: =IFERROR(__xludf.DUMMYFUNCTION("""COMPUTED_VALUE"""),"Spatial View Cells in the Primate Hippocampus: Effects of Removal of View Details") -> Spatial View Cells in the Primate Hippocampus: Effects of Removal of View Details | J77: =IFERROR(__xludf.DUMMYFUNCTION("""COMPUTED_VALUE"""),"Journal of Neurophysiology") -> Journal of Neurophysiology | L77: =IFERROR(__xludf.DUMMYFUNCTION("""COMPUTED_VALUE"""),"Ayako Fukawa") -> Ayako Fukawa | M77: =IFERROR(__xludf.DUMMYFUNCTION("""COMPUTED_VALUE"""),"AT20HippocampalFormation") -> AT20HippocampalFormation
A78: =IFERROR(__xludf.DUMMYFUNCTION("""COMPUTED_VALUE"""),"Robertson, 1998") -> Robertson, 1998 | B78: =IFERROR(__xludf.DUMMYFUNCTION("""COMPUTED_VALUE"""),"DOC") -> DOC | C78: =IFERROR(__xludf.DUMMYFUNCTION("""COMPUTED_VALUE"""),"BIB") -> BIB | D78: =IFERROR(__xludf.DUMMYFUNCTION("""COMPUTED_VALUE"""),"10.1152/jn.1998.79.3.1145") -> 10.1152/jn.1998.79.3.1145 | E78: =IFERROR(__xludf.DUMMYFUNCTION("""COMPUTED_VALUE"""),"@article{Robertson_1998, doi = {10.1152/jn.1998.79.3.1145}, url = {https://doi.org/10.1152%2Fjn.1998.79.3.1145}, year = 1998, month = {mar}, publisher = {American Physiological Society}, volume = {79}, number = {3}, pages = {1145--1156}, author ="&" {Robert G. Robertson and Edmund T. Rolls and Pierre Georges-Fran{\c{c}}ois}, title = {Spatial View Cells in the Primate Hippocampus: Effects of Removal of View Details}, journal = {Journal of Neurophysiology} }") -> @article{Robertson_1998, doi = {10.1152/jn.1998.79.3.1145}, url = {https://doi.org/10.1152%2Fjn.1998.79.3.1145}, year = 1998, month = {mar}, publisher = {American Physiological Society}, volume = {79}, number = {3}, pages = {1145--1156}, author = {Robert G. Robertson and Edmund T. Rolls and Pierre Georges-Fran{\c{c}}ois}, title = {Spatial View Cells in the Primate Hippocampus: Effects of Removal of View Details}, journal = {Journal of Neurophysiology} } | G78: =IFERROR(__xludf.DUMMYFUNCTION("""COMPUTED_VALUE"""),"Article") -> Article | H78: =IFERROR(__xludf.DUMMYFUNCTION("""COMPUTED_VALUE"""),"Robert G. Robertson, Edmund T. Rolls, Pierre Georges-Fran{\c{c}}ois") -> Robert G. Robertson, Edmund T. Rolls, Pierre Georges-Fran{\c{c}}ois | I78: =IFERROR(__xludf.DUMMYFUNCTION("""COMPUTED_VALUE"""),"Spatial View Cells in the Primate Hippocampus: Effects of Removal of View Details") -> Spatial View Cells in the Primate Hippocampus: Effects of Removal of View Details | J78: =IFERROR(__xludf.DUMMYFUNCTION("""COMPUTED_VALUE"""),"Journal of Neurophysiology") -> Journal of Neurophysiology
A79: =IFERROR(__xludf.DUMMYFUNCTION("""COMPUTED_VALUE"""),"Ralph, 2016") -> Ralph, 2016 | B79: =IFERROR(__xludf.DUMMYFUNCTION("""COMPUTED_VALUE"""),"DOC") -> DOC | C79: =IFERROR(__xludf.DUMMYFUNCTION("""COMPUTED_VALUE"""),"BIB") -> BIB | D79: =IFERROR(__xludf.DUMMYFUNCTION("""COMPUTED_VALUE"""),"10.1038/nrn.2016.150") -> 10.1038/nrn.2016.150 | E79: =IFERROR(__xludf.DUMMYFUNCTION("""COMPUTED_VALUE"""),"@article{Ralph_2016, doi = {10.1038/nrn.2016.150}, url = {https://doi.org/10.1038%2Fnrn.2016.150}, year = 2016, month = {nov}, publisher = {Springer Science and Business Media {LLC}}, volume = {18}, number = {1}, pages = {42--55}, author = {Matth"&"ew A. Lambon Ralph and Elizabeth Jefferies and Karalyn Patterson and Timothy T. Rogers}, title = {The neural and computational bases of semantic cognition}, journal = {Nature Reviews Neuroscience} }") -> @article{Ralph_2016, doi = {10.1038/nrn.2016.150}, url = {https://doi.org/10.1038%2Fnrn.2016.150}, year = 2016, month = {nov}, publisher = {Springer Science and Business Media {LLC}}, volume = {18}, number = {1}, pages = {42--55}, author = {Matthew A. Lambon Ralph and Elizabeth Jefferies and Karalyn Patterson and Timothy T. Rogers}, title = {The neural and computational bases of semantic cognition}, journal = {Nature Reviews Neuroscience} } | G79: =IFERROR(__xludf.DUMMYFUNCTION("""COMPUTED_VALUE"""),"Article") -> Article | H79: =IFERROR(__xludf.DUMMYFUNCTION("""COMPUTED_VALUE"""),"Matthew A. Lambon Ralph, Elizabeth Jefferies, Karalyn Patterson, Timothy T. Rogers") -> Matthew A. Lambon Ralph, Elizabeth Jefferies, Karalyn Patterson, Timothy T. Rogers | I79: =IFERROR(__xludf.DUMMYFUNCTION("""COMPUTED_VALUE"""),"The neural and computational bases of semantic cognition") -> The neural and computational bases of semantic cognition | J79: =IFERROR(__xludf.DUMMYFUNCTION("""COMPUTED_VALUE"""),"Nature Reviews Neuroscience") -> Nature Reviews Neuroscience | L79: =IFERROR(__xludf.DUMMYFUNCTION("""COMPUTED_VALUE"""),"Hiroshi Yamakawa") -> Hiroshi Yamakawa | M79: =IFERROR(__xludf.DUMMYFUNCTION("""COMPUTED_VALUE"""),"HY22DAA") -> HY22DAA
A80: =IFERROR(__xludf.DUMMYFUNCTION("""COMPUTED_VALUE"""),"Rajakumar, 1993") -> Rajakumar, 1993 | B80: =IFERROR(__xludf.DUMMYFUNCTION("""COMPUTED_VALUE"""),"DOC") -> DOC | C80: =IFERROR(__xludf.DUMMYFUNCTION("""COMPUTED_VALUE"""),"BIB") -> BIB | D80: =IFERROR(__xludf.DUMMYFUNCTION("""COMPUTED_VALUE"""),"10.1002/cne.903310210") -> 10.1002/cne.903310210 | E80: =IFERROR(__xludf.DUMMYFUNCTION("""COMPUTED_VALUE"""),"@article{Rajakumar_1993, doi = {10.1002/cne.903310210}, url = {https://doi.org/10.1002%2Fcne.903310210}, year = 1993, month = {may}, publisher = {Wiley}, volume = {331}, number = {2}, pages = {286--296}, author = {N. Rajakumar and K. Elisevich an"&"d B. A. Flumerfelt}, title = {Compartmental origin of the striato-entopeduncular projection in the rat}, journal = {The Journal of Comparative Neurology} }") -> @article{Rajakumar_1993, doi = {10.1002/cne.903310210}, url = {https://doi.org/10.1002%2Fcne.903310210}, year = 1993, month = {may}, publisher = {Wiley}, volume = {331}, number = {2}, pages = {286--296}, author = {N. Rajakumar and K. Elisevich and B. A. Flumerfelt}, title = {Compartmental origin of the striato-entopeduncular projection in the rat}, journal = {The Journal of Comparative Neurology} } | G80: =IFERROR(__xludf.DUMMYFUNCTION("""COMPUTED_VALUE"""),"Article") -> Article | H80: =IFERROR(__xludf.DUMMYFUNCTION("""COMPUTED_VALUE"""),"N. Rajakumar, K. Elisevich, B. A. Flumerfelt") -> N. Rajakumar, K. Elisevich, B. A. Flumerfelt | I80: =IFERROR(__xludf.DUMMYFUNCTION("""COMPUTED_VALUE"""),"Compartmental origin of the striato-entopeduncular projection in the rat") -> Compartmental origin of the striato-entopeduncular projection in the rat | J80: =IFERROR(__xludf.DUMMYFUNCTION("""COMPUTED_VALUE"""),"The Journal of Comparative Neurology") -> The Journal of Comparative Neurology | L80: =IFERROR(__xludf.DUMMYFUNCTION("""COMPUTED_VALUE"""),"Yuske Shibata") -> Yuske Shibata | M80: =IFERROR(__xludf.DUMMYFUNCTION("""COMPUTED_VALUE"""),"YS21BgLoop") -> YS21BgLoop
A81: =IFERROR(__xludf.DUMMYFUNCTION("""COMPUTED_VALUE"""),"Rajakumar, 1993") -> Rajakumar, 1993 | B81: =IFERROR(__xludf.DUMMYFUNCTION("""COMPUTED_VALUE"""),"DOC") -> DOC | C81: =IFERROR(__xludf.DUMMYFUNCTION("""COMPUTED_VALUE"""),"BIB") -> BIB | D81: =IFERROR(__xludf.DUMMYFUNCTION("""COMPUTED_VALUE"""),"10.1002/cne.903310210") -> 10.1002/cne.903310210 | E81: =IFERROR(__xludf.DUMMYFUNCTION("""COMPUTED_VALUE"""),"@article{Rajakumar_1993, doi = {10.1002/cne.903310210}, url = {https://doi.org/10.1002%2Fcne.903310210}, year = 1993, month = {may}, publisher = {Wiley}, volume = {331}, number = {2}, pages = {286--296}, author = {N. Rajakumar and K. Elisevich an"&"d B. A. Flumerfelt}, title = {Compartmental origin of the striato-entopeduncular projection in the rat}, journal = {The Journal of Comparative Neurology} }") -> @article{Rajakumar_1993, doi = {10.1002/cne.903310210}, url = {https://doi.org/10.1002%2Fcne.903310210}, year = 1993, month = {may}, publisher = {Wiley}, volume = {331}, number = {2}, pages = {286--296}, author = {N. Rajakumar and K. Elisevich and B. A. Flumerfelt}, title = {Compartmental origin of the striato-entopeduncular projection in the rat}, journal = {The Journal of Comparative Neurology} } | G81: =IFERROR(__xludf.DUMMYFUNCTION("""COMPUTED_VALUE"""),"Article") -> Article | H81: =IFERROR(__xludf.DUMMYFUNCTION("""COMPUTED_VALUE"""),"N. Rajakumar, K. Elisevich, B. A. Flumerfelt") -> N. Rajakumar, K. Elisevich, B. A. Flumerfelt | I81: =IFERROR(__xludf.DUMMYFUNCTION("""COMPUTED_VALUE"""),"Compartmental origin of the striato-entopeduncular projection in the rat") -> Compartmental origin of the striato-entopeduncular projection in the rat | J81: =IFERROR(__xludf.DUMMYFUNCTION("""COMPUTED_VALUE"""),"The Journal of Comparative Neurology") -> The Journal of Comparative Neurology
A82: =IFERROR(__xludf.DUMMYFUNCTION("""COMPUTED_VALUE"""),"Quinet, 2020") -> Quinet, 2020 | B82: =IFERROR(__xludf.DUMMYFUNCTION("""COMPUTED_VALUE"""),"DOC") -> DOC | C82: =IFERROR(__xludf.DUMMYFUNCTION("""COMPUTED_VALUE"""),"BIB") -> BIB | D82: =IFERROR(__xludf.DUMMYFUNCTION("""COMPUTED_VALUE"""),"10.1073/pnas.2015318117") -> 10.1073/pnas.2015318117 | E82: =IFERROR(__xludf.DUMMYFUNCTION("""COMPUTED_VALUE"""),"@article{Quinet_2020, doi = {10.1073/pnas.2015318117}, url = {https://doi.org/10.1073%2Fpnas.2015318117}, year = 2020, month = {nov}, publisher = {Proceedings of the National Academy of Sciences}, volume = {117}, number = {46}, pages = {29123--291"&"32}, author = {Julie Quinet and Kevin Schultz and Paul J. May and Paul D. Gamlin}, title = {Neural control of rapid binocular eye movements: Saccade-vergence burst neurons}, journal = {Proceedings of the National Academy of Sciences} }") -> @article{Quinet_2020, doi = {10.1073/pnas.2015318117}, url = {https://doi.org/10.1073%2Fpnas.2015318117}, year = 2020, month = {nov}, publisher = {Proceedings of the National Academy of Sciences}, volume = {117}, number = {46}, pages = {29123--29132}, author = {Julie Quinet and Kevin Schultz and Paul J. May and Paul D. Gamlin}, title = {Neural control of rapid binocular eye movements: Saccade-vergence burst neurons}, journal = {Proceedings of the National Academy of Sciences} } | G82: =IFERROR(__xludf.DUMMYFUNCTION("""COMPUTED_VALUE"""),"Article") -> Article | H82: =IFERROR(__xludf.DUMMYFUNCTION("""COMPUTED_VALUE"""),"Julie Quinet, Kevin Schultz, Paul J. May, Paul D. Gamlin") -> Julie Quinet, Kevin Schultz, Paul J. May, Paul D. Gamlin | I82: =IFERROR(__xludf.DUMMYFUNCTION("""COMPUTED_VALUE"""),"Neural control of rapid binocular eye movements: Saccade-vergence burst neurons") -> Neural control of rapid binocular eye movements: Saccade-vergence burst neurons | J82: =IFERROR(__xludf.DUMMYFUNCTION("""COMPUTED_VALUE"""),"Proceedings of the National Academy of Sciences") -> Proceedings of the National Academy of Sciences | L82: =IFERROR(__xludf.DUMMYFUNCTION("""COMPUTED_VALUE"""),"Yoshinasa Tawatsji") -> Yoshinasa Tawatsji | M82: =IFERROR(__xludf.DUMMYFUNCTION("""COMPUTED_VALUE"""),"Oculomotor") -> Oculomotor
A83: =IFERROR(__xludf.DUMMYFUNCTION("""COMPUTED_VALUE"""),"Pitkänen, 2000") -> Pitkänen, 2000 | B83: =IFERROR(__xludf.DUMMYFUNCTION("""COMPUTED_VALUE"""),"DOC(alt)") -> DOC(alt) | C83: =IFERROR(__xludf.DUMMYFUNCTION("""COMPUTED_VALUE"""),"(no DOI)") -> (no DOI) | E83: =IFERROR(__xludf.DUMMYFUNCTION("""COMPUTED_VALUE"""),"@ARTICLE{Pitkänen2000, title = {Anatomic heterogeneity of the rat amygdaloid complex}, author = {Pitkänen, A and Jolkkonen, E and Kemppainen, S}, journal = {Folia morphologica}, volume = 59, number = 1, pages = ""1--23"", year"&" = 2000, language = ""en"", issn = ""0015-5659"", pmid = ""10774087"" }") -> @ARTICLE{Pitkänen2000, title = {Anatomic heterogeneity of the rat amygdaloid complex}, author = {Pitkänen, A and Jolkkonen, E and Kemppainen, S}, journal = {Folia morphologica}, volume = 59, number = 1, pages = "1--23", year = 2000, language = "en", issn = "0015-5659", pmid = "10774087" } | F83: =IFERROR(__xludf.DUMMYFUNCTION("""COMPUTED_VALUE"""),"Review") -> Review | G83: =IFERROR(__xludf.DUMMYFUNCTION("""COMPUTED_VALUE"""),"Article") -> Article | H83: =IFERROR(__xludf.DUMMYFUNCTION("""COMPUTED_VALUE"""),"Pitkänen, A, Jolkkonen, E, Kemppainen, S") -> Pitkänen, A, Jolkkonen, E, Kemppainen, S | I83: =IFERROR(__xludf.DUMMYFUNCTION("""COMPUTED_VALUE"""),"Anatomic heterogeneity of the rat amygdaloid complex") -> Anatomic heterogeneity of the rat amygdaloid complex | J83: =IFERROR(__xludf.DUMMYFUNCTION("""COMPUTED_VALUE"""),"Folia morphologica") -> Folia morphologica | K83: =IFERROR(__xludf.DUMMYFUNCTION("""COMPUTED_VALUE"""),"https://journals.viamedica.pl/folia_morphologica/article/viewFile/16543/13176#page=1") -> https://journals.viamedica.pl/folia_morphologica/article/viewFile/16543/13176#page=1 | L83: =IFERROR(__xludf.DUMMYFUNCTION("""COMPUTED_VALUE"""),"Tatsuya Miyamoto") -> Tatsuya Miyamoto | M83: =IFERROR(__xludf.DUMMYFUNCTION("""COMPUTED_VALUE"""),"TM21Amygdala") -> TM21Amygdala
A84: =IFERROR(__xludf.DUMMYFUNCTION("""COMPUTED_VALUE"""),"Pierce, 2020") -> Pierce, 2020 | B84: =IFERROR(__xludf.DUMMYFUNCTION("""COMPUTED_VALUE"""),"DOC") -> DOC | C84: =IFERROR(__xludf.DUMMYFUNCTION("""COMPUTED_VALUE"""),"BIB") -> BIB | D84: =IFERROR(__xludf.DUMMYFUNCTION("""COMPUTED_VALUE"""),"10.1093/scan/nsaa076") -> 10.1093/scan/nsaa076 | E84: =IFERROR(__xludf.DUMMYFUNCTION("""COMPUTED_VALUE"""),"@article{Pierce_2020, doi = {10.1093/scan/nsaa076}, url = {https://doi.org/10.1093%2Fscan%2Fnsaa076}, year = 2020, month = {may}, publisher = {Oxford University Press ({OUP})}, volume = {15}, number = {5}, pages = {599--613}, author = {Jordan E P"&"ierce and Julie P{\'{e}}ron}, title = {The basal ganglia and the cerebellum in human emotion}, journal = {Social Cognitive and Affective Neuroscience} }") -> @article{Pierce_2020, doi = {10.1093/scan/nsaa076}, url = {https://doi.org/10.1093%2Fscan%2Fnsaa076}, year = 2020, month = {may}, publisher = {Oxford University Press ({OUP})}, volume = {15}, number = {5}, pages = {599--613}, author = {Jordan E Pierce and Julie P{\'{e}}ron}, title = {The basal ganglia and the cerebellum in human emotion}, journal = {Social Cognitive and Affective Neuroscience} } | G84: =IFERROR(__xludf.DUMMYFUNCTION("""COMPUTED_VALUE"""),"Article") -> Article | H84: =IFERROR(__xludf.DUMMYFUNCTION("""COMPUTED_VALUE"""),"Jordan E Pierce, Julie P{\'{e}}ron") -> Jordan E Pierce, Julie P{\'{e}}ron | I84: =IFERROR(__xludf.DUMMYFUNCTION("""COMPUTED_VALUE"""),"The basal ganglia and the cerebellum in human emotion") -> The basal ganglia and the cerebellum in human emotion | J84: =IFERROR(__xludf.DUMMYFUNCTION("""COMPUTED_VALUE"""),"Social Cognitive and Affective Neuroscience") -> Social Cognitive and Affective Neuroscience | L84: =IFERROR(__xludf.DUMMYFUNCTION("""COMPUTED_VALUE"""),"Yuske Shibata") -> Yuske Shibata | M84: =IFERROR(__xludf.DUMMYFUNCTION("""COMPUTED_VALUE"""),"YS21BgLoop") -> YS21BgLoop
A85: =IFERROR(__xludf.DUMMYFUNCTION("""COMPUTED_VALUE"""),"Pierce, 2020") -> Pierce, 2020 | B85: =IFERROR(__xludf.DUMMYFUNCTION("""COMPUTED_VALUE"""),"DOC") -> DOC | C85: =IFERROR(__xludf.DUMMYFUNCTION("""COMPUTED_VALUE"""),"BIB") -> BIB | D85: =IFERROR(__xludf.DUMMYFUNCTION("""COMPUTED_VALUE"""),"10.1093/scan/nsaa076") -> 10.1093/scan/nsaa076 | E85: =IFERROR(__xludf.DUMMYFUNCTION("""COMPUTED_VALUE"""),"@article{Pierce_2020, doi = {10.1093/scan/nsaa076}, url = {https://doi.org/10.1093%2Fscan%2Fnsaa076}, year = 2020, month = {may}, publisher = {Oxford University Press ({OUP})}, volume = {15}, number = {5}, pages = {599--613}, author = {Jordan E P"&"ierce and Julie P{\'{e}}ron}, title = {The basal ganglia and the cerebellum in human emotion}, journal = {Social Cognitive and Affective Neuroscience} }") -> @article{Pierce_2020, doi = {10.1093/scan/nsaa076}, url = {https://doi.org/10.1093%2Fscan%2Fnsaa076}, year = 2020, month = {may}, publisher = {Oxford University Press ({OUP})}, volume = {15}, number = {5}, pages = {599--613}, author = {Jordan E Pierce and Julie P{\'{e}}ron}, title = {The basal ganglia and the cerebellum in human emotion}, journal = {Social Cognitive and Affective Neuroscience} } | G85: =IFERROR(__xludf.DUMMYFUNCTION("""COMPUTED_VALUE"""),"Article") -> Article | H85: =IFERROR(__xludf.DUMMYFUNCTION("""COMPUTED_VALUE"""),"Jordan E Pierce, Julie P{\'{e}}ron") -> Jordan E Pierce, Julie P{\'{e}}ron | I85: =IFERROR(__xludf.DUMMYFUNCTION("""COMPUTED_VALUE"""),"The basal ganglia and the cerebellum in human emotion") -> The basal ganglia and the cerebellum in human emotion | J85: =IFERROR(__xludf.DUMMYFUNCTION("""COMPUTED_VALUE"""),"Social Cognitive and Affective Neuroscience") -> Social Cognitive and Affective Neuroscience
A86: =IFERROR(__xludf.DUMMYFUNCTION("""COMPUTED_VALUE"""),"Piantoni, 2016") -> Piantoni, 2016 | B86: =IFERROR(__xludf.DUMMYFUNCTION("""COMPUTED_VALUE"""),"DOC") -> DOC | C86: =IFERROR(__xludf.DUMMYFUNCTION("""COMPUTED_VALUE"""),"BIB") -> BIB | D86: =IFERROR(__xludf.DUMMYFUNCTION("""COMPUTED_VALUE"""),"10.1155/2016/3024342") -> 10.1155/2016/3024342 | E86: =IFERROR(__xludf.DUMMYFUNCTION("""COMPUTED_VALUE"""),"@article{Piantoni_2016, doi = {10.1155/2016/3024342}, url = {https://doi.org/10.1155%2F2016%2F3024342}, year = 2016, publisher = {Hindawi Limited}, volume = {2016}, pages = {1--10}, author = {Giovanni Piantoni and Eric Halgren and Sydney S. Cash}, "&" title = {The Contribution of Thalamocortical Core and Matrix Pathways to Sleep Spindles}, journal = {Neural Plasticity} }") -> @article{Piantoni_2016, doi = {10.1155/2016/3024342}, url = {https://doi.org/10.1155%2F2016%2F3024342}, year = 2016, publisher = {Hindawi Limited}, volume = {2016}, pages = {1--10}, author = {Giovanni Piantoni and Eric Halgren and Sydney S. Cash}, title = {The Contribution of Thalamocortical Core and Matrix Pathways to Sleep Spindles}, journal = {Neural Plasticity} } | G86: =IFERROR(__xludf.DUMMYFUNCTION("""COMPUTED_VALUE"""),"Article") -> Article | H86: =IFERROR(__xludf.DUMMYFUNCTION("""COMPUTED_VALUE"""),"Giovanni Piantoni, Eric Halgren, Sydney S. Cash") -> Giovanni Piantoni, Eric Halgren, Sydney S. Cash | I86: =IFERROR(__xludf.DUMMYFUNCTION("""COMPUTED_VALUE"""),"The Contribution of Thalamocortical Core and Matrix Pathways to Sleep Spindles") -> The Contribution of Thalamocortical Core and Matrix Pathways to Sleep Spindles | J86: =IFERROR(__xludf.DUMMYFUNCTION("""COMPUTED_VALUE"""),"Neural Plasticity") -> Neural Plasticity | K86: =IFERROR(__xludf.DUMMYFUNCTION("""COMPUTED_VALUE"""),"Fig.1") -> Fig.1 | L86: =IFERROR(__xludf.DUMMYFUNCTION("""COMPUTED_VALUE"""),"Hiroshi Yamakawa") -> Hiroshi Yamakawa | M86: =IFERROR(__xludf.DUMMYFUNCTION("""COMPUTED_VALUE"""),"HY18NeocorticalInterareaSignals") -> HY18NeocorticalInterareaSignals
A87: =IFERROR(__xludf.DUMMYFUNCTION("""COMPUTED_VALUE"""),"Petrides, 2012") -> Petrides, 2012 | B87: =IFERROR(__xludf.DUMMYFUNCTION("""COMPUTED_VALUE"""),"DOC") -> DOC | C87: =IFERROR(__xludf.DUMMYFUNCTION("""COMPUTED_VALUE"""),"BIB") -> BIB | D87: =IFERROR(__xludf.DUMMYFUNCTION("""COMPUTED_VALUE"""),"10.1016/j.cortex.2011.07.002") -> 10.1016/j.cortex.2011.07.002 | E87: =IFERROR(__xludf.DUMMYFUNCTION("""COMPUTED_VALUE"""),"@article{Petrides_2012, doi = {10.1016/j.cortex.2011.07.002}, url = {https://doi.org/10.1016%2Fj.cortex.2011.07.002}, year = 2012, month = {jan}, publisher = {Elsevier {BV}}, volume = {48}, number = {1}, pages = {46--57}, author = {Michael Petrid"&"es and Francesco Tomaiuolo and Edward H. Yeterian and Deepak N. Pandya}, title = {The prefrontal cortex: Comparative architectonic organization in the human and the macaque monkey brains}, journal = {Cortex} }") -> @article{Petrides_2012, doi = {10.1016/j.cortex.2011.07.002}, url = {https://doi.org/10.1016%2Fj.cortex.2011.07.002}, year = 2012, month = {jan}, publisher = {Elsevier {BV}}, volume = {48}, number = {1}, pages = {46--57}, author = {Michael Petrides and Francesco Tomaiuolo and Edward H. Yeterian and Deepak N. Pandya}, title = {The prefrontal cortex: Comparative architectonic organization in the human and the macaque monkey brains}, journal = {Cortex} } | G87: =IFERROR(__xludf.DUMMYFUNCTION("""COMPUTED_VALUE"""),"Article") -> Article | H87: =IFERROR(__xludf.DUMMYFUNCTION("""COMPUTED_VALUE"""),"Michael Petrides, Francesco Tomaiuolo, Edward H. Yeterian, Deepak N. Pandya") -> Michael Petrides, Francesco Tomaiuolo, Edward H. Yeterian, Deepak N. Pandya | I87: =IFERROR(__xludf.DUMMYFUNCTION("""COMPUTED_VALUE"""),"The prefrontal cortex: Comparative architectonic organization in the human and the macaque monkey brains") -> The prefrontal cortex: Comparative architectonic organization in the human and the macaque monkey brains | J87: =IFERROR(__xludf.DUMMYFUNCTION("""COMPUTED_VALUE"""),"Cortex") -> Cortex
A88: =IFERROR(__xludf.DUMMYFUNCTION("""COMPUTED_VALUE"""),"PereiradeVasconcelos, 2015") -> PereiradeVasconcelos, 2015 | B88: =IFERROR(__xludf.DUMMYFUNCTION("""COMPUTED_VALUE"""),"DOC") -> DOC | C88: =IFERROR(__xludf.DUMMYFUNCTION("""COMPUTED_VALUE"""),"BIB") -> BIB | D88: =IFERROR(__xludf.DUMMYFUNCTION("""COMPUTED_VALUE"""),"10.1016/j.neubiorev.2014.10.021") -> 10.1016/j.neubiorev.2014.10.021 | E88: =IFERROR(__xludf.DUMMYFUNCTION("""COMPUTED_VALUE"""),"@article{Pereira_de_Vasconcelos_2015, doi = {10.1016/j.neubiorev.2014.10.021}, url = {https://doi.org/10.1016%2Fj.neubiorev.2014.10.021}, year = 2015, month = {jul}, publisher = {Elsevier {BV}}, volume = {54"&"}, pages = {175--196}, author = {Anne Pereira de Vasconcelos and Jean-Christophe Cassel}, title = {The nonspecific thalamus: A place in a wedding bed for making memories last?}, journal = {Neuroscience & Biobehavioral Revie"&"ws} }") -> @article{Pereira_de_Vasconcelos_2015, doi = {10.1016/j.neubiorev.2014.10.021}, url = {https://doi.org/10.1016%2Fj.neubiorev.2014.10.021}, year = 2015, month = {jul}, publisher = {Elsevier {BV}}, volume = {54}, pages = {175--196}, author = {Anne Pereira de Vasconcelos and Jean-Christophe Cassel}, title = {The nonspecific thalamus: A place in a wedding bed for making memories last?}, journal = {Neuroscience & Biobehavioral Reviews} } | G88: =IFERROR(__xludf.DUMMYFUNCTION("""COMPUTED_VALUE"""),"Article") -> Article | H88: =IFERROR(__xludf.DUMMYFUNCTION("""COMPUTED_VALUE"""),"Anne Pereira de Vasconcelos, Jean-Christophe Cassel") -> Anne Pereira de Vasconcelos, Jean-Christophe Cassel | I88: =IFERROR(__xludf.DUMMYFUNCTION("""COMPUTED_VALUE"""),"The nonspecific thalamus: A place in a wedding bed for making memories last?") -> The nonspecific thalamus: A place in a wedding bed for making memories last? | J88: =IFERROR(__xludf.DUMMYFUNCTION("""COMPUTED_VALUE"""),"Neuroscience & Biobehavioral Reviews") -> Neuroscience & Biobehavioral Reviews | K88: =IFERROR(__xludf.DUMMYFUNCTION("""COMPUTED_VALUE"""),"Fig.5") -> Fig.5 | L88: =IFERROR(__xludf.DUMMYFUNCTION("""COMPUTED_VALUE"""),"Hiroshi Yamakawa") -> Hiroshi Yamakawa | M88: =IFERROR(__xludf.DUMMYFUNCTION("""COMPUTED_VALUE"""),"HY18NeocorticalInterareaSignals") -> HY18NeocorticalInterareaSignals
A89: =IFERROR(__xludf.DUMMYFUNCTION("""COMPUTED_VALUE"""),"Paxinos, 2012") -> Paxinos, 2012 | B89: =IFERROR(__xludf.DUMMYFUNCTION("""COMPUTED_VALUE"""),"DOC(alt)") -> DOC(alt) | C89: =IFERROR(__xludf.DUMMYFUNCTION("""COMPUTED_VALUE"""),"(no DOI)") -> (no DOI) | E89: =IFERROR(__xludf.DUMMYFUNCTION("""COMPUTED_VALUE""")," @BOOK{Paxinos2012, title = {The Marmoset Brain in Stereotaxic Coordinates}, author = {Paxinos, George and Watson, Charles and Petrides, Michael and Rosa, Marcello and Tokuno, Hironobu}, publisher = ""Elsevier Science"", month = ""27~"&""" # oct, year = 2012, language = ""en"", isbn = ""9780124158184"" } ") -> @BOOK{Paxinos2012, title = {The Marmoset Brain in Stereotaxic Coordinates}, author = {Paxinos, George and Watson, Charles and Petrides, Michael and Rosa, Marcello and Tokuno, Hironobu}, publisher = "Elsevier Science", month = "27~" # oct, year = 2012, language = "en", isbn = "9780124158184" } | G89: =IFERROR(__xludf.DUMMYFUNCTION("""COMPUTED_VALUE"""),"Book") -> Book | H89: =IFERROR(__xludf.DUMMYFUNCTION("""COMPUTED_VALUE"""),"Paxinos, George, Watson, Charles, Petrides, Michael, Rosa, Marcello, Tokuno, Hironobu") -> Paxinos, George, Watson, Charles, Petrides, Michael, Rosa, Marcello, Tokuno, Hironobu | I89: =IFERROR(__xludf.DUMMYFUNCTION("""COMPUTED_VALUE"""),"The Marmoset Brain in Stereotaxic Coordinates") -> The Marmoset Brain in Stereotaxic Coordinates | J89: =IFERROR(__xludf.DUMMYFUNCTION("""COMPUTED_VALUE"""),"-") -> - | K89: =IFERROR(__xludf.DUMMYFUNCTION("""COMPUTED_VALUE"""),"https://www.marmosetbrain.org/reference https://journals.viamedica.pl/folia_morphologica/article/viewFile/16543/13176#page=1") -> https://www.marmosetbrain.org/reference https://journals.viamedica.pl/folia_morphologica/article/viewFile/16543/13176#page=1 | L89: =IFERROR(__xludf.DUMMYFUNCTION("""COMPUTED_VALUE"""),"Yudai Suzuki") -> Yudai Suzuki | M89: =IFERROR(__xludf.DUMMYFUNCTION("""COMPUTED_VALUE"""),"YS21Trust") -> YS21Trust
A90: =IFERROR(__xludf.DUMMYFUNCTION("""COMPUTED_VALUE"""),"Passingham, 2012") -> Passingham, 2012 | B90: =IFERROR(__xludf.DUMMYFUNCTION("""COMPUTED_VALUE"""),"DOC") -> DOC | C90: =IFERROR(__xludf.DUMMYFUNCTION("""COMPUTED_VALUE"""),"BIB") -> BIB | D90: =IFERROR(__xludf.DUMMYFUNCTION("""COMPUTED_VALUE"""),"10.1093/acprof:osobl/9780199552917.001.0001") -> 10.1093/acprof:osobl/9780199552917.001.0001 | E90: =IFERROR(__xludf.DUMMYFUNCTION("""COMPUTED_VALUE"""),"@book{Passingham_2012, doi = {10.1093/acprof:osobl/9780199552917.001.0001}, url = {https://doi.org/10.1093%2Facprof%3Aosobl%2F9780199552917.001.0001}, year = 2012, month = {jul}, publisher = {Oxford University Press"&"}, author = {Richard E. Passingham and Steven P. Wise}, title = {The Neurobiology of the Prefrontal Cortex} }") -> @book{Passingham_2012, doi = {10.1093/acprof:osobl/9780199552917.001.0001}, url = {https://doi.org/10.1093%2Facprof%3Aosobl%2F9780199552917.001.0001}, year = 2012, month = {jul}, publisher = {Oxford University Press}, author = {Richard E. Passingham and Steven P. Wise}, title = {The Neurobiology of the Prefrontal Cortex} } | G90: =IFERROR(__xludf.DUMMYFUNCTION("""COMPUTED_VALUE"""),"Book") -> Book | H90: =IFERROR(__xludf.DUMMYFUNCTION("""COMPUTED_VALUE"""),"Richard E. Passingham, Steven P. Wise") -> Richard E. Passingham, Steven P. Wise | I90: =IFERROR(__xludf.DUMMYFUNCTION("""COMPUTED_VALUE"""),"The Neurobiology of the Prefrontal Cortex") -> The Neurobiology of the Prefrontal Cortex | J90: =IFERROR(__xludf.DUMMYFUNCTION("""COMPUTED_VALUE"""),"-") -> -
A91: =IFERROR(__xludf.DUMMYFUNCTION("""COMPUTED_VALUE"""),"Pascual, 2013") -> Pascual, 2013 | B91: =IFERROR(__xludf.DUMMYFUNCTION("""COMPUTED_VALUE"""),"DOC") -> DOC | C91: =IFERROR(__xludf.DUMMYFUNCTION("""COMPUTED_VALUE"""),"BIB") -> BIB | D91: =IFERROR(__xludf.DUMMYFUNCTION("""COMPUTED_VALUE"""),"10.1093/cercor/bht260") -> 10.1093/cercor/bht260 | E91: =IFERROR(__xludf.DUMMYFUNCTION("""COMPUTED_VALUE"""),"@article{Pascual2013, doi = {10.1093/cercor/bht260}, url = {https://doi.org/10.1093/cercor/bht260}, year = {2013}, month = sep, publisher = {Oxford University Press ({OUP})}, volume = {25}, number = {3}, pages = {680--702}, author = {Bel"&"en Pascual and Joseph C. Masdeu and Mark Hollenbeck and Nikos Makris and Ricardo Insausti and Song-Lin Ding and Bradford C. Dickerson}, title = {Large-Scale Brain Networks of the Human Left Temporal Pole: A Functional Connectivity MRI Study}, journal "&"= {Cerebral Cortex} }") -> @article{Pascual2013, doi = {10.1093/cercor/bht260}, url = {https://doi.org/10.1093/cercor/bht260}, year = {2013}, month = sep, publisher = {Oxford University Press ({OUP})}, volume = {25}, number = {3}, pages = {680--702}, author = {Belen Pascual and Joseph C. Masdeu and Mark Hollenbeck and Nikos Makris and Ricardo Insausti and Song-Lin Ding and Bradford C. Dickerson}, title = {Large-Scale Brain Networks of the Human Left Temporal Pole: A Functional Connectivity MRI Study}, journal = {Cerebral Cortex} } | G91: =IFERROR(__xludf.DUMMYFUNCTION("""COMPUTED_VALUE"""),"Article") -> Article | H91: =IFERROR(__xludf.DUMMYFUNCTION("""COMPUTED_VALUE"""),"Belen Pascual, Joseph C. Masdeu, Mark Hollenbeck, Nikos Makris, Ricardo Insausti, Song-Lin Ding, Bradford C. Dickerson") -> Belen Pascual, Joseph C. Masdeu, Mark Hollenbeck, Nikos Makris, Ricardo Insausti, Song-Lin Ding, Bradford C. Dickerson | I91: =IFERROR(__xludf.DUMMYFUNCTION("""COMPUTED_VALUE"""),"Large-Scale Brain Networks of the Human Left Temporal Pole: A Functional Connectivity MRI Study") -> Large-Scale Brain Networks of the Human Left Temporal Pole: A Functional Connectivity MRI Study | J91: =IFERROR(__xludf.DUMMYFUNCTION("""COMPUTED_VALUE"""),"Cerebral Cortex") -> Cerebral Cortex | L91: =IFERROR(__xludf.DUMMYFUNCTION("""COMPUTED_VALUE"""),"Hiroshi Yamakawa") -> Hiroshi Yamakawa | M91: =IFERROR(__xludf.DUMMYFUNCTION("""COMPUTED_VALUE"""),"HY22DAA") -> HY22DAA
A92: =IFERROR(__xludf.DUMMYFUNCTION("""COMPUTED_VALUE"""),"OReilly, 2012-ne") -> OReilly, 2012-ne | B92: =IFERROR(__xludf.DUMMYFUNCTION("""COMPUTED_VALUE"""),"DOC(alt)") -> DOC(alt) | C92: =IFERROR(__xludf.DUMMYFUNCTION("""COMPUTED_VALUE"""),"(no DOI)") -> (no DOI) | E92: =IFERROR(__xludf.DUMMYFUNCTION("""COMPUTED_VALUE""")," @BOOK{OReilly2012-ne, title = {Computational cognitive neuroscience}, author = {O'Reilly, Randall C}, publisher = ""University of California Davis"", year = 2012, language = ""en"" }") -> @BOOK{OReilly2012-ne, title = {Computational cognitive neuroscience}, author = {O'Reilly, Randall C}, publisher = "University of California Davis", year = 2012, language = "en" } | G92: =IFERROR(__xludf.DUMMYFUNCTION("""COMPUTED_VALUE"""),"Book") -> Book | H92: =IFERROR(__xludf.DUMMYFUNCTION("""COMPUTED_VALUE"""),"O'Reilly, Randall C") -> O'Reilly, Randall C | I92: =IFERROR(__xludf.DUMMYFUNCTION("""COMPUTED_VALUE"""),"Computational cognitive neuroscience") -> Computational cognitive neuroscience | J92: =IFERROR(__xludf.DUMMYFUNCTION("""COMPUTED_VALUE"""),"-") -> - | K92: =IFERROR(__xludf.DUMMYFUNCTION("""COMPUTED_VALUE"""),"https://github.com/CompCogNeuro/ed4") -> https://github.com/CompCogNeuro/ed4
A93: =IFERROR(__xludf.DUMMYFUNCTION("""COMPUTED_VALUE"""),"OKeefe, 1976") -> OKeefe, 1976 | B93: =IFERROR(__xludf.DUMMYFUNCTION("""COMPUTED_VALUE"""),"DOC") -> DOC | C93: =IFERROR(__xludf.DUMMYFUNCTION("""COMPUTED_VALUE"""),"BIB") -> BIB | D93: =IFERROR(__xludf.DUMMYFUNCTION("""COMPUTED_VALUE"""),"10.1016/0014-4886(76)90055-8") -> 10.1016/0014-4886(76)90055-8 | E93: =IFERROR(__xludf.DUMMYFUNCTION("""COMPUTED_VALUE"""),"@article{O_Keefe_1976, doi = {10.1016/0014-4886(76)90055-8}, url = {https://doi.org/10.1016%2F0014-4886%2876%2990055-8}, year = 1976, month = {jan}, publisher = {Elsevier {BV}}, volume = {51}, number = {1}, pages = {78--109}, author = {John O{\te"&"xtquotesingle}Keefe}, title = {Place units in the hippocampus of the freely moving rat}, journal = {Experimental Neurology} }") -> @article{O_Keefe_1976, doi = {10.1016/0014-4886(76)90055-8}, url = {https://doi.org/10.1016%2F0014-4886%2876%2990055-8}, year = 1976, month = {jan}, publisher = {Elsevier {BV}}, volume = {51}, number = {1}, pages = {78--109}, author = {John O{\textquotesingle}Keefe}, title = {Place units in the hippocampus of the freely moving rat}, journal = {Experimental Neurology} } | G93: =IFERROR(__xludf.DUMMYFUNCTION("""COMPUTED_VALUE"""),"Article") -> Article | H93: =IFERROR(__xludf.DUMMYFUNCTION("""COMPUTED_VALUE"""),"John O{\textquotesingle}Keefe") -> John O{\textquotesingle}Keefe | I93: =IFERROR(__xludf.DUMMYFUNCTION("""COMPUTED_VALUE"""),"Place units in the hippocampus of the freely moving rat") -> Place units in the hippocampus of the freely moving rat | J93: =IFERROR(__xludf.DUMMYFUNCTION("""COMPUTED_VALUE"""),"Experimental Neurology") -> Experimental Neurology | L93: =IFERROR(__xludf.DUMMYFUNCTION("""COMPUTED_VALUE"""),"Ayako Fukawa") -> Ayako Fukawa | M93: =IFERROR(__xludf.DUMMYFUNCTION("""COMPUTED_VALUE"""),"AT20HippocampalFormation") -> AT20HippocampalFormation
A94: =IFERROR(__xludf.DUMMYFUNCTION("""COMPUTED_VALUE"""),"OKeefe, 1976") -> OKeefe, 1976 | B94: =IFERROR(__xludf.DUMMYFUNCTION("""COMPUTED_VALUE"""),"DOC") -> DOC | C94: =IFERROR(__xludf.DUMMYFUNCTION("""COMPUTED_VALUE"""),"BIB") -> BIB | D94: =IFERROR(__xludf.DUMMYFUNCTION("""COMPUTED_VALUE"""),"10.1016/0014-4886(76)90055-8") -> 10.1016/0014-4886(76)90055-8 | E94: =IFERROR(__xludf.DUMMYFUNCTION("""COMPUTED_VALUE"""),"@article{O_Keefe_1976, doi = {10.1016/0014-4886(76)90055-8}, url = {https://doi.org/10.1016%2F0014-4886%2876%2990055-8}, year = 1976, month = {jan}, publisher = {Elsevier {BV}}, volume = {51}, number = {1}, pages = {78--109}, author = {John O{\te"&"xtquotesingle}Keefe}, title = {Place units in the hippocampus of the freely moving rat}, journal = {Experimental Neurology} }") -> @article{O_Keefe_1976, doi = {10.1016/0014-4886(76)90055-8}, url = {https://doi.org/10.1016%2F0014-4886%2876%2990055-8}, year = 1976, month = {jan}, publisher = {Elsevier {BV}}, volume = {51}, number = {1}, pages = {78--109}, author = {John O{\textquotesingle}Keefe}, title = {Place units in the hippocampus of the freely moving rat}, journal = {Experimental Neurology} } | G94: =IFERROR(__xludf.DUMMYFUNCTION("""COMPUTED_VALUE"""),"Article") -> Article | H94: =IFERROR(__xludf.DUMMYFUNCTION("""COMPUTED_VALUE"""),"John O{\textquotesingle}Keefe") -> John O{\textquotesingle}Keefe | I94: =IFERROR(__xludf.DUMMYFUNCTION("""COMPUTED_VALUE"""),"Place units in the hippocampus of the freely moving rat") -> Place units in the hippocampus of the freely moving rat | J94: =IFERROR(__xludf.DUMMYFUNCTION("""COMPUTED_VALUE"""),"Experimental Neurology") -> Experimental Neurology
A95: =IFERROR(__xludf.DUMMYFUNCTION("""COMPUTED_VALUE"""),"Ohara, 2018") -> Ohara, 2018 | B95: =IFERROR(__xludf.DUMMYFUNCTION("""COMPUTED_VALUE"""),"DOC") -> DOC | C95: =IFERROR(__xludf.DUMMYFUNCTION("""COMPUTED_VALUE"""),"BIB") -> BIB | D95: =IFERROR(__xludf.DUMMYFUNCTION("""COMPUTED_VALUE"""),"10.1016/j.celrep.2018.06.014") -> 10.1016/j.celrep.2018.06.014 | E95: =IFERROR(__xludf.DUMMYFUNCTION("""COMPUTED_VALUE"""),"@article{Ohara_2018, doi = {10.1016/j.celrep.2018.06.014}, url = {https://doi.org/10.1016%2Fj.celrep.2018.06.014}, year = 2018, month = {jul}, publisher = {Elsevier {BV}}, volume = {24}, number = {1}, pages = {107--116}, author = {Shinya Ohara an"&"d Mariko Onodera and {\O}yvind W. Simonsen and Rintaro Yoshino and Hiroyuki Hioki and Toshio Iijima and Ken-Ichiro Tsutsui and Menno P. Witter}, title = {Intrinsic Projections of Layer Vb Neurons to Layers Va, {III}, and {II} in the Lateral and Medial En"&"torhinal Cortex of the Rat}, journal = {Cell Reports} }") -> @article{Ohara_2018, doi = {10.1016/j.celrep.2018.06.014}, url = {https://doi.org/10.1016%2Fj.celrep.2018.06.014}, year = 2018, month = {jul}, publisher = {Elsevier {BV}}, volume = {24}, number = {1}, pages = {107--116}, author = {Shinya Ohara and Mariko Onodera and {\O}yvind W. Simonsen and Rintaro Yoshino and Hiroyuki Hioki and Toshio Iijima and Ken-Ichiro Tsutsui and Menno P. Witter}, title = {Intrinsic Projections of Layer Vb Neurons to Layers Va, {III}, and {II} in the Lateral and Medial Entorhinal Cortex of the Rat}, journal = {Cell Reports} } | G95: =IFERROR(__xludf.DUMMYFUNCTION("""COMPUTED_VALUE"""),"Article") -> Article | H95: =IFERROR(__xludf.DUMMYFUNCTION("""COMPUTED_VALUE"""),"Shinya Ohara, Mariko Onodera, {\O}yvind W. Simonsen, Rintaro Yoshino, Hiroyuki Hioki, Toshio Iijima, Ken-Ichiro Tsutsui, Menno P. Witter") -> Shinya Ohara, Mariko Onodera, {\O}yvind W. Simonsen, Rintaro Yoshino, Hiroyuki Hioki, Toshio Iijima, Ken-Ichiro Tsutsui, Menno P. Witter | I95: =IFERROR(__xludf.DUMMYFUNCTION("""COMPUTED_VALUE"""),"Intrinsic Projections of Layer Vb Neurons to Layers Va, {III}, and {II} in the Lateral and Medial Entorhinal Cortex of the Rat") -> Intrinsic Projections of Layer Vb Neurons to Layers Va, {III}, and {II} in the Lateral and Medial Entorhinal Cortex of the Rat | J95: =IFERROR(__xludf.DUMMYFUNCTION("""COMPUTED_VALUE"""),"Cell Reports") -> Cell Reports | L95: =IFERROR(__xludf.DUMMYFUNCTION("""COMPUTED_VALUE"""),"Ayako Fukawa") -> Ayako Fukawa | M95: =IFERROR(__xludf.DUMMYFUNCTION("""COMPUTED_VALUE"""),"AT20HippocampalFormation") -> AT20HippocampalFormation
A96: =IFERROR(__xludf.DUMMYFUNCTION("""COMPUTED_VALUE"""),"Noda, 1990") -> Noda, 1990 | B96: =IFERROR(__xludf.DUMMYFUNCTION("""COMPUTED_VALUE"""),"DOC") -> DOC | C96: =IFERROR(__xludf.DUMMYFUNCTION("""COMPUTED_VALUE"""),"BIB") -> BIB | D96: =IFERROR(__xludf.DUMMYFUNCTION("""COMPUTED_VALUE"""),"10.1002/cne.903020211") -> 10.1002/cne.903020211 | E96: =IFERROR(__xludf.DUMMYFUNCTION("""COMPUTED_VALUE"""),"@article{Noda_1990, doi = {10.1002/cne.903020211}, url = {https://doi.org/10.1002%2Fcne.903020211}, year = 1990, month = {dec}, publisher = {Wiley}, volume = {302}, number = {2}, pages = {330--348}, author = {Hiroharu Noda and Shoei Sugita and Yo"&"ichi Ikeda}, title = {Afferent and efferent connections of the oculomotor region of the fastigial nucleus in the macaque monkey}, journal = {The Journal of Comparative Neurology} }") -> @article{Noda_1990, doi = {10.1002/cne.903020211}, url = {https://doi.org/10.1002%2Fcne.903020211}, year = 1990, month = {dec}, publisher = {Wiley}, volume = {302}, number = {2}, pages = {330--348}, author = {Hiroharu Noda and Shoei Sugita and Yoichi Ikeda}, title = {Afferent and efferent connections of the oculomotor region of the fastigial nucleus in the macaque monkey}, journal = {The Journal of Comparative Neurology} } | G96: =IFERROR(__xludf.DUMMYFUNCTION("""COMPUTED_VALUE"""),"Article") -> Article | H96: =IFERROR(__xludf.DUMMYFUNCTION("""COMPUTED_VALUE"""),"Hiroharu Noda, Shoei Sugita, Yoichi Ikeda") -> Hiroharu Noda, Shoei Sugita, Yoichi Ikeda | I96: =IFERROR(__xludf.DUMMYFUNCTION("""COMPUTED_VALUE"""),"Afferent and efferent connections of the oculomotor region of the fastigial nucleus in the macaque monkey") -> Afferent and efferent connections of the oculomotor region of the fastigial nucleus in the macaque monkey | J96: =IFERROR(__xludf.DUMMYFUNCTION("""COMPUTED_VALUE"""),"The Journal of Comparative Neurology") -> The Journal of Comparative Neurology | L96: =IFERROR(__xludf.DUMMYFUNCTION("""COMPUTED_VALUE"""),"Yoshinasa Tawatsji") -> Yoshinasa Tawatsji | M96: =IFERROR(__xludf.DUMMYFUNCTION("""COMPUTED_VALUE"""),"Oculomotor") -> Oculomotor
A97: =IFERROR(__xludf.DUMMYFUNCTION("""COMPUTED_VALUE"""),"Munoz, 1993") -> Munoz, 1993 | B97: =IFERROR(__xludf.DUMMYFUNCTION("""COMPUTED_VALUE"""),"DOC") -> DOC | C97: =IFERROR(__xludf.DUMMYFUNCTION("""COMPUTED_VALUE"""),"BIB") -> BIB | D97: =IFERROR(__xludf.DUMMYFUNCTION("""COMPUTED_VALUE"""),"10.1152/jn.1993.70.2.559") -> 10.1152/jn.1993.70.2.559 | E97: =IFERROR(__xludf.DUMMYFUNCTION("""COMPUTED_VALUE"""),"@article{Munoz_1993, doi = {10.1152/jn.1993.70.2.559}, url = {https://doi.org/10.1152%2Fjn.1993.70.2.559}, year = 1993, month = {aug}, publisher = {American Physiological Society}, volume = {70}, number = {2}, pages = {559--575}, author = {D. P. "&"Munoz and R. H. Wurtz}, title = {Fixation cells in monkey superior colliculus. I. Characteristics of cell discharge}, journal = {Journal of Neurophysiology} }") -> @article{Munoz_1993, doi = {10.1152/jn.1993.70.2.559}, url = {https://doi.org/10.1152%2Fjn.1993.70.2.559}, year = 1993, month = {aug}, publisher = {American Physiological Society}, volume = {70}, number = {2}, pages = {559--575}, author = {D. P. Munoz and R. H. Wurtz}, title = {Fixation cells in monkey superior colliculus. I. Characteristics of cell discharge}, journal = {Journal of Neurophysiology} } | G97: =IFERROR(__xludf.DUMMYFUNCTION("""COMPUTED_VALUE"""),"Article") -> Article | H97: =IFERROR(__xludf.DUMMYFUNCTION("""COMPUTED_VALUE"""),"D. P. Munoz, R. H. Wurtz") -> D. P. Munoz, R. H. Wurtz | I97: =IFERROR(__xludf.DUMMYFUNCTION("""COMPUTED_VALUE"""),"Fixation cells in monkey superior colliculus. I. Characteristics of cell discharge") -> Fixation cells in monkey superior colliculus. I. Characteristics of cell discharge | J97: =IFERROR(__xludf.DUMMYFUNCTION("""COMPUTED_VALUE"""),"Journal of Neurophysiology") -> Journal of Neurophysiology | L97: =IFERROR(__xludf.DUMMYFUNCTION("""COMPUTED_VALUE"""),"Yoshinasa Tawatsji") -> Yoshinasa Tawatsji | M97: =IFERROR(__xludf.DUMMYFUNCTION("""COMPUTED_VALUE"""),"Oculomotor") -> Oculomotor
A98: =IFERROR(__xludf.DUMMYFUNCTION("""COMPUTED_VALUE"""),"Mungall, 2012") -> Mungall, 2012 | B98: =IFERROR(__xludf.DUMMYFUNCTION("""COMPUTED_VALUE"""),"DOC") -> DOC | C98: =IFERROR(__xludf.DUMMYFUNCTION("""COMPUTED_VALUE"""),"BIB") -> BIB | D98: =IFERROR(__xludf.DUMMYFUNCTION("""COMPUTED_VALUE"""),"10.1186/gb-2012-13-1-r5") -> 10.1186/gb-2012-13-1-r5 | E98: =IFERROR(__xludf.DUMMYFUNCTION("""COMPUTED_VALUE"""),"@article{Mungall2012, doi = {10.1186/gb-2012-13-1-r5}, url = {https://doi.org/10.1186/gb-2012-13-1-r5}, year = {2012}, publisher = {Springer Science and Business Media {LLC}}, volume = {13}, number = {1}, pages = {R5}, author = {Ch"&"ristopher J Mungall and Carlo Torniai and Georgios V Gkoutos and Suzanna E Lewis and Melissa A Haendel}, title = {Uberon, an integrative multi-species anatomy ontology}, journal = {Genome Biology} }") -> @article{Mungall2012, doi = {10.1186/gb-2012-13-1-r5}, url = {https://doi.org/10.1186/gb-2012-13-1-r5}, year = {2012}, publisher = {Springer Science and Business Media {LLC}}, volume = {13}, number = {1}, pages = {R5}, author = {Christopher J Mungall and Carlo Torniai and Georgios V Gkoutos and Suzanna E Lewis and Melissa A Haendel}, title = {Uberon, an integrative multi-species anatomy ontology}, journal = {Genome Biology} } | G98: =IFERROR(__xludf.DUMMYFUNCTION("""COMPUTED_VALUE"""),"Article") -> Article | H98: =IFERROR(__xludf.DUMMYFUNCTION("""COMPUTED_VALUE"""),"Christopher J Mungall, Carlo Torniai, Georgios V Gkoutos, Suzanna E Lewis, Melissa A Haendel") -> Christopher J Mungall, Carlo Torniai, Georgios V Gkoutos, Suzanna E Lewis, Melissa A Haendel | I98: =IFERROR(__xludf.DUMMYFUNCTION("""COMPUTED_VALUE"""),"Uberon, an integrative multi-species anatomy ontology") -> Uberon, an integrative multi-species anatomy ontology | J98: =IFERROR(__xludf.DUMMYFUNCTION("""COMPUTED_VALUE"""),"Genome Biology") -> Genome Biology | L98: =IFERROR(__xludf.DUMMYFUNCTION("""COMPUTED_VALUE"""),"Hiroshi Yamakawa") -> Hiroshi Yamakawa | M98: =IFERROR(__xludf.DUMMYFUNCTION("""COMPUTED_VALUE"""),"HY20Cerebellum") -> HY20Cerebellum
A99: =IFERROR(__xludf.DUMMYFUNCTION("""COMPUTED_VALUE"""),"Moser, 2010") -> Moser, 2010 | B99: =IFERROR(__xludf.DUMMYFUNCTION("""COMPUTED_VALUE"""),"DOC") -> DOC | C99: =IFERROR(__xludf.DUMMYFUNCTION("""COMPUTED_VALUE"""),"BIB") -> BIB | D99: =IFERROR(__xludf.DUMMYFUNCTION("""COMPUTED_VALUE"""),"10.1093/med/9780195389883.003.0017") -> 10.1093/med/9780195389883.003.0017 | E99: =IFERROR(__xludf.DUMMYFUNCTION("""COMPUTED_VALUE"""),"@incollection{Moser_2010, doi = {10.1093/med/9780195389883.003.0017}, url = {https://doi.org/10.1093%2Fmed%2F9780195389883.003.0017}, year = 2010, month = {aug}, publisher = {Oxford University Press}, pages = {175--190}, author = {Edvard I. Moser a"&"nd Menno P. Witter and May-Britt Moser}, title = {Entorhinal Cortex}, booktitle = {Handbook of Brain Microcircuits} }") -> @incollection{Moser_2010, doi = {10.1093/med/9780195389883.003.0017}, url = {https://doi.org/10.1093%2Fmed%2F9780195389883.003.0017}, year = 2010, month = {aug}, publisher = {Oxford University Press}, pages = {175--190}, author = {Edvard I. Moser and Menno P. Witter and May-Britt Moser}, title = {Entorhinal Cortex}, booktitle = {Handbook of Brain Microcircuits} } | F99: =IFERROR(__xludf.DUMMYFUNCTION("""COMPUTED_VALUE"""),"Textbook") -> Textbook | G99: =IFERROR(__xludf.DUMMYFUNCTION("""COMPUTED_VALUE"""),"Incollection") -> Incollection | H99: =IFERROR(__xludf.DUMMYFUNCTION("""COMPUTED_VALUE"""),"Edvard I. Moser, Menno P. Witter, May-Britt Moser") -> Edvard I. Moser, Menno P. Witter, May-Britt Moser | I99: =IFERROR(__xludf.DUMMYFUNCTION("""COMPUTED_VALUE"""),"Entorhinal Cortex") -> Entorhinal Cortex | J99: =IFERROR(__xludf.DUMMYFUNCTION("""COMPUTED_VALUE"""),"Handbook of Brain Microcircuits") -> Handbook of Brain Microcircuits | K99: =IFERROR(__xludf.DUMMYFUNCTION("""COMPUTED_VALUE"""),"https://oxfordmedicine.com/view/10.1093/med/9780195389883.001.0001/med-9780195389883") -> https://oxfordmedicine.com/view/10.1093/med/9780195389883.001.0001/med-9780195389883 | L99: =IFERROR(__xludf.DUMMYFUNCTION("""COMPUTED_VALUE"""),"Ayako Fukawa") -> Ayako Fukawa | M99: =IFERROR(__xludf.DUMMYFUNCTION("""COMPUTED_VALUE"""),"AT20HippocampalFormation") -> AT20HippocampalFormation
A100: =IFERROR(__xludf.DUMMYFUNCTION("""COMPUTED_VALUE"""),"Monakow, 1978") -> Monakow, 1978 | B100: =IFERROR(__xludf.DUMMYFUNCTION("""COMPUTED_VALUE"""),"DOC") -> DOC | C100: =IFERROR(__xludf.DUMMYFUNCTION("""COMPUTED_VALUE"""),"BIB") -> BIB | D100: =IFERROR(__xludf.DUMMYFUNCTION("""COMPUTED_VALUE"""),"10.1007/BF00235561") -> 10.1007/BF00235561 | E100: =IFERROR(__xludf.DUMMYFUNCTION("""COMPUTED_VALUE"""),"@article{Monakow_1978, doi = {10.1007/bf00235561}, url = {https://doi.org/10.1007%2Fbf00235561}, year = 1978, publisher = {Springer Science and Business Media {LLC}}, volume = {33}, number = {3-4}, a"&"uthor = {K.Hartmann-von Monakow and K. Akert and H. Künzle }, title = {Projections of the precentral motor cortex and other cortical areas of the frontal lobe to the subthalamic nucleus in the monkey}, journal = {Experimental Brain Researc"&"h} }") -> @article{Monakow_1978, doi = {10.1007/bf00235561}, url = {https://doi.org/10.1007%2Fbf00235561}, year = 1978, publisher = {Springer Science and Business Media {LLC}}, volume = {33}, number = {3-4}, author = {K.Hartmann-von Monakow and K. Akert and H. Künzle }, title = {Projections of the precentral motor cortex and other cortical areas of the frontal lobe to the subthalamic nucleus in the monkey}, journal = {Experimental Brain Research} } | G100: =IFERROR(__xludf.DUMMYFUNCTION("""COMPUTED_VALUE"""),"Article") -> Article | H100: =IFERROR(__xludf.DUMMYFUNCTION("""COMPUTED_VALUE"""),"K.Hartmann-von Monakow, K. Akert, H. Künzle ") -> K.Hartmann-von Monakow, K. Akert, H. Künzle | I100: =IFERROR(__xludf.DUMMYFUNCTION("""COMPUTED_VALUE"""),"Projections of the precentral motor cortex and other cortical areas of the frontal lobe to the subthalamic nucleus in the monkey") -> Projections of the precentral motor cortex and other cortical areas of the frontal lobe to the subthalamic nucleus in the monkey | J100: =IFERROR(__xludf.DUMMYFUNCTION("""COMPUTED_VALUE"""),"Experimental Brain Research") -> Experimental Brain Research | L100: =IFERROR(__xludf.DUMMYFUNCTION("""COMPUTED_VALUE"""),"Yuske Shibata") -> Yuske Shibata | M100: =IFERROR(__xludf.DUMMYFUNCTION("""COMPUTED_VALUE"""),"YS21BgLoop") -> YS21BgLoop
A101: =IFERROR(__xludf.DUMMYFUNCTION("""COMPUTED_VALUE"""),"Monakow, 1978") -> Monakow, 1978 | B101: =IFERROR(__xludf.DUMMYFUNCTION("""COMPUTED_VALUE"""),"DOC") -> DOC | C101: =IFERROR(__xludf.DUMMYFUNCTION("""COMPUTED_VALUE"""),"BIB") -> BIB | D101: =IFERROR(__xludf.DUMMYFUNCTION("""COMPUTED_VALUE"""),"10.1007/BF00235561") -> 10.1007/BF00235561 | E101: =IFERROR(__xludf.DUMMYFUNCTION("""COMPUTED_VALUE"""),"@article{Monakow_1978, doi = {10.1007/bf00235561}, url = {https://doi.org/10.1007%2Fbf00235561}, year = 1978, publisher = {Springer Science and Business Media {LLC}}, volume = {33}, number = {3-4}, a"&"uthor = {K.Hartmann-von Monakow and K. Akert and H. Künzle }, title = {Projections of the precentral motor cortex and other cortical areas of the frontal lobe to the subthalamic nucleus in the monkey}, journal = {Experimental Brain Researc"&"h} }") -> @article{Monakow_1978, doi = {10.1007/bf00235561}, url = {https://doi.org/10.1007%2Fbf00235561}, year = 1978, publisher = {Springer Science and Business Media {LLC}}, volume = {33}, number = {3-4}, author = {K.Hartmann-von Monakow and K. Akert and H. Künzle }, title = {Projections of the precentral motor cortex and other cortical areas of the frontal lobe to the subthalamic nucleus in the monkey}, journal = {Experimental Brain Research} } | G101: =IFERROR(__xludf.DUMMYFUNCTION("""COMPUTED_VALUE"""),"Article") -> Article | H101: =IFERROR(__xludf.DUMMYFUNCTION("""COMPUTED_VALUE"""),"K.Hartmann-von Monakow, K. Akert, H. Künzle ") -> K.Hartmann-von Monakow, K. Akert, H. Künzle | I101: =IFERROR(__xludf.DUMMYFUNCTION("""COMPUTED_VALUE"""),"Projections of the precentral motor cortex and other cortical areas of the frontal lobe to the subthalamic nucleus in the monkey") -> Projections of the precentral motor cortex and other cortical areas of the frontal lobe to the subthalamic nucleus in the monkey | J101: =IFERROR(__xludf.DUMMYFUNCTION("""COMPUTED_VALUE"""),"Experimental Brain Research") -> Experimental Brain Research | L101: =IFERROR(__xludf.DUMMYFUNCTION("""COMPUTED_VALUE"""),"Yuske Shibata") -> Yuske Shibata | M101: =IFERROR(__xludf.DUMMYFUNCTION("""COMPUTED_VALUE"""),"YS21BgLoop") -> YS21BgLoop
...

Sheet Circuits
A1: =IFERROR(__xludf.DUMMYFUNCTION("IMPORTRANGE(Settings!$A$2,""wbCircuits!A1:AM1"")"),"Circuit ID") -> Circuit ID | B1: =IFERROR(__xludf.DUMMYFUNCTION("""COMPUTED_VALUE"""),"Source of ID") -> Source of ID | C1: =IFERROR(__xludf.DUMMYFUNCTION("""COMPUTED_VALUE"""),"Names") -> Names | D1: =IFERROR(__xludf.DUMMYFUNCTION("""COMPUTED_VALUE"""),"DHBA: graph_order") -> DHBA: graph_order | E1: =IFERROR(__xludf.DUMMYFUNCTION("""COMPUTED_VALUE"""),"DHBA: name") -> DHBA: name | F1: =IFERROR(__xludf.DUMMYFUNCTION("""COMPUTED_VALUE"""),"DHBA: Lv.2") -> DHBA: Lv.2 | G1: =IFERROR(__xludf.DUMMYFUNCTION("""COMPUTED_VALUE"""),"DHBA: Lv.3") -> DHBA: Lv.3 | H1: =IFERROR(__xludf.DUMMYFUNCTION("""COMPUTED_VALUE"""),"DHBA: Lv.4") -> DHBA: Lv.4 | I1: =IFERROR(__xludf.DUMMYFUNCTION("""COMPUTED_VALUE"""),"DHBA: Lv.5") -> DHBA: Lv.5 | J1: =IFERROR(__xludf.DUMMYFUNCTION("""COMPUTED_VALUE"""),"DHBA: Lv.6") -> DHBA: Lv.6 | K1: =IFERROR(__xludf.DUMMYFUNCTION("""COMPUTED_VALUE"""),"DHBA: Lv.7") -> DHBA: Lv.7 | L1: =IFERROR(__xludf.DUMMYFUNCTION("""COMPUTED_VALUE"""),"DHBA: Lv.8") -> DHBA: Lv.8 | M1: =IFERROR(__xludf.DUMMYFUNCTION("""COMPUTED_VALUE"""),"DHBA: Lv.9") -> DHBA: Lv.9 | N1: =IFERROR(__xludf.DUMMYFUNCTION("""COMPUTED_VALUE"""),"DHBA: Lv.10") -> DHBA: Lv.10 | O1: =IFERROR(__xludf.DUMMYFUNCTION("""COMPUTED_VALUE"""),"DHBA: Lv.11") -> DHBA: Lv.11 | P1: =IFERROR(__xludf.DUMMYFUNCTION("""COMPUTED_VALUE"""),"DHBA: Lv.12") -> DHBA: Lv.12 | Q1: =IFERROR(__xludf.DUMMYFUNCTION("""COMPUTED_VALUE"""),"DHBA: Lv.13") -> DHBA: Lv.13 | R1: =IFERROR(__xludf.DUMMYFUNCTION("""COMPUTED_VALUE"""),"DHBA: Lv.14") -> DHBA: Lv.14 | S1: =IFERROR(__xludf.DUMMYFUNCTION("""COMPUTED_VALUE"""),"Sub-Circuits") -> Sub-Circuits | T1: =IFERROR(__xludf.DUMMYFUNCTION("""COMPUTED_VALUE"""),"Super Class ") -> Super Class | U1: =IFERROR(__xludf.DUMMYFUNCTION("""COMPUTED_VALUE"""),"Uniform") -> Uniform | V1: =IFERROR(__xludf.DUMMYFUNCTION("""COMPUTED_VALUE"""),"Transmitter") -> Transmitter | W1: =IFERROR(__xludf.DUMMYFUNCTION("""COMPUTED_VALUE"""),"Modulation Type") -> Modulation Type | X1: =IFERROR(__xludf.DUMMYFUNCTION("""COMPUTED_VALUE"""),"Size") -> Size | Y1: =IFERROR(__xludf.DUMMYFUNCTION("""COMPUTED_VALUE"""),"Output Semantics (0)") -> Output Semantics (0) | Z1: =IFERROR(__xludf.DUMMYFUNCTION("""COMPUTED_VALUE"""),"Physiological Data") -> Physiological Data | AA1: =IFERROR(__xludf.DUMMYFUNCTION("""COMPUTED_VALUE"""),"Comments") -> Comments | AB1: =IFERROR(__xludf.DUMMYFUNCTION("""COMPUTED_VALUE"""),"Contributor") -> Contributor | AC1: =IFERROR(__xludf.DUMMYFUNCTION("""COMPUTED_VALUE"""),"Project ID") -> Project ID | AD1: =IFERROR(__xludf.DUMMYFUNCTION("""COMPUTED_VALUE"""),"Contributor Response to Reviewers") -> Contributor Response to Reviewers | AE1: =IFERROR(__xludf.DUMMYFUNCTION("""COMPUTED_VALUE"""),"Status") -> Status | AF1: =IFERROR(__xludf.DUMMYFUNCTION("""COMPUTED_VALUE"""),"Review results") -> Review results | AG1: =IFERROR(__xludf.DUMMYFUNCTION("""COMPUTED_VALUE"""),"Auto Error Codes") -> Auto Error Codes | AH1: =IFERROR(__xludf.DUMMYFUNCTION("""COMPUTED_VALUE"""),"Error Code-1") -> Error Code-1 | AI1: =IFERROR(__xludf.DUMMYFUNCTION("""COMPUTED_VALUE"""),"Error Code-2") -> Error Code-2 | AJ1: =IFERROR(__xludf.DUMMYFUNCTION("""COMPUTED_VALUE"""),"Other Error Codes") -> Other Error Codes | AK1: =IFERROR(__xludf.DUMMYFUNCTION("""COMPUTED_VALUE"""),"Review comments") -> Review comments | AL1: =IFERROR(__xludf.DUMMYFUNCTION("""COMPUTED_VALUE"""),"Reviewer") -> Reviewer | AM1: =IFERROR(__xludf.DUMMYFUNCTION("""COMPUTED_VALUE"""),"Reviewed date") -> Reviewed date | AO1: [WS] ROI Circuits
A2: ROI_ | AO2: =IFERROR(__xludf.DUMMYFUNCTION("IF(ISBLANK(A2),,IF(ISBLANK(S2), A2&"";"", TEXTJOIN(CHAR(10), TRUE, A2&"";"", ARRAYFORMULA(VLOOKUP(SPLIT(S2, "";"" & CHAR(10)), $A:$AO, 41, FALSE)))))"),"ROI_;") -> ROI_;
AO3: =IFERROR(__xludf.DUMMYFUNCTION("IF(ISBLANK(A3),,IF(ISBLANK(S3), A3&"";"", TEXTJOIN(CHAR(10), TRUE, A3&"";"", ARRAYFORMULA(VLOOKUP(SPLIT(S3, "";"" & CHAR(10)), $A:$AO, 41, FALSE)))))"),"")
AO4: =IFERROR(__xludf.DUMMYFUNCTION("IF(ISBLANK(A4),,IF(ISBLANK(S4), A4&"";"", TEXTJOIN(CHAR(10), TRUE, A4&"";"", ARRAYFORMULA(VLOOKUP(SPLIT(S4, "";"" & CHAR(10)), $A:$AO, 41, FALSE)))))"),"")
AO5: =IFERROR(__xludf.DUMMYFUNCTION("IF(ISBLANK(A5),,IF(ISBLANK(S5), A5&"";"", TEXTJOIN(CHAR(10), TRUE, A5&"";"", ARRAYFORMULA(VLOOKUP(SPLIT(S5, "";"" & CHAR(10)), $A:$AO, 41, FALSE)))))"),"")
AO6: =IFERROR(__xludf.DUMMYFUNCTION("IF(ISBLANK(A6),,IF(ISBLANK(S6), A6&"";"", TEXTJOIN(CHAR(10), TRUE, A6&"";"", ARRAYFORMULA(VLOOKUP(SPLIT(S6, "";"" & CHAR(10)), $A:$AO, 41, FALSE)))))"),"")
AO7: =IFERROR(__xludf.DUMMYFUNCTION("IF(ISBLANK(A7),,IF(ISBLANK(S7), A7&"";"", TEXTJOIN(CHAR(10), TRUE, A7&"";"", ARRAYFORMULA(VLOOKUP(SPLIT(S7, "";"" & CHAR(10)), $A:$AO, 41, FALSE)))))"),"")
AO8: =IFERROR(__xludf.DUMMYFUNCTION("IF(ISBLANK(A8),,IF(ISBLANK(S8), A8&"";"", TEXTJOIN(CHAR(10), TRUE, A8&"";"", ARRAYFORMULA(VLOOKUP(SPLIT(S8, "";"" & CHAR(10)), $A:$AO, 41, FALSE)))))"),"")
AO9: =IFERROR(__xludf.DUMMYFUNCTION("IF(ISBLANK(A9),,IF(ISBLANK(S9), A9&"";"", TEXTJOIN(CHAR(10), TRUE, A9&"";"", ARRAYFORMULA(VLOOKUP(SPLIT(S9, "";"" & CHAR(10)), $A:$AO, 41, FALSE)))))"),"")
AO10: =IFERROR(__xludf.DUMMYFUNCTION("IF(ISBLANK(A10),,IF(ISBLANK(S10), A10&"";"", TEXTJOIN(CHAR(10), TRUE, A10&"";"", ARRAYFORMULA(VLOOKUP(SPLIT(S10, "";"" & CHAR(10)), $A:$AO, 41, FALSE)))))"),"")
AO11: =IFERROR(__xludf.DUMMYFUNCTION("IF(ISBLANK(A11),,IF(ISBLANK(S11), A11&"";"", TEXTJOIN(CHAR(10), TRUE, A11&"";"", ARRAYFORMULA(VLOOKUP(SPLIT(S11, "";"" & CHAR(10)), $A:$AO, 41, FALSE)))))"),"")
AO12: =IFERROR(__xludf.DUMMYFUNCTION("IF(ISBLANK(A12),,IF(ISBLANK(S12), A12&"";"", TEXTJOIN(CHAR(10), TRUE, A12&"";"", ARRAYFORMULA(VLOOKUP(SPLIT(S12, "";"" & CHAR(10)), $A:$AO, 41, FALSE)))))"),"")
AO13: =IFERROR(__xludf.DUMMYFUNCTION("IF(ISBLANK(A13),,IF(ISBLANK(S13), A13&"";"", TEXTJOIN(CHAR(10), TRUE, A13&"";"", ARRAYFORMULA(VLOOKUP(SPLIT(S13, "";"" & CHAR(10)), $A:$AO, 41, FALSE)))))"),"")
AO14: =IFERROR(__xludf.DUMMYFUNCTION("IF(ISBLANK(A14),,IF(ISBLANK(S14), A14&"";"", TEXTJOIN(CHAR(10), TRUE, A14&"";"", ARRAYFORMULA(VLOOKUP(SPLIT(S14, "";"" & CHAR(10)), $A:$AO, 41, FALSE)))))"),"")
AO15: =IFERROR(__xludf.DUMMYFUNCTION("IF(ISBLANK(A15),,IF(ISBLANK(S15), A15&"";"", TEXTJOIN(CHAR(10), TRUE, A15&"";"", ARRAYFORMULA(VLOOKUP(SPLIT(S15, "";"" & CHAR(10)), $A:$AO, 41, FALSE)))))"),"")
AO16: =IFERROR(__xludf.DUMMYFUNCTION("IF(ISBLANK(A16),,IF(ISBLANK(S16), A16&"";"", TEXTJOIN(CHAR(10), TRUE, A16&"";"", ARRAYFORMULA(VLOOKUP(SPLIT(S16, "";"" & CHAR(10)), $A:$AO, 41, FALSE)))))"),"")
AO17: =IFERROR(__xludf.DUMMYFUNCTION("IF(ISBLANK(A17),,IF(ISBLANK(S17), A17&"";"", TEXTJOIN(CHAR(10), TRUE, A17&"";"", ARRAYFORMULA(VLOOKUP(SPLIT(S17, "";"" & CHAR(10)), $A:$AO, 41, FALSE)))))"),"")
AO18: =IFERROR(__xludf.DUMMYFUNCTION("IF(ISBLANK(A18),,IF(ISBLANK(S18), A18&"";"", TEXTJOIN(CHAR(10), TRUE, A18&"";"", ARRAYFORMULA(VLOOKUP(SPLIT(S18, "";"" & CHAR(10)), $A:$AO, 41, FALSE)))))"),"")
AO19: =IFERROR(__xludf.DUMMYFUNCTION("IF(ISBLANK(A19),,IF(ISBLANK(S19), A19&"";"", TEXTJOIN(CHAR(10), TRUE, A19&"";"", ARRAYFORMULA(VLOOKUP(SPLIT(S19, "";"" & CHAR(10)), $A:$AO, 41, FALSE)))))"),"")
AO20: =IFERROR(__xludf.DUMMYFUNCTION("IF(ISBLANK(A20),,IF(ISBLANK(S20), A20&"";"", TEXTJOIN(CHAR(10), TRUE, A20&"";"", ARRAYFORMULA(VLOOKUP(SPLIT(S20, "";"" & CHAR(10)), $A:$AO, 41, FALSE)))))"),"")
AO21: =IFERROR(__xludf.DUMMYFUNCTION("IF(ISBLANK(A21),,IF(ISBLANK(S21), A21&"";"", TEXTJOIN(CHAR(10), TRUE, A21&"";"", ARRAYFORMULA(VLOOKUP(SPLIT(S21, "";"" & CHAR(10)), $A:$AO, 41, FALSE)))))"),"")
AO22: =IFERROR(__xludf.DUMMYFUNCTION("IF(ISBLANK(A22),,IF(ISBLANK(S22), A22&"";"", TEXTJOIN(CHAR(10), TRUE, A22&"";"", ARRAYFORMULA(VLOOKUP(SPLIT(S22, "";"" & CHAR(10)), $A:$AO, 41, FALSE)))))"),"")
AO23: =IFERROR(__xludf.DUMMYFUNCTION("IF(ISBLANK(A23),,IF(ISBLANK(S23), A23&"";"", TEXTJOIN(CHAR(10), TRUE, A23&"";"", ARRAYFORMULA(VLOOKUP(SPLIT(S23, "";"" & CHAR(10)), $A:$AO, 41, FALSE)))))"),"")
AO24: =IFERROR(__xludf.DUMMYFUNCTION("IF(ISBLANK(A24),,IF(ISBLANK(S24), A24&"";"", TEXTJOIN(CHAR(10), TRUE, A24&"";"", ARRAYFORMULA(VLOOKUP(SPLIT(S24, "";"" & CHAR(10)), $A:$AO, 41, FALSE)))))"),"")
AO25: =IFERROR(__xludf.DUMMYFUNCTION("IF(ISBLANK(A25),,IF(ISBLANK(S25), A25&"";"", TEXTJOIN(CHAR(10), TRUE, A25&"";"", ARRAYFORMULA(VLOOKUP(SPLIT(S25, "";"" & CHAR(10)), $A:$AO, 41, FALSE)))))"),"")
AO26: =IFERROR(__xludf.DUMMYFUNCTION("IF(ISBLANK(A26),,IF(ISBLANK(S26), A26&"";"", TEXTJOIN(CHAR(10), TRUE, A26&"";"", ARRAYFORMULA(VLOOKUP(SPLIT(S26, "";"" & CHAR(10)), $A:$AO, 41, FALSE)))))"),"")
AO27: =IFERROR(__xludf.DUMMYFUNCTION("IF(ISBLANK(A27),,IF(ISBLANK(S27), A27&"";"", TEXTJOIN(CHAR(10), TRUE, A27&"";"", ARRAYFORMULA(VLOOKUP(SPLIT(S27, "";"" & CHAR(10)), $A:$AO, 41, FALSE)))))"),"")
AO28: =IFERROR(__xludf.DUMMYFUNCTION("IF(ISBLANK(A28),,IF(ISBLANK(S28), A28&"";"", TEXTJOIN(CHAR(10), TRUE, A28&"";"", ARRAYFORMULA(VLOOKUP(SPLIT(S28, "";"" & CHAR(10)), $A:$AO, 41, FALSE)))))"),"")
AO29: =IFERROR(__xludf.DUMMYFUNCTION("IF(ISBLANK(A29),,IF(ISBLANK(S29), A29&"";"", TEXTJOIN(CHAR(10), TRUE, A29&"";"", ARRAYFORMULA(VLOOKUP(SPLIT(S29, "";"" & CHAR(10)), $A:$AO, 41, FALSE)))))"),"")
AO30: =IFERROR(__xludf.DUMMYFUNCTION("IF(ISBLANK(A30),,IF(ISBLANK(S30), A30&"";"", TEXTJOIN(CHAR(10), TRUE, A30&"";"", ARRAYFORMULA(VLOOKUP(SPLIT(S30, "";"" & CHAR(10)), $A:$AO, 41, FALSE)))))"),"")
AO31: =IFERROR(__xludf.DUMMYFUNCTION("IF(ISBLANK(A31),,IF(ISBLANK(S31), A31&"";"", TEXTJOIN(CHAR(10), TRUE, A31&"";"", ARRAYFORMULA(VLOOKUP(SPLIT(S31, "";"" & CHAR(10)), $A:$AO, 41, FALSE)))))"),"")
AO32: =IFERROR(__xludf.DUMMYFUNCTION("IF(ISBLANK(A32),,IF(ISBLANK(S32), A32&"";"", TEXTJOIN(CHAR(10), TRUE, A32&"";"", ARRAYFORMULA(VLOOKUP(SPLIT(S32, "";"" & CHAR(10)), $A:$AO, 41, FALSE)))))"),"")
A33: =IFERROR(__xludf.DUMMYFUNCTION("IMPORTRANGE(Settings!$A$2,""wbCircuits!A2:AM4000"")"),"Br") -> Br | B33: =IFERROR(__xludf.DUMMYFUNCTION("""COMPUTED_VALUE"""),"DHBA") -> DHBA | C33: =IFERROR(__xludf.DUMMYFUNCTION("""COMPUTED_VALUE"""),"brain") -> brain | D33: =IFERROR(__xludf.DUMMYFUNCTION("""COMPUTED_VALUE"""),2.0) -> 2 | E33: =IFERROR(__xludf.DUMMYFUNCTION("""COMPUTED_VALUE"""),"brain") -> brain | F33: =IFERROR(__xludf.DUMMYFUNCTION("""COMPUTED_VALUE"""),"Br") -> Br | S33: =IFERROR(__xludf.DUMMYFUNCTION("""COMPUTED_VALUE"""),"F; M; H") -> F; M; H | U33: =IFERROR(__xludf.DUMMYFUNCTION("""COMPUTED_VALUE"""),FALSE) -> FALSE | AB33: =IFERROR(__xludf.DUMMYFUNCTION("""COMPUTED_VALUE"""),"allen institute") -> allen institute | AC33: =IFERROR(__xludf.DUMMYFUNCTION("""COMPUTED_VALUE"""),"DHBA") -> DHBA | AO33: =IFERROR(__xludf.DUMMYFUNCTION("IF(ISBLANK(A33),,IF(ISBLANK(S33), A33&"";"", TEXTJOIN(CHAR(10), TRUE, A33&"";"", ARRAYFORMULA(VLOOKUP(SPLIT(S33, "";"" & CHAR(10)), $A:$AO, 41, FALSE)))))"),"#REF!") -> #REF!
A34: =IFERROR(__xludf.DUMMYFUNCTION("""COMPUTED_VALUE"""),"N") -> N | B34: =IFERROR(__xludf.DUMMYFUNCTION("""COMPUTED_VALUE"""),"collection") -> collection | C34: =IFERROR(__xludf.DUMMYFUNCTION("""COMPUTED_VALUE"""),"Oculomotor nuclei (ROI2)") -> Oculomotor nuclei (ROI2) | D34: =IFERROR(__xludf.DUMMYFUNCTION("""COMPUTED_VALUE"""),2.1) -> 2.1 | E34: =IFERROR(__xludf.DUMMYFUNCTION("""COMPUTED_VALUE"""),"") | F34: =IFERROR(__xludf.DUMMYFUNCTION("""COMPUTED_VALUE"""),"") | G34: =IFERROR(__xludf.DUMMYFUNCTION("""COMPUTED_VALUE"""),"") | H34: =IFERROR(__xludf.DUMMYFUNCTION("""COMPUTED_VALUE"""),"") | I34: =IFERROR(__xludf.DUMMYFUNCTION("""COMPUTED_VALUE"""),"") | J34: =IFERROR(__xludf.DUMMYFUNCTION("""COMPUTED_VALUE"""),"") | K34: =IFERROR(__xludf.DUMMYFUNCTION("""COMPUTED_VALUE"""),"") | L34: =IFERROR(__xludf.DUMMYFUNCTION("""COMPUTED_VALUE"""),"") | ... R34: =IFERROR(__xludf.DUMMYFUNCTION("""COMPUTED_VALUE"""),"") | S34: =IFERROR(__xludf.DUMMYFUNCTION("""COMPUTED_VALUE"""),"3N; 4N; 6N") -> 3N; 4N; 6N | U34: =IFERROR(__xludf.DUMMYFUNCTION("""COMPUTED_VALUE"""),FALSE) -> FALSE | W34: =IFERROR(__xludf.DUMMYFUNCTION("""COMPUTED_VALUE"""),"Excitatory") -> Excitatory | Y34: =IFERROR(__xludf.DUMMYFUNCTION("""COMPUTED_VALUE"""),"imort from Oculomotor.bra") -> imort from Oculomotor.bra | AB34: =IFERROR(__xludf.DUMMYFUNCTION("""COMPUTED_VALUE"""),"Yoshimasa Tawatsuji") -> Yoshimasa Tawatsuji | AC34: =IFERROR(__xludf.DUMMYFUNCTION("""COMPUTED_VALUE"""),"YT20Oculomotor") -> YT20Oculomotor | AO34: =IFERROR(__xludf.DUMMYFUNCTION("IF(ISBLANK(A34),,IF(ISBLANK(S34), A34&"";"", TEXTJOIN(CHAR(10), TRUE, A34&"";"", ARRAYFORMULA(VLOOKUP(SPLIT(S34, "";"" & CHAR(10)), $A:$AO, 41, FALSE)))))"),"N; 3N; 3N_IR; 3N_IO; 3N_SR; 3N_MR; 4N; 6N; AIN; MNs;") -> N; 3N; 3N_IR; 3N_IO; 3N_SR; 3N_MR; 4N; 6N; AIN; MNs;
A35: =IFERROR(__xludf.DUMMYFUNCTION("""COMPUTED_VALUE"""),"BN_out") -> BN_out | B35: =IFERROR(__xludf.DUMMYFUNCTION("""COMPUTED_VALUE"""),"collection") -> collection | C35: =IFERROR(__xludf.DUMMYFUNCTION("""COMPUTED_VALUE"""),"output of basal ganglia") -> output of basal ganglia | D35: =IFERROR(__xludf.DUMMYFUNCTION("""COMPUTED_VALUE"""),2.1) -> 2.1 | E35: =IFERROR(__xludf.DUMMYFUNCTION("""COMPUTED_VALUE"""),"") | F35: =IFERROR(__xludf.DUMMYFUNCTION("""COMPUTED_VALUE"""),"") | G35: =IFERROR(__xludf.DUMMYFUNCTION("""COMPUTED_VALUE"""),"") | H35: =IFERROR(__xludf.DUMMYFUNCTION("""COMPUTED_VALUE"""),"") | I35: =IFERROR(__xludf.DUMMYFUNCTION("""COMPUTED_VALUE"""),"") | J35: =IFERROR(__xludf.DUMMYFUNCTION("""COMPUTED_VALUE"""),"") | K35: =IFERROR(__xludf.DUMMYFUNCTION("""COMPUTED_VALUE"""),"") | L35: =IFERROR(__xludf.DUMMYFUNCTION("""COMPUTED_VALUE"""),"") | ... R35: =IFERROR(__xludf.DUMMYFUNCTION("""COMPUTED_VALUE"""),"") | S35: =IFERROR(__xludf.DUMMYFUNCTION("""COMPUTED_VALUE"""),"GPi; SNR") -> GPi; SNR | U35: =IFERROR(__xludf.DUMMYFUNCTION("""COMPUTED_VALUE"""),FALSE) -> FALSE | Y35: =IFERROR(__xludf.DUMMYFUNCTION("""COMPUTED_VALUE"""),"principal basal ganglia output for control of limb movement. Given that the BG send inhibitory outputs via the GPm and SNr to the brainstem, particularly the MLR that includes the PPTg (Ce- bria ́ n et al., 2005; Parent and De Bellefeuille, 1982; Roseber"&"ry et al., 2016), we further examined the impact of GPm outputs to PPTg (Figure S9A). Photoactivation of GPm inputs to the brain- stem enhanced rotation behavior (Figure S9B; Movie S4), a phenotype induced by hemispheric activation of locomotion. In addit"&"ion, no significant changes in rigidity or hypokinesia were evident (Figures S9C and S9D Movie S4). These results indicate that the multiple motor abnormalities induced by photostimula- tion of GPm inputs to VL are not due to inhibition of the brainstem n"&"eurons that also receive GPm inputs. [Kim, 2017] GPm and SNr neurons send descending projections to the thal- amus and brainstem with different spatial patterns. While the SNr sends more inputs to the MLR regions of the brainstem, GPm axons project heavi"&"ly to the VL (Figure S1) (Cebria ́n et al., 2005; Hikosaka et al., 2000; Kreitzer and Malenka, 2008; Parent et al., 2001). The SNr-MLR pathway is reported to exert a strong impact on locomotion through modulating glutamatergic neu- rons in the MLR (Antal "&"et al., 2014; Roseberry et al., 2016; Stefani et al., 2007), which may explain the hypokinetic state observed in BG-related disorders. Here, we have shown that GPm input to the VL thalamus has a stronger impact on motor function than SNr input (Figure S2)"&". Consistent with this finding, an earlier study reported that SNr does not induce rebound excitation with hyperpolarization in a thalamic slice in vitro (Edgerton and Jaeger, 2014). [Kim, 2017] it is plausible that while the SNr-MRL pathway modulates lo"&"comotion activity, the GPm-VL pathway effectively terminates actions requiring locomotion by inducing excitatory firing in the thalamus. [Kim, 2017]") -> principal basal ganglia output for control of limb movement. Given that the BG send inhibitory outputs via the GPm and SNr to the brainstem, particularly the MLR that includes the PPTg (Ce- bria ́ n et al., 2005; Parent and De Bellefeuille, 1982; Roseberry et al., 2016), we further examined the impact of GPm outputs to PPTg (Figure S9A). Photoactivation of GPm inputs to the brain- stem enhanced rotation behavior (Figure S9B; Movie S4), a phenotype induced by hemispheric activation of locomotion. In addition, no significant changes in rigidity or hypokinesia were evident (Figures S9C and S9D Movie S4). These results indicate that the multiple motor abnormalities induced by photostimula- tion of GPm inputs to VL are not due to inhibition of the brainstem neurons that also receive GPm inputs. [Kim, 2017] GPm and SNr neurons send descending projections to the thal- amus and brainstem with different spatial patterns. While the SNr sends more inputs to the MLR regions of the brainstem, GPm axons project heavily to the VL (Figure S1) (Cebria ́n et al., 2005; Hikosaka et al., 2000; Kreitzer and Malenka, 2008; Parent et al., 2001). The SNr-MLR pathway is reported to exert a strong impact on locomotion through modulating glutamatergic neu- rons in the MLR (Antal et al., 2014; Roseberry et al., 2016; Stefani et al., 2007), which may explain the hypokinetic state observed in BG-related disorders. Here, we have shown that GPm input to the VL thalamus has a stronger impact on motor function than SNr input (Figure S2). Consistent with this finding, an earlier study reported that SNr does not induce rebound excitation with hyperpolarization in a thalamic slice in vitro (Edgerton and Jaeger, 2014). [Kim, 2017] it is plausible that while the SNr-MRL pathway modulates locomotion activity, the GPm-VL pathway effectively terminates actions requiring locomotion by inducing excitatory firing in the thalamus. [Kim, 2017] | AB35: =IFERROR(__xludf.DUMMYFUNCTION("""COMPUTED_VALUE"""),"Yuske Shibata") -> Yuske Shibata | AC35: =IFERROR(__xludf.DUMMYFUNCTION("""COMPUTED_VALUE"""),"YS21BgLoop") -> YS21BgLoop | AO35: =IFERROR(__xludf.DUMMYFUNCTION("IF(ISBLANK(A35),,IF(ISBLANK(S35), A35&"";"", TEXTJOIN(CHAR(10), TRUE, A35&"";"", ARRAYFORMULA(VLOOKUP(SPLIT(S35, "";"" & CHAR(10)), $A:$AO, 41, FALSE)))))"),"BN_out; GPi; GPic; GPip; SNR;") -> BN_out; GPi; GPic; GPip; SNR;
